Workbook
Name COD: WACC!$J$58
Name COE: WACC!$J$56
Name Cost_of_Debt: WACC!$J$58
Name Taper_rate: WACC!$C$17
Name Tax_rate: WACC!$C$21
Name UPDATE: 'Data Sheet'!$E$1
Name WACC: WACC!$J$61

Sheet HistoricalFS
B2: ='Dupont Analysis'!B3 -> TRENT LTD
B3: ='Dupont Analysis'!B4 -> ( TRENT | BSE Code: 500251)
B5: ₹ in Crores
B6: ="Historical Financial Statement - "&'Data Sheet'!B1 -> Historical Financial Statement - TRENT LTD
B7: Years | C7: ='Data Sheet'!B16 -> 42460 | D7: ='Data Sheet'!C16 -> 42825 | E7: ='Data Sheet'!D16 -> 43190 | F7: ='Data Sheet'!E16 -> 43555 | G7: ='Data Sheet'!F16 -> 43921 | H7: ='Data Sheet'!G16 -> 44286 | I7: ='Data Sheet'!H16 -> 44651 | J7: ='Data Sheet'!I16 -> 45016 | ... L7: ='Data Sheet'!K16 -> 45747 | M7: LTM
A9: # | B9: Income Statement
B10: Sales | C10: =IFERROR('Data Sheet'!B17,0) -> 1686.17 | D10: =IFERROR('Data Sheet'!C17,0) -> 1812.44 | E10: =IFERROR('Data Sheet'!D17,0) -> 2157.46 | F10: =IFERROR('Data Sheet'!E17,0) -> 2630.24 | G10: =IFERROR('Data Sheet'!F17,0) -> 3485.98 | H10: =IFERROR('Data Sheet'!G17,0) -> 2592.96 | I10: =IFERROR('Data Sheet'!H17,0) -> 4498.02 | J10: =IFERROR('Data Sheet'!I17,0) -> 8242.02 | ... L10: =IFERROR('Data Sheet'!K17,0) -> 17134.61 | M10: =IFERROR(SUM('Data Sheet'!H42:K42),0) -> 19263.16
B11: Sales Growth | C11: - | D11: =D10/C10-1 -> 0.074885688 | E11: =E10/D10-1 -> 0.19036216 | F11: =F10/E10-1 -> 0.21913732 | G11: =G10/F10-1 -> 0.32534674 | H11: =H10/G10-1 -> -0.25617473 | I11: =I10/H10-1 -> 0.73470474 | J11: =J10/I10-1 -> 0.83236624 | K11: =K10/J10-1 -> 0.50146566 | ... M11: =M10/L10-1 -> 0.12422518
B13: COGS | C13: =IFERROR(SUM('Data Sheet'!B18,-'Data Sheet'!B19,'Data Sheet'!B20:B21),0) -> 920.95 | D13: =IFERROR(SUM('Data Sheet'!C18,-'Data Sheet'!C19,'Data Sheet'!C20:C21),0) -> 1014.55 | E13: =IFERROR(SUM('Data Sheet'!D18,-'Data Sheet'!D19,'Data Sheet'!D20:D21),0) -> 1175.04 | F13: =IFERROR(SUM('Data Sheet'!E18,-'Data Sheet'!E19,'Data Sheet'!E20:E21),0) -> 1492.71 | G13: =IFERROR(SUM('Data Sheet'!F18,-'Data Sheet'!F19,'Data Sheet'!F20:F21),0) -> 2045.9 | H13: =IFERROR(SUM('Data Sheet'!G18,-'Data Sheet'!G19,'Data Sheet'!G20:G21),0) -> 1675.41 | I13: =IFERROR(SUM('Data Sheet'!H18,-'Data Sheet'!H19,'Data Sheet'!H20:H21),0) -> 2680.57 | J13: =IFERROR(SUM('Data Sheet'!I18,-'Data Sheet'!I19,'Data Sheet'!I20:I21),0) -> 5076.01 | ... L13: =IFERROR(SUM('Data Sheet'!K18,-'Data Sheet'!K19,'Data Sheet'!K20:K21),0) -> 10408.8 | M13: =IFERROR(SUM('Data Sheet'!H43:K43),0) -> 15867.34
B14: COGS % Sales | C14: =C13/C10 -> 0.54617862 | D14: =D13/D10 -> 0.55977025 | E14: =E13/E10 -> 0.54464046 | F14: =F13/F10 -> 0.56751855 | G14: =G13/G10 -> 0.58689379 | H14: =H13/H10 -> 0.646138 | I14: =I13/I10 -> 0.59594444 | J14: =J13/J10 -> 0.61586965 | ... M14: =M13/M10 -> 0.82371428
B16: Gross Profit | C16: =C10-C13 -> 765.22 | D16: =D10-D13 -> 797.89 | E16: =E10-E13 -> 982.42 | F16: =F10-F13 -> 1137.53 | G16: =G10-G13 -> 1440.08 | H16: =H10-H13 -> 917.55 | I16: =I10-I13 -> 1817.45 | J16: =J10-J13 -> 3166.01 | ... M16: =M10-M13 -> 3395.82
B17: Gross Margin | C17: =C16/C10 -> 0.45382138 | D17: =D16/D10 -> 0.44022975 | E17: =E16/E10 -> 0.45535954 | F17: =F16/F10 -> 0.43248145 | G17: =G16/G10 -> 0.41310621 | H17: =H16/H10 -> 0.353862 | I17: =I16/I10 -> 0.40405556 | J17: =J16/J10 -> 0.38413035 | ... M17: =M16/M10 -> 0.17628572
B19: Selling & General Expenses | C19: =IFERROR(SUM('Data Sheet'!B22:B24),0) -> 675.46 | D19: =IFERROR(SUM('Data Sheet'!C22:C24),0) -> 664.36 | E19: =IFERROR(SUM('Data Sheet'!D22:D24),0) -> 773.92 | F19: =IFERROR(SUM('Data Sheet'!E22:E24),0) -> 896.89 | G19: =IFERROR(SUM('Data Sheet'!F22:F24),0) -> 911.11 | H19: =IFERROR(SUM('Data Sheet'!G22:G24),0) -> 803.68 | I19: =IFERROR(SUM('Data Sheet'!H22:H24),0) -> 1222.73 | J19: =IFERROR(SUM('Data Sheet'!I22:I24),0) -> 2051.86 | ... L19: =IFERROR(SUM('Data Sheet'!K22:K24),0) -> 3905.85 | M19: =IFERROR(SUM('Data Sheet'!L23:L24),0) -> 0
B20: S&G Exp % Sales | C20: =C19/C10 -> 0.40058832 | D20: =D19/D10 -> 0.36655558 | E20: =E19/E10 -> 0.35871812 | F20: =F19/F10 -> 0.3409917 | G20: =G19/G10 -> 0.26136409 | H20: =H19/H10 -> 0.30994693 | I20: =I19/I10 -> 0.27183739 | J20: =J19/J10 -> 0.24895111 | ... M20: =M19/M10 -> 0 | N20: =IFERROR((HistoricalFS!C22-HistoricalFS!C31)/(SUM(HistoricalFS!C57:C59)),0) -> 0.022545985
B22: EBITDA | C22: =C16-C19 -> 89.76 | D22: =D16-D19 -> 133.53 | E22: =E16-E19 -> 208.5 | F22: =F16-F19 -> 240.64 | G22: =G16-G19 -> 528.97 | H22: =H16-H19 -> 113.87 | I22: =I16-I19 -> 594.72 | J22: =J16-J19 -> 1114.15 | ... M22: =M16-M19 -> 3395.82 | V22: =I40+I37+I25 -> 269.88 | W22: =J40+J37+J25 -> 705.16
B23: EBITDA Margin | C23: =C22/C10 -> 0.053233067 | D23: =D22/D10 -> 0.073674163 | E23: =E22/E10 -> 0.096641421 | F23: =F22/F10 -> 0.09148975 | G23: =G22/G10 -> 0.15174212 | H23: =H22/H10 -> 0.043915062 | I23: =I22/I10 -> 0.13221818 | J23: =J22/J10 -> 0.13517924 | ... M23: =M22/M10 -> 0.17628572
B25: Depreciation | C25: =IFERROR('Data Sheet'!B26,0) -> 38.59 | D25: =IFERROR('Data Sheet'!C26,0) -> 41.29 | E25: =IFERROR('Data Sheet'!D26,0) -> 45.53 | F25: =IFERROR('Data Sheet'!E26,0) -> 51.67 | G25: =IFERROR('Data Sheet'!F26,0) -> 247.24 | H25: =IFERROR('Data Sheet'!G26,0) -> 257.3 | I25: =IFERROR('Data Sheet'!H26,0) -> 310.82 | J25: =IFERROR('Data Sheet'!I26,0) -> 493.69 | ... M25: =IFERROR('Data Sheet'!L26,0) -> 0
B26: Depreciation%Sales | C26: =C25/C10 -> 0.022886186 | D26: =D25/D10 -> 0.022781444 | E26: =E25/E10 -> 0.02110352 | F26: =F25/F10 -> 0.019644595 | G26: =G25/G10 -> 0.070924102 | H26: =H25/H10 -> 0.099230223 | I26: =I25/I10 -> 0.069101516 | J26: =J25/J10 -> 0.059899151 | ... M26: =M25/M10 -> 0
B28: EBIT | C28: =C22-C25 -> 51.17 | D28: =D22-D25 -> 92.24 | E28: =E22-E25 -> 162.97 | F28: =F22-F25 -> 188.97 | G28: =G22-G25 -> 281.73 | H28: =H22-H25 -> -143.43 | I28: =I22-I25 -> 283.9 | J28: =J22-J25 -> 620.46 | ... M28: =M22-M25 -> 3395.82
B29: EBIT margin | C29: =C28/C10 -> 0.030346881 | D29: =D28/D10 -> 0.050892719 | E29: =E28/E10 -> 0.075537901 | F29: =F28/F10 -> 0.071845155 | G29: =G28/G10 -> 0.08081802 | H29: =H28/H10 -> -0.055315161 | I29: =I28/I10 -> 0.06311666 | J29: =J28/J10 -> 0.075280089 | ... M29: =M28/M10 -> 0.17628572
B31: Intrest | C31: =IFERROR('Data Sheet'!B27,0) -> 47.73 | D31: =IFERROR('Data Sheet'!C27,0) -> 45.55 | E31: =IFERROR('Data Sheet'!D27,0) -> 43.78 | F31: =IFERROR('Data Sheet'!E27,0) -> 50.64 | G31: =IFERROR('Data Sheet'!F27,0) -> 263.37 | H31: =IFERROR('Data Sheet'!G27,0) -> 260.79 | I31: =IFERROR('Data Sheet'!H27,0) -> 324.84 | J31: =IFERROR('Data Sheet'!I27,0) -> 408.99 | ... M31: =IFERROR('Data Sheet'!L27,0) -> 0
B32: Intrest%Sales | C32: =C31/C10 -> 0.028306754 | D32: =D31/D10 -> 0.025131866 | E32: =E31/E10 -> 0.020292381 | F32: =F31/F10 -> 0.019252996 | G32: =G31/G10 -> 0.075551208 | H32: =H31/H10 -> 0.10057618 | I32: =I31/I10 -> 0.072218443 | J32: =J31/J10 -> 0.049622544 | ... M32: =M31/M10 -> 0
B34: EBT | C34: =C28-C31 -> 3.44 | D34: =D28-D31 -> 46.69 | E34: =E28-E31 -> 119.19 | F34: =F28-F31 -> 138.33 | G34: =G28-G31 -> 18.36 | H34: =H28-H31 -> -404.22 | I34: =I28-I31 -> -40.94 | J34: =J28-J31 -> 211.47 | ... M34: =M28-M31 -> 3395.82
B35: EBT % Sales | C35: =C34/C10 -> 0.0020401264 | D35: =D34/D10 -> 0.025760853 | E35: =E34/E10 -> 0.05524552 | F35: =F34/F10 -> 0.052592159 | G35: =G34/G10 -> 0.0052668116 | H35: =H34/H10 -> -0.15589134 | I35: =I34/I10 -> -0.0091017826 | J35: =J34/J10 -> 0.025657545 | ... M35: =M34/M10 -> 0.17628572
B37: Tax | C37: =IFERROR('Data Sheet'!B29,0) -> 34.71 | D37: =IFERROR('Data Sheet'!C29,0) -> 43.05 | E37: =IFERROR('Data Sheet'!D29,0) -> 59.62 | F37: =IFERROR('Data Sheet'!E29,0) -> 73.61 | G37: =IFERROR('Data Sheet'!F29,0) -> 59.01 | H37: =IFERROR('Data Sheet'!G29,0) -> -23.69 | I37: =IFERROR('Data Sheet'!H29,0) -> 76.62 | J37: =IFERROR('Data Sheet'!I29,0) -> 158.44 | ... L37: =IFERROR('Data Sheet'!K29,0) -> 495.33 | M37: =IFERROR(SUM('Data Sheet'!H48:K48),0) -> 513.53
B38: Effective tax Rate | C38: =C37/C34 -> 10.090116 | D38: =D37/D34 -> 0.92203898 | E38: =E37/E34 -> 0.50020975 | F38: =F37/F34 -> 0.5321333 | G38: =G37/G34 -> 3.2140523 | H38: =H37/H34 -> 0.058606699 | I38: =I37/I34 -> -1.8715193 | J38: =J37/J34 -> 0.74923157 | ... M38: =M37/M34 -> 0.15122415
B40: Net Profit | C40: =IFERROR(C34-C37,0) -> -31.27 | D40: =IFERROR(D34-D37,0) -> 3.64 | E40: =IFERROR(E34-E37,0) -> 59.57 | F40: =IFERROR(F34-F37,0) -> 64.72 | G40: =IFERROR(G34-G37,0) -> -40.65 | H40: =IFERROR(H34-H37,0) -> -380.53 | I40: =IFERROR(I34-I37,0) -> -117.56 | J40: =IFERROR(J34-J37,0) -> 53.03 | ... M40: =IFERROR(M34-M37,0) -> 2882.29
B41: Net profit Margin | C41: =C40/C10 -> -0.018544987 | D41: =D40/D10 -> 0.0020083423 | E41: =E40/E10 -> 0.027611172 | F41: =F40/F10 -> 0.02460612 | G41: =G40/G10 -> -0.011660996 | H41: =H40/H10 -> -0.14675506 | I41: =I40/I10 -> -0.026135944 | J41: =J40/J10 -> 0.0064341023 | ... M41: =M40/M10 -> 0.14962706
B43: No. of Equity Shares | C43: ='Data Sheet'!B100 -> 33.23 | D43: ='Data Sheet'!C100 -> 33.23 | E43: ='Data Sheet'!D100 -> 33.23 | F43: ='Data Sheet'!E100 -> 33.23 | G43: ='Data Sheet'!F100 -> 35.55 | H43: ='Data Sheet'!G100 -> 35.55 | I43: ='Data Sheet'!H100 -> 35.55 | J43: ='Data Sheet'!I100 -> 35.55 | ... L43: ='Data Sheet'!K100 -> 35.55 | M43: =L43 -> 35.55
B45: EPS | C45: =IFERROR(C40/C43,0) -> -0.94101715 | D45: =IFERROR(D40/D43,0) -> 0.10953957 | E45: =IFERROR(E40/E43,0) -> 1.7926572 | F45: =IFERROR(F40/F43,0) -> 1.9476377 | G45: =IFERROR(G40/G43,0) -> -1.1434599 | H45: =IFERROR(H40/H43,0) -> -10.704079 | I45: =IFERROR(I40/I43,0) -> -3.3068917 | J45: =IFERROR(J40/J43,0) -> 1.4917018 | ... M45: =IFERROR(M40/M43,0) -> 81.077075
B46: EPS Growth % | C46: - | D46: =IFERROR(D45/C45-1,0) -> -1.1164055 | E46: =IFERROR(E45/D45-1,0) -> 15.365385 | F46: =IFERROR(F45/E45-1,0) -> 0.086452913 | G46: =IFERROR(G45/F45-1,0) -> -1.5871009 | H46: =IFERROR(H45/G45-1,0) -> 8.3611316 | I46: =IFERROR(I45/H45-1,0) -> -0.69106247 | J46: =IFERROR(J45/I45-1,0) -> -1.4510888 | K46: =IFERROR(K45/J45-1,0) -> 8.2127098 | ... M46: =IFERROR(M45/L45-1,0) -> 1.3445642
B48: Divided per Share | C48: =IFERROR('Data Sheet'!B31/HistoricalFS!C43,0) -> 0.90009028 | D48: =IFERROR('Data Sheet'!C31/HistoricalFS!D43,0) -> 1 | E48: =IFERROR('Data Sheet'!D31/HistoricalFS!E43,0) -> 1.1498646 | F48: =IFERROR('Data Sheet'!E31/HistoricalFS!F43,0) -> 1.3000301 | G48: =IFERROR('Data Sheet'!F31/HistoricalFS!G43,0) -> 1 | H48: =IFERROR('Data Sheet'!G31/HistoricalFS!H43,0) -> 0.6 | I48: =IFERROR('Data Sheet'!H31/HistoricalFS!I43,0) -> 1.7001406 | J48: =IFERROR('Data Sheet'!I31/HistoricalFS!J43,0) -> 2.2 | ... M48: =IFERROR('Data Sheet'!L31/HistoricalFS!M43,0) -> 0
B49: Divided Payout Ratio | C49: =IFERROR(C48/C45,0) -> -0.95650783 | D49: =IFERROR(D48/D45,0) -> 9.1291209 | E49: =IFERROR(E48/E45,0) -> 0.64143025 | F49: =IFERROR(F48/F45,0) -> 0.66749073 | G49: =IFERROR(G48/G45,0) -> -0.87453875 | H49: =IFERROR(H48/H45,0) -> -0.056053399 | I49: =IFERROR(I48/I45,0) -> -0.51412045 | J49: =IFERROR(J48/J45,0) -> 1.4748256 | ... M49: =IFERROR(M48/M45,0) -> 0
B51: Retained Earning | C51: =IFERROR(IF(C45>C48,1-C49,0),0) -> 0 | D51: =IFERROR(IF(D45>D48,1-D49,0),0) -> 0 | E51: =IFERROR(IF(E45>E48,1-E49,0),0) -> 0.35856975 | F51: =IFERROR(IF(F45>F48,1-F49,0),0) -> 0.33250927 | G51: =IFERROR(IF(G45>G48,1-G49,0),0) -> 0 | H51: =IFERROR(IF(H45>H48,1-H49,0),0) -> 0 | I51: =IFERROR(IF(I45>I48,1-I49,0),0) -> 0 | J51: =IFERROR(IF(J45>J48,1-J49,0),0) -> 0 | ... M51: =IFERROR(IF(M45>M48,1-M49,0),0) -> 1
A53: # | B53: Balance Sheet
B55: Particulars | C55: =C7 -> 42460 | D55: =D7 -> 42825 | E55: =E7 -> 43190 | F55: =F7 -> 43555 | G55: =G7 -> 43921 | H55: =H7 -> 44286 | I55: =I7 -> 44651 | J55: =J7 -> 45016 | ... L55: =L7 -> 45747
B57: Equity Share Capital | C57: =IFERROR('Data Sheet'!B57,0) -> 33.23 | D57: =IFERROR('Data Sheet'!C57,0) -> 33.23 | E57: =IFERROR('Data Sheet'!D57,0) -> 33.23 | F57: =IFERROR('Data Sheet'!E57,0) -> 33.23 | G57: =IFERROR('Data Sheet'!F57,0) -> 35.55 | H57: =IFERROR('Data Sheet'!G57,0) -> 35.55 | I57: =IFERROR('Data Sheet'!H57,0) -> 35.55 | J57: =IFERROR('Data Sheet'!I57,0) -> 35.55 | ... L57: =IFERROR('Data Sheet'!K57,0) -> 35.55
B58: Reserves | C58: =IFERROR('Data Sheet'!B58,0) -> 1431.16 | D58: =IFERROR('Data Sheet'!C58,0) -> 1514.46 | E58: =IFERROR('Data Sheet'!D58,0) -> 1562.14 | F58: =IFERROR('Data Sheet'!E58,0) -> 1613.28 | G58: =IFERROR('Data Sheet'!F58,0) -> 2352.22 | H58: =IFERROR('Data Sheet'!G58,0) -> 2277.48 | I58: =IFERROR('Data Sheet'!H58,0) -> 2328.45 | J58: =IFERROR('Data Sheet'!I58,0) -> 2559.94 | ... L58: =IFERROR('Data Sheet'!K58,0) -> 5426.19
B59: Borrowings | C59: =IFERROR('Data Sheet'!B59,0) -> 399.8 | D59: =IFERROR('Data Sheet'!C59,0) -> 391.74 | E59: =IFERROR('Data Sheet'!D59,0) -> 391.43 | F59: =IFERROR('Data Sheet'!E59,0) -> 494.14 | G59: =IFERROR('Data Sheet'!F59,0) -> 299.74 | H59: =IFERROR('Data Sheet'!G59,0) -> 299.93 | I59: =IFERROR('Data Sheet'!H59,0) -> 4725.36 | J59: =IFERROR('Data Sheet'!I59,0) -> 4464.14 | ... L59: =IFERROR('Data Sheet'!K59,0) -> 2237.19
B60: Other Liabilities | C60: =IFERROR('Data Sheet'!B60,0) -> 292.4 | D60: =IFERROR('Data Sheet'!C60,0) -> 282.82 | E60: =IFERROR('Data Sheet'!D60,0) -> 349.06 | F60: =IFERROR('Data Sheet'!E60,0) -> 418.11 | G60: =IFERROR('Data Sheet'!F60,0) -> 2819.17 | H60: =IFERROR('Data Sheet'!G60,0) -> 3110.77 | I60: =IFERROR('Data Sheet'!H60,0) -> 636.66 | J60: =IFERROR('Data Sheet'!I60,0) -> 1021.9 | ... L60: =IFERROR('Data Sheet'!K60,0) -> 1720.71
B61: Total Liabilities | C61: =IFERROR('Data Sheet'!B61,0) -> 2156.59 | D61: =IFERROR('Data Sheet'!C61,0) -> 2222.25 | E61: =IFERROR('Data Sheet'!D61,0) -> 2335.86 | F61: =IFERROR('Data Sheet'!E61,0) -> 2558.76 | G61: =IFERROR('Data Sheet'!F61,0) -> 5506.68 | H61: =IFERROR('Data Sheet'!G61,0) -> 5723.73 | I61: =IFERROR('Data Sheet'!H61,0) -> 7726.02 | J61: =IFERROR('Data Sheet'!I61,0) -> 8081.53 | ... L61: =IFERROR('Data Sheet'!K61,0) -> 9419.64
B63: Fixed Assets Net Block | C63: =IFERROR('Data Sheet'!B62,0) -> 476.79 | D63: =IFERROR('Data Sheet'!C62,0) -> 548.71 | E63: =IFERROR('Data Sheet'!D62,0) -> 612.53 | F63: =IFERROR('Data Sheet'!E62,0) -> 662.18 | G63: =IFERROR('Data Sheet'!F62,0) -> 2738.43 | H63: =IFERROR('Data Sheet'!G62,0) -> 3053.82 | I63: =IFERROR('Data Sheet'!H62,0) -> 4686.71 | J63: =IFERROR('Data Sheet'!I62,0) -> 4526.95 | ... L63: =IFERROR('Data Sheet'!K62,0) -> 3895.13
B64: Capital Working in Progess | C64: =IFERROR('Data Sheet'!B63,0) -> 54.86 | D64: =IFERROR('Data Sheet'!C63,0) -> 5.48 | E64: =IFERROR('Data Sheet'!D63,0) -> 9.59 | F64: =IFERROR('Data Sheet'!E63,0) -> 87.18 | G64: =IFERROR('Data Sheet'!F63,0) -> 23.32 | H64: =IFERROR('Data Sheet'!G63,0) -> 107.98 | I64: =IFERROR('Data Sheet'!H63,0) -> 104.72 | J64: =IFERROR('Data Sheet'!I63,0) -> 101.72 | ... L64: =IFERROR('Data Sheet'!K63,0) -> 179.5
B65: Investments | C65: =IFERROR('Data Sheet'!B64,0) -> 1066.97 | D65: =IFERROR('Data Sheet'!C64,0) -> 1079.96 | E65: =IFERROR('Data Sheet'!D64,0) -> 1022.88 | F65: =IFERROR('Data Sheet'!E64,0) -> 882.83 | G65: =IFERROR('Data Sheet'!F64,0) -> 1514.78 | H65: =IFERROR('Data Sheet'!G64,0) -> 1487.29 | I65: =IFERROR('Data Sheet'!H64,0) -> 1283.72 | J65: =IFERROR('Data Sheet'!I64,0) -> 1109.87 | ... L65: =IFERROR('Data Sheet'!K64,0) -> 1480.25
B66: Other Assets | C66: =IFERROR('Data Sheet'!B65-SUM('Data Sheet'!B67:B69),0) -> 238.89 | D66: =IFERROR('Data Sheet'!C65-SUM('Data Sheet'!C67:C69),0) -> 242.54 | E66: =IFERROR('Data Sheet'!D65-SUM('Data Sheet'!D67:D69),0) -> 298.18 | F66: =IFERROR('Data Sheet'!E65-SUM('Data Sheet'!E67:E69),0) -> 358.79 | G66: =IFERROR('Data Sheet'!F65-SUM('Data Sheet'!F67:F69),0) -> 543.81 | H66: =IFERROR('Data Sheet'!G65-SUM('Data Sheet'!G67:G69),0) -> 544.01 | I66: =IFERROR('Data Sheet'!H65-SUM('Data Sheet'!H67:H69),0) -> 678.86 | J66: =IFERROR('Data Sheet'!I65-SUM('Data Sheet'!I67:I69),0) -> 861.14 | ... L66: =IFERROR('Data Sheet'!K65-SUM('Data Sheet'!K67:K69),0) -> 1416.92
B67: Total Non Current Assets | C67: =SUM(C63:C66) -> 1837.51 | D67: =SUM(D63:D66) -> 1876.69 | E67: =SUM(E63:E66) -> 1943.18 | F67: =SUM(F63:F66) -> 1990.98 | G67: =SUM(G63:G66) -> 4820.34 | H67: =SUM(H63:H66) -> 5193.1 | I67: =SUM(I63:I66) -> 6754.01 | J67: =SUM(J63:J66) -> 6599.68 | ... L67: =SUM(L63:L66) -> 6971.8
B69: Receivables | C69: =IFERROR('Data Sheet'!B67,0) -> 12.99 | D69: =IFERROR('Data Sheet'!C67,0) -> 5.92 | E69: =IFERROR('Data Sheet'!D67,0) -> 15.1 | F69: =IFERROR('Data Sheet'!E67,0) -> 16.54 | G69: =IFERROR('Data Sheet'!F67,0) -> 17.12 | H69: =IFERROR('Data Sheet'!G67,0) -> 20.77 | I69: =IFERROR('Data Sheet'!H67,0) -> 18.26 | J69: =IFERROR('Data Sheet'!I67,0) -> 34.39 | ... L69: =IFERROR('Data Sheet'!K67,0) -> 62.95
B70: Inventory | C70: =IFERROR('Data Sheet'!B68,0) -> 279.19 | D70: =IFERROR('Data Sheet'!C68,0) -> 305.36 | E70: =IFERROR('Data Sheet'!D68,0) -> 344.77 | F70: =IFERROR('Data Sheet'!E68,0) -> 497.01 | G70: =IFERROR('Data Sheet'!F68,0) -> 607.81 | H70: =IFERROR('Data Sheet'!G68,0) -> 428.39 | I70: =IFERROR('Data Sheet'!H68,0) -> 867.78 | J70: =IFERROR('Data Sheet'!I68,0) -> 1361.16 | ... L70: =IFERROR('Data Sheet'!K68,0) -> 2045.05
B71: Cash & Bank | C71: =IFERROR('Data Sheet'!B69,0) -> 26.9 | D71: =IFERROR('Data Sheet'!C69,0) -> 34.28 | E71: =IFERROR('Data Sheet'!D69,0) -> 32.81 | F71: =IFERROR('Data Sheet'!E69,0) -> 54.23 | G71: =IFERROR('Data Sheet'!F69,0) -> 61.41 | H71: =IFERROR('Data Sheet'!G69,0) -> 81.47 | I71: =IFERROR('Data Sheet'!H69,0) -> 85.97 | J71: =IFERROR('Data Sheet'!I69,0) -> 86.3 | ... L71: =IFERROR('Data Sheet'!K69,0) -> 339.84
B72: Total Current Assets | C72: =SUM(C69:C71) -> 319.08 | D72: =SUM(D69:D71) -> 345.56 | E72: =SUM(E69:E71) -> 392.68 | F72: =SUM(F69:F71) -> 567.78 | G72: =SUM(G69:G71) -> 686.34 | H72: =SUM(H69:H71) -> 530.63 | I72: =SUM(I69:I71) -> 972.01 | J72: =SUM(J69:J71) -> 1481.85 | ... L72: =SUM(L69:L71) -> 2447.84
B74: Total Assets | C74: =IFERROR(C72+C67,0) -> 2156.59 | D74: =IFERROR(D72+D67,0) -> 2222.25 | E74: =IFERROR(E72+E67,0) -> 2335.86 | F74: =IFERROR(F72+F67,0) -> 2558.76 | G74: =IFERROR(G72+G67,0) -> 5506.68 | H74: =IFERROR(H72+H67,0) -> 5723.73 | I74: =IFERROR(I72+I67,0) -> 7726.02 | J74: =IFERROR(J72+J67,0) -> 8081.53 | ... L74: =IFERROR(L72+L67,0) -> 9419.64
A76: # | B76: Check | C76: =C74=C61 -> TRUE | D76: =D74=D61 -> TRUE | E76: =E74=E61 -> TRUE | F76: =F74=F61 -> TRUE | G76: =G74=G61 -> TRUE | H76: =H74=H61 -> TRUE | I76: =I74=I61 -> TRUE | J76: =J74=J61 -> TRUE | ... L76: =L74=L61 -> TRUE
B78: Cash Flow Statement
B80: Operating Flow Activites
B81: =' Cash Flow Date'!B4 -> Profit from operations | C81: =IFERROR(' Cash Flow Date'!C4,0) -> 2848 | D81: =IFERROR(' Cash Flow Date'!D4,0) -> 3056 | E81: =IFERROR(' Cash Flow Date'!E4,0) -> 3274 | F81: =IFERROR(' Cash Flow Date'!F4,0) -> 3861 | G81: =IFERROR(' Cash Flow Date'!G4,0) -> 4380 | H81: =IFERROR(' Cash Flow Date'!H4,0) -> 4970 | I81: =IFERROR(' Cash Flow Date'!I4,0) -> 4957 | J81: =IFERROR(' Cash Flow Date'!J4,0) -> 6460 | ... L81: =IFERROR(' Cash Flow Date'!L4,0) -> 6390
B82: =' Cash Flow Date'!B5 -> Receivables | C82: =IFERROR(' Cash Flow Date'!C5,0) -> -146 | D82: =IFERROR(' Cash Flow Date'!D5,0) -> -475 | E82: =IFERROR(' Cash Flow Date'!E5,0) -> -483 | F82: =IFERROR(' Cash Flow Date'!F5,0) -> -205 | G82: =IFERROR(' Cash Flow Date'!G5,0) -> 160 | H82: =IFERROR(' Cash Flow Date'!H5,0) -> -849 | I82: =IFERROR(' Cash Flow Date'!I5,0) -> -1326 | J82: =IFERROR(' Cash Flow Date'!J5,0) -> -834 | ... L82: =IFERROR(' Cash Flow Date'!L5,0) -> 282
B83: =' Cash Flow Date'!B6 -> Inventory | C83: =IFERROR(' Cash Flow Date'!C6,0) -> 202 | D83: =IFERROR(' Cash Flow Date'!D6,0) -> -629 | E83: =IFERROR(' Cash Flow Date'!E6,0) -> -39 | F83: =IFERROR(' Cash Flow Date'!F6,0) -> -492 | G83: =IFERROR(' Cash Flow Date'!G6,0) -> -251 | H83: =IFERROR(' Cash Flow Date'!H6,0) -> -409 | I83: =IFERROR(' Cash Flow Date'!I6,0) -> -2354 | J83: =IFERROR(' Cash Flow Date'!J6,0) -> -56 | ... L83: =IFERROR(' Cash Flow Date'!L6,0) -> -805
B84: =' Cash Flow Date'!B7 -> Payables | C84: =IFERROR(' Cash Flow Date'!C7,0) -> 142 | D84: =IFERROR(' Cash Flow Date'!D7,0) -> 501 | E84: =IFERROR(' Cash Flow Date'!E7,0) -> 442 | F84: =IFERROR(' Cash Flow Date'!F7,0) -> 287 | G84: =IFERROR(' Cash Flow Date'!G7,0) -> -241 | H84: =IFERROR(' Cash Flow Date'!H7,0) -> 1143 | I84: =IFERROR(' Cash Flow Date'!I7,0) -> 644 | J84: =IFERROR(' Cash Flow Date'!J7,0) -> -539 | ... L84: =IFERROR(' Cash Flow Date'!L7,0) -> -160
B85: =' Cash Flow Date'!B8 -> Other WC items | C85: =IFERROR(' Cash Flow Date'!C8,0) -> 0 | D85: =IFERROR(' Cash Flow Date'!D8,0) -> 0 | E85: =IFERROR(' Cash Flow Date'!E8,0) -> 0 | F85: =IFERROR(' Cash Flow Date'!F8,0) -> 0 | G85: =IFERROR(' Cash Flow Date'!G8,0) -> 0 | H85: =IFERROR(' Cash Flow Date'!H8,0) -> -92 | I85: =IFERROR(' Cash Flow Date'!I8,0) -> 242 | J85: =IFERROR(' Cash Flow Date'!J8,0) -> 657 | ... L85: =IFERROR(' Cash Flow Date'!L8,0) -> 114
B86: =' Cash Flow Date'!B9 -> Working capital changes | C86: =IFERROR(' Cash Flow Date'!C9,0) -> 198 | D86: =IFERROR(' Cash Flow Date'!D9,0) -> -603 | E86: =IFERROR(' Cash Flow Date'!E9,0) -> -80 | F86: =IFERROR(' Cash Flow Date'!F9,0) -> -410 | G86: =IFERROR(' Cash Flow Date'!G9,0) -> -331 | H86: =IFERROR(' Cash Flow Date'!H9,0) -> -206 | I86: =IFERROR(' Cash Flow Date'!I9,0) -> -2795 | J86: =IFERROR(' Cash Flow Date'!J9,0) -> -772 | ... L86: =IFERROR(' Cash Flow Date'!L9,0) -> -570
B87: =' Cash Flow Date'!B10 -> Direct taxes | C87: =IFERROR(' Cash Flow Date'!C10,0) -> -802 | D87: =IFERROR(' Cash Flow Date'!D10,0) -> -925 | E87: =IFERROR(' Cash Flow Date'!E10,0) -> -1081 | F87: =IFERROR(' Cash Flow Date'!F10,0) -> -982 | G87: =IFERROR(' Cash Flow Date'!G10,0) -> -1011 | H87: =IFERROR(' Cash Flow Date'!H10,0) -> -1080 | I87: =IFERROR(' Cash Flow Date'!I10,0) -> -1176 | J87: =IFERROR(' Cash Flow Date'!J10,0) -> -1494 | ... L87: =IFERROR(' Cash Flow Date'!L10,0) -> -1396
B88: =' Cash Flow Date'!B3 -> Cash from Operating Activity - | C88: =SUM(C81:C87) -> 2442 | D88: =SUM(D81:D87) -> 925 | E88: =SUM(E81:E87) -> 2033 | F88: =SUM(F81:F87) -> 2059 | G88: =SUM(G81:G87) -> 2706 | H88: =SUM(H81:H87) -> 3477 | I88: =SUM(I81:I87) -> -1808 | J88: =SUM(J81:J87) -> 3422 | ... L88: =SUM(L81:L87) -> 3855
B90: Investing Activities
B91: =' Cash Flow Date'!B12 -> Fixed assets purchased | C91: =IFERROR(' Cash Flow Date'!C12,0) -> -817 | D91: =IFERROR(' Cash Flow Date'!D12,0) -> -684 | E91: =IFERROR(' Cash Flow Date'!E12,0) -> -1426 | F91: =IFERROR(' Cash Flow Date'!F12,0) -> -1151 | G91: =IFERROR(' Cash Flow Date'!G12,0) -> -404 | H91: =IFERROR(' Cash Flow Date'!H12,0) -> -282 | I91: =IFERROR(' Cash Flow Date'!I12,0) -> -551 | J91: =IFERROR(' Cash Flow Date'!J12,0) -> -1446 | ... L91: =IFERROR(' Cash Flow Date'!L12,0) -> -1830
B92: =' Cash Flow Date'!B13 -> Fixed assets sold | C92: =IFERROR(' Cash Flow Date'!C13,0) -> 15 | D92: =IFERROR(' Cash Flow Date'!D13,0) -> 17 | E92: =IFERROR(' Cash Flow Date'!E13,0) -> 17 | F92: =IFERROR(' Cash Flow Date'!F13,0) -> 17 | G92: =IFERROR(' Cash Flow Date'!G13,0) -> 37 | H92: =IFERROR(' Cash Flow Date'!H13,0) -> 28 | I92: =IFERROR(' Cash Flow Date'!I13,0) -> 40 | J92: =IFERROR(' Cash Flow Date'!J13,0) -> 26 | ... L92: =IFERROR(' Cash Flow Date'!L13,0) -> 10
B93: =' Cash Flow Date'!B14 -> Investments purchased | C93: =IFERROR(' Cash Flow Date'!C14,0) -> -282 | D93: =IFERROR(' Cash Flow Date'!D14,0) -> -153 | E93: =IFERROR(' Cash Flow Date'!E14,0) -> -320 | F93: =IFERROR(' Cash Flow Date'!F14,0) -> -573 | G93: =IFERROR(' Cash Flow Date'!G14,0) -> -25 | H93: =IFERROR(' Cash Flow Date'!H14,0) -> -140 | I93: =IFERROR(' Cash Flow Date'!I14,0) -> 0 | J93: =IFERROR(' Cash Flow Date'!J14,0) -> -146 | ... L93: =IFERROR(' Cash Flow Date'!L14,0) -> -1
B94: =' Cash Flow Date'!B15 -> Investments sold | C94: =IFERROR(' Cash Flow Date'!C15,0) -> 205 | D94: =IFERROR(' Cash Flow Date'!D15,0) -> 357 | E94: =IFERROR(' Cash Flow Date'!E15,0) -> 362 | F94: =IFERROR(' Cash Flow Date'!F15,0) -> 733 | G94: =IFERROR(' Cash Flow Date'!G15,0) -> 134 | H94: =IFERROR(' Cash Flow Date'!H15,0) -> 272 | I94: =IFERROR(' Cash Flow Date'!I15,0) -> 207 | J94: =IFERROR(' Cash Flow Date'!J15,0) -> 446 | ... L94: =IFERROR(' Cash Flow Date'!L15,0) -> 421
B95: =' Cash Flow Date'!B16 -> Interest received | C95: =IFERROR(' Cash Flow Date'!C16,0) -> 15 | D95: =IFERROR(' Cash Flow Date'!D16,0) -> 32 | E95: =IFERROR(' Cash Flow Date'!E16,0) -> 39 | F95: =IFERROR(' Cash Flow Date'!F16,0) -> 40 | G95: =IFERROR(' Cash Flow Date'!G16,0) -> 65 | H95: =IFERROR(' Cash Flow Date'!H16,0) -> 73 | I95: =IFERROR(' Cash Flow Date'!I16,0) -> 77 | J95: =IFERROR(' Cash Flow Date'!J16,0) -> 87 | ... L95: =IFERROR(' Cash Flow Date'!L16,0) -> 155
B96: =' Cash Flow Date'!B17 -> Dividends received | C96: =IFERROR(' Cash Flow Date'!C17,0) -> 69 | D96: =IFERROR(' Cash Flow Date'!D17,0) -> 74 | E96: =IFERROR(' Cash Flow Date'!E17,0) -> 38 | F96: =IFERROR(' Cash Flow Date'!F17,0) -> 40 | G96: =IFERROR(' Cash Flow Date'!G17,0) -> 27 | H96: =IFERROR(' Cash Flow Date'!H17,0) -> 8 | I96: =IFERROR(' Cash Flow Date'!I17,0) -> 15 | J96: =IFERROR(' Cash Flow Date'!J17,0) -> 56 | ... L96: =IFERROR(' Cash Flow Date'!L17,0) -> 136
B97: =' Cash Flow Date'!B18 -> Investment in group cos | C97: =IFERROR(' Cash Flow Date'!C18,0) -> 0 | D97: =IFERROR(' Cash Flow Date'!D18,0) -> 0 | E97: =IFERROR(' Cash Flow Date'!E18,0) -> 0 | F97: =IFERROR(' Cash Flow Date'!F18,0) -> 0 | G97: =IFERROR(' Cash Flow Date'!G18,0) -> 0 | H97: =IFERROR(' Cash Flow Date'!H18,0) -> 0 | I97: =IFERROR(' Cash Flow Date'!I18,0) -> 0 | J97: =IFERROR(' Cash Flow Date'!J18,0) -> -180 | ... L97: =IFERROR(' Cash Flow Date'!L18,0) -> 0
B98: =' Cash Flow Date'!B19 -> Redemp n Canc of Shares | C98: =IFERROR(' Cash Flow Date'!C19,0) -> 0 | D98: =IFERROR(' Cash Flow Date'!D19,0) -> 0 | E98: =IFERROR(' Cash Flow Date'!E19,0) -> 141 | F98: =IFERROR(' Cash Flow Date'!F19,0) -> 0 | G98: =IFERROR(' Cash Flow Date'!G19,0) -> 0 | H98: =IFERROR(' Cash Flow Date'!H19,0) -> 0 | I98: =IFERROR(' Cash Flow Date'!I19,0) -> 0 | J98: =IFERROR(' Cash Flow Date'!J19,0) -> 0 | ... L98: =IFERROR(' Cash Flow Date'!L19,0) -> 38
B99: =' Cash Flow Date'!B20 -> Acquisition of companies | C99: =IFERROR(' Cash Flow Date'!C20,0) -> 0 | D99: =IFERROR(' Cash Flow Date'!D20,0) -> 0 | E99: =IFERROR(' Cash Flow Date'!E20,0) -> -525 | F99: =IFERROR(' Cash Flow Date'!F20,0) -> 0 | G99: =IFERROR(' Cash Flow Date'!G20,0) -> 0 | H99: =IFERROR(' Cash Flow Date'!H20,0) -> 0 | I99: =IFERROR(' Cash Flow Date'!I20,0) -> 0 | J99: =IFERROR(' Cash Flow Date'!J20,0) -> 0 | ... L99: =IFERROR(' Cash Flow Date'!L20,0) -> 0
B100: =' Cash Flow Date'!B21 -> Other investing items | C100: =IFERROR(' Cash Flow Date'!C21,0) -> -70 | D100: =IFERROR(' Cash Flow Date'!D21,0) -> -324 | E100: =IFERROR(' Cash Flow Date'!E21,0) -> 118 | F100: =IFERROR(' Cash Flow Date'!F21,0) -> -24 | G100: =IFERROR(' Cash Flow Date'!G21,0) -> -353 | H100: =IFERROR(' Cash Flow Date'!H21,0) -> -500 | I100: =IFERROR(' Cash Flow Date'!I21,0) -> -105 | J100: =IFERROR(' Cash Flow Date'!J21,0) -> -126 | ... L100: =IFERROR(' Cash Flow Date'!L21,0) -> 130
B101: Cash From Investing Activity- | C101: =SUM(C91:C100) -> -865 | D101: =SUM(D91:D100) -> -681 | E101: =SUM(E91:E100) -> -1556 | F101: =SUM(F91:F100) -> -918 | G101: =SUM(G91:G100) -> -519 | H101: =SUM(H91:H100) -> -541 | I101: =SUM(I91:I100) -> -317 | J101: =SUM(J91:J100) -> -1283 | ... L101: =SUM(L91:L100) -> -941
B103: Financing Activity
B104: =' Cash Flow Date'!B23 -> Proceeds from shares | C104: =IFERROR(' Cash Flow Date'!C23,0) -> 0 | D104: =IFERROR(' Cash Flow Date'!D23,0) -> 0 | E104: =IFERROR(' Cash Flow Date'!E23,0) -> 0 | F104: =IFERROR(' Cash Flow Date'!F23,0) -> 0 | G104: =IFERROR(' Cash Flow Date'!G23,0) -> 0 | H104: =IFERROR(' Cash Flow Date'!H23,0) -> 0 | I104: =IFERROR(' Cash Flow Date'!I23,0) -> 0 | J104: =IFERROR(' Cash Flow Date'!J23,0) -> 0 | ... L104: =IFERROR(' Cash Flow Date'!L23,0) -> 0
B105: =' Cash Flow Date'!B24 -> Proceeds from borrowings | C105: =IFERROR(' Cash Flow Date'!C24,0) -> 8 | D105: =IFERROR(' Cash Flow Date'!D24,0) -> 271 | E105: =IFERROR(' Cash Flow Date'!E24,0) -> 10 | F105: =IFERROR(' Cash Flow Date'!F24,0) -> 243 | G105: =IFERROR(' Cash Flow Date'!G24,0) -> 18 | H105: =IFERROR(' Cash Flow Date'!H24,0) -> 155 | I105: =IFERROR(' Cash Flow Date'!I24,0) -> 418 | J105: =IFERROR(' Cash Flow Date'!J24,0) -> 254 | ... L105: =IFERROR(' Cash Flow Date'!L24,0) -> 415
B106: =' Cash Flow Date'!B25 -> Repayment of borrowings | C106: =IFERROR(' Cash Flow Date'!C25,0) -> -119 | D106: =IFERROR(' Cash Flow Date'!D25,0) -> -58 | E106: =IFERROR(' Cash Flow Date'!E25,0) -> -54 | F106: =IFERROR(' Cash Flow Date'!F25,0) -> -26 | G106: =IFERROR(' Cash Flow Date'!G25,0) -> -279 | H106: =IFERROR(' Cash Flow Date'!H25,0) -> -14 | I106: =IFERROR(' Cash Flow Date'!I25,0) -> -8 | J106: =IFERROR(' Cash Flow Date'!J25,0) -> -25 | ... L106: =IFERROR(' Cash Flow Date'!L25,0) -> -428
B107: =' Cash Flow Date'!B26 -> Interest paid fin | C107: =IFERROR(' Cash Flow Date'!C26,0) -> -40 | D107: =IFERROR(' Cash Flow Date'!D26,0) -> -36 | E107: =IFERROR(' Cash Flow Date'!E26,0) -> -35 | F107: =IFERROR(' Cash Flow Date'!F26,0) -> -106 | G107: =IFERROR(' Cash Flow Date'!G26,0) -> -101 | H107: =IFERROR(' Cash Flow Date'!H26,0) -> -89 | I107: =IFERROR(' Cash Flow Date'!I26,0) -> -94 | J107: =IFERROR(' Cash Flow Date'!J26,0) -> -142 | ... L107: =IFERROR(' Cash Flow Date'!L26,0) -> -203
B108: =' Cash Flow Date'!B27 -> Dividends paid | C108: =IFERROR(' Cash Flow Date'!C27,0) -> -764 | D108: =IFERROR(' Cash Flow Date'!D27,0) -> -947 | E108: =IFERROR(' Cash Flow Date'!E27,0) -> -1218 | F108: =IFERROR(' Cash Flow Date'!F27,0) -> -1049 | G108: =IFERROR(' Cash Flow Date'!G27,0) -> -2121 | H108: =IFERROR(' Cash Flow Date'!H27,0) -> -499 | I108: =IFERROR(' Cash Flow Date'!I27,0) -> -1763 | J108: =IFERROR(' Cash Flow Date'!J27,0) -> -1936 | ... L108: =IFERROR(' Cash Flow Date'!L27,0) -> -3140
B109: =' Cash Flow Date'!B28 -> Financial liabilities | C109: =IFERROR(' Cash Flow Date'!C28,0) -> 0 | D109: =IFERROR(' Cash Flow Date'!D28,0) -> 0 | E109: =IFERROR(' Cash Flow Date'!E28,0) -> 0 | F109: =IFERROR(' Cash Flow Date'!F28,0) -> -180 | G109: =IFERROR(' Cash Flow Date'!G28,0) -> -179 | H109: =IFERROR(' Cash Flow Date'!H28,0) -> -203 | I109: =IFERROR(' Cash Flow Date'!I28,0) -> -221 | J109: =IFERROR(' Cash Flow Date'!J28,0) -> -256 | ... L109: =IFERROR(' Cash Flow Date'!L28,0) -> -325
B110: =' Cash Flow Date'!B29 -> Other financing items | C110: =IFERROR(' Cash Flow Date'!C29,0) -> 66 | D110: =IFERROR(' Cash Flow Date'!D29,0) -> 13 | E110: =IFERROR(' Cash Flow Date'!E29,0) -> -82 | F110: =IFERROR(' Cash Flow Date'!F29,0) -> 0 | G110: =IFERROR(' Cash Flow Date'!G29,0) -> -209 | H110: =IFERROR(' Cash Flow Date'!H29,0) -> 0 | I110: =IFERROR(' Cash Flow Date'!I29,0) -> -140 | J110: =IFERROR(' Cash Flow Date'!J29,0) -> -36 | ... L110: =IFERROR(' Cash Flow Date'!L29,0) -> -72
B111: Cash from Financing Actitvity | C111: =SUM(C104:C110) -> -849 | D111: =SUM(D104:D110) -> -757 | E111: =SUM(E104:E110) -> -1379 | F111: =SUM(F104:F110) -> -1118 | G111: =SUM(G104:G110) -> -2871 | H111: =SUM(H104:H110) -> -650 | I111: =SUM(I104:I110) -> -1808 | J111: =SUM(J104:J110) -> -2141 | ... L111: =SUM(L104:L110) -> -3753
B113: Net Cash Flow | C113: =IFERROR(C88+C101+C111,0) -> 728 | D113: =IFERROR(D88+D101+D111,0) -> -513 | E113: =IFERROR(E88+E101+E111,0) -> -902 | F113: =IFERROR(F88+F101+F111,0) -> 23 | G113: =IFERROR(G88+G101+G111,0) -> -684 | H113: =IFERROR(H88+H101+H111,0) -> 2286 | I113: =IFERROR(I88+I101+I111,0) -> -3933 | J113: =IFERROR(J88+J101+J111,0) -> -2 | ... L113: =IFERROR(L88+L101+L111,0) -> -839

Sheet Ration Analysis
B4: =HistoricalFS!B2 -> TRENT LTD
B5: =HistoricalFS!B3 -> ( TRENT | BSE Code: 500251)
B7: ="Ration Analysis -"&'Data Sheet'!B1 -> Ration Analysis -TRENT LTD
B8: Years | C8: =HistoricalFS!C7 -> 42460 | D8: =HistoricalFS!D7 -> 42825 | E8: =HistoricalFS!E7 -> 43190 | F8: =HistoricalFS!F7 -> 43555 | G8: =HistoricalFS!G7 -> 43921 | H8: =HistoricalFS!H7 -> 44286 | I8: =HistoricalFS!I7 -> 44651 | J8: =HistoricalFS!J7 -> 45016 | ... L8: =HistoricalFS!L7 -> 45747 | M8: Trend | N8: Mean | O8: Median
B10: Growth Ratio
B11: Sales Growth | D11: =IFERROR(HistoricalFS!D11,0) -> 0.074885688 | E11: =IFERROR(HistoricalFS!E11,0) -> 0.19036216 | F11: =IFERROR(HistoricalFS!F11,0) -> 0.21913732 | G11: =IFERROR(HistoricalFS!G11,0) -> 0.32534674 | H11: =IFERROR(HistoricalFS!H11,0) -> -0.25617473 | I11: =IFERROR(HistoricalFS!I11,0) -> 0.73470474 | J11: =IFERROR(HistoricalFS!J11,0) -> 0.83236624 | K11: =IFERROR(HistoricalFS!K11,0) -> 0.50146566 | L11: =IFERROR(HistoricalFS!L11,0) -> 0.38460264 | N11: =IFERROR(AVERAGE(D11:L11),0) -> 0.33407738 | O11: =IFERROR(MEDIAN(C11:L11),0) -> 0.32534674
B12: EBITDA Growth | D12: =IFERROR(HistoricalFS!D22/HistoricalFS!C22-1,0) -> 0.48763369 | E12: =IFERROR(HistoricalFS!E22/HistoricalFS!D22-1,0) -> 0.56144687 | F12: =IFERROR(HistoricalFS!F22/HistoricalFS!E22-1,0) -> 0.15414868 | G12: =IFERROR(HistoricalFS!G22/HistoricalFS!F22-1,0) -> 1.1981799 | H12: =IFERROR(HistoricalFS!H22/HistoricalFS!G22-1,0) -> -0.78473259 | I12: =IFERROR(HistoricalFS!I22/HistoricalFS!H22-1,0) -> 4.2227979 | J12: =IFERROR(HistoricalFS!J22/HistoricalFS!I22-1,0) -> 0.87340261 | K12: =IFERROR(HistoricalFS!K22/HistoricalFS!J22-1,0) -> 0.76878338 | L12: =IFERROR(HistoricalFS!L22/HistoricalFS!K22-1,0) -> 0.43095058 | N12: =IFERROR(AVERAGE(D12:L12),0) -> 0.879179 | O12: =IFERROR(MEDIAN(C12:L12),0) -> 0.56144687
B13: EBT Growth | D13: =IFERROR(HistoricalFS!D34/HistoricalFS!C34-1,0) -> 12.572674 | E13: =IFERROR(HistoricalFS!E34/HistoricalFS!D34-1,0) -> 1.552795 | F13: =IFERROR(HistoricalFS!F34/HistoricalFS!E34-1,0) -> 0.16058394 | G13: =IFERROR(HistoricalFS!G34/HistoricalFS!F34-1,0) -> -0.86727391 | H13: =IFERROR(HistoricalFS!H34/HistoricalFS!G34-1,0) -> -23.01634 | I13: =IFERROR(HistoricalFS!I34/HistoricalFS!H34-1,0) -> -0.89871852 | J13: =IFERROR(HistoricalFS!J34/HistoricalFS!I34-1,0) -> -6.1653639 | K13: =IFERROR(HistoricalFS!K34/HistoricalFS!J34-1,0) -> 3.4068662 | L13: =IFERROR(HistoricalFS!L34/HistoricalFS!K34-1,0) -> 0.85067388 | N13: =IFERROR(AVERAGE(D13:L13),0) -> -1.3782336 | O13: =IFERROR(MEDIAN(C13:L13),0) -> 0.16058394
B14: Net Profit Growth | D14: =IFERROR(HistoricalFS!D40/HistoricalFS!C40-1,0) -> -1.1164055 | E14: =IFERROR(HistoricalFS!E40/HistoricalFS!D40-1,0) -> 15.365385 | F14: =IFERROR(HistoricalFS!F40/HistoricalFS!E40-1,0) -> 0.086452913 | G14: =IFERROR(HistoricalFS!G40/HistoricalFS!F40-1,0) -> -1.6280902 | H14: =IFERROR(HistoricalFS!H40/HistoricalFS!G40-1,0) -> 8.3611316 | I14: =IFERROR(HistoricalFS!I40/HistoricalFS!H40-1,0) -> -0.69106247 | J14: =IFERROR(HistoricalFS!J40/HistoricalFS!I40-1,0) -> -1.4510888 | K14: =IFERROR(HistoricalFS!K40/HistoricalFS!J40-1,0) -> 8.2127098 | L14: =IFERROR(HistoricalFS!L40/HistoricalFS!K40-1,0) -> 1.5163238 | N14: =IFERROR(AVERAGE(D14:L14),0) -> 3.1839284 | O14: =IFERROR(MEDIAN(C14:L14),0) -> 0.086452913
B15: Dividend Growth | D15: =IFERROR(HistoricalFS!D48/HistoricalFS!C48-1,0) -> 0.11099967 | E15: =IFERROR(HistoricalFS!E48/HistoricalFS!D48-1,0) -> 0.14986458 | F15: =IFERROR(HistoricalFS!F48/HistoricalFS!E48-1,0) -> 0.13059409 | G15: =IFERROR(HistoricalFS!G48/HistoricalFS!F48-1,0) -> -0.23078704 | H15: =IFERROR(HistoricalFS!H48/HistoricalFS!G48-1,0) -> -0.4 | I15: =IFERROR(HistoricalFS!I48/HistoricalFS!H48-1,0) -> 1.8335677 | J15: =IFERROR(HistoricalFS!J48/HistoricalFS!I48-1,0) -> 0.29401059 | K15: =IFERROR(HistoricalFS!K48/HistoricalFS!J48-1,0) -> 0 | L15: =IFERROR(HistoricalFS!L48/HistoricalFS!K48-1,0) -> 0 | N15: =IFERROR(AVERAGE(D15:L15),0) -> 0.20980551 | O15: =IFERROR(MEDIAN(C15:L15),0) -> 0.11099967
B17: Profitability Ratio
B18: Gross Margin | C18: =IFERROR(HistoricalFS!C17,0) -> 0.45382138 | D18: =IFERROR(HistoricalFS!D17,0) -> 0.44022975 | E18: =IFERROR(HistoricalFS!E17,0) -> 0.45535954 | F18: =IFERROR(HistoricalFS!F17,0) -> 0.43248145 | G18: =IFERROR(HistoricalFS!G17,0) -> 0.41310621 | H18: =IFERROR(HistoricalFS!H17,0) -> 0.353862 | I18: =IFERROR(HistoricalFS!I17,0) -> 0.40405556 | J18: =IFERROR(HistoricalFS!J17,0) -> 0.38413035 | ... L18: =IFERROR(HistoricalFS!L17,0) -> 0.39252776 | N18: =IFERROR(AVERAGE(C18:L18),0) -> 0.41273458 | O18: =IFERROR(MEDIAN(C18:L18),0) -> 0.40858089
B19: EBITDA Margin | C19: =IFERROR(HistoricalFS!C23,0) -> 0.053233067 | D19: =IFERROR(HistoricalFS!D23,0) -> 0.073674163 | E19: =IFERROR(HistoricalFS!E23,0) -> 0.096641421 | F19: =IFERROR(HistoricalFS!F23,0) -> 0.09148975 | G19: =IFERROR(HistoricalFS!G23,0) -> 0.15174212 | H19: =IFERROR(HistoricalFS!H23,0) -> 0.043915062 | I19: =IFERROR(HistoricalFS!I23,0) -> 0.13221818 | J19: =IFERROR(HistoricalFS!J23,0) -> 0.13517924 | ... L19: =IFERROR(HistoricalFS!L23,0) -> 0.16457684 | N19: =IFERROR(AVERAGE(C19:L19),0) -> 0.11019161 | O19: =IFERROR(MEDIAN(C19:L19),0) -> 0.1144298
B20: EBIT Margin | C20: =IFERROR(HistoricalFS!C29,0) -> 0.030346881 | D20: =HistoricalFS!D29 -> 0.050892719 | E20: =HistoricalFS!E29 -> 0.075537901 | F20: =HistoricalFS!F29 -> 0.071845155 | G20: =HistoricalFS!G29 -> 0.08081802 | H20: =HistoricalFS!H29 -> -0.055315161 | I20: =HistoricalFS!I29 -> 0.06311666 | J20: =HistoricalFS!J29 -> 0.075280089 | K20: =HistoricalFS!K29 -> 0.10501563 | L20: =HistoricalFS!L29 -> 0.11233287 | N20: =IFERROR(AVERAGE(C20:L20),0) -> 0.060987077 | O20: =IFERROR(MEDIAN(C20:L20),0) -> 0.073562622
B21: EBT Margin | C21: =IFERROR(HistoricalFS!C35,0) -> 0.0020401264 | D21: =IFERROR(HistoricalFS!D35,0) -> 0.025760853 | E21: =IFERROR(HistoricalFS!E35,0) -> 0.05524552 | F21: =IFERROR(HistoricalFS!F35,0) -> 0.052592159 | G21: =IFERROR(HistoricalFS!G35,0) -> 0.0052668116 | H21: =IFERROR(HistoricalFS!H35,0) -> -0.15589134 | I21: =IFERROR(HistoricalFS!I35,0) -> -0.0091017826 | J21: =IFERROR(HistoricalFS!J35,0) -> 0.025657545 | ... L21: =IFERROR(HistoricalFS!L35,0) -> 0.10065476 | N21: =IFERROR(AVERAGE(C21:L21),0) -> 0.017753065 | O21: =IFERROR(MEDIAN(C21:L21),0) -> 0.025709199
B22: Net Profit Margin | C22: =IFERROR(HistoricalFS!C41,0) -> -0.018544987 | D22: =IFERROR(HistoricalFS!D41,0) -> 0.0020083423 | E22: =IFERROR(HistoricalFS!E41,0) -> 0.027611172 | F22: =IFERROR(HistoricalFS!F41,0) -> 0.02460612 | G22: =IFERROR(HistoricalFS!G41,0) -> -0.011660996 | H22: =IFERROR(HistoricalFS!H41,0) -> -0.14675506 | I22: =IFERROR(HistoricalFS!I41,0) -> -0.026135944 | J22: =IFERROR(HistoricalFS!J41,0) -> 0.0064341023 | ... L22: =IFERROR(HistoricalFS!L41,0) -> 0.071746599 | N22: =IFERROR(AVERAGE(C22:L22),0) -> -0.0031212214 | O22: =IFERROR(MEDIAN(C22:L22),0) -> 0.0042212223
B23: Return On Equity (ROE) | C23: - | D23: =HistoricalFS!D40/'Data Sheet'!C79 -> 0.0024169345 | E23: =HistoricalFS!E40/'Data Sheet'!D79 -> 0.037905735 | F23: =HistoricalFS!F40/'Data Sheet'!E79 -> 0.03992745 | G23: =HistoricalFS!G40/'Data Sheet'!F79 -> -0.020152295 | H23: =HistoricalFS!H40/'Data Sheet'!G79 -> -0.1619001 | I23: =HistoricalFS!I40/'Data Sheet'!H79 -> -0.050271219 | J23: =HistoricalFS!J40/'Data Sheet'!I79 -> 0.021385263 | K23: =HistoricalFS!K40/'Data Sheet'!J79 -> 0.14664059 | L23: =HistoricalFS!L40/'Data Sheet'!K79 -> 0.25800988 | N23: =IFERROR(AVERAGE(C23:L23),0) -> 0.030440249 | O23: =IFERROR(MEDIAN(C23:L23),0) -> 0.021385263
B24: Return On Captial Employed (ROCE) | C24: - | D24: =HistoricalFS!D28/'Data Sheet'!C82 -> 0.048501165 | E24: =HistoricalFS!E28/'Data Sheet'!D82 -> 0.083016023 | F24: =HistoricalFS!F28/'Data Sheet'!E82 -> 0.091567433 | G24: =HistoricalFS!G28/'Data Sheet'!F82 -> 0.11670284 | H24: =HistoricalFS!H28/'Data Sheet'!G82 -> -0.054119729 | I24: =HistoricalFS!I28/'Data Sheet'!H82 -> 0.058522085 | J24: =HistoricalFS!J28/'Data Sheet'!I82 -> 0.087703787 | K24: =HistoricalFS!K28/'Data Sheet'!J82 -> 0.2017925 | L24: =HistoricalFS!L28/'Data Sheet'!K82 -> 0.28473793 | N24: =IFERROR(AVERAGE(C24:L24),0) -> 0.10204711 | O24: =IFERROR(MEDIAN(C24:L24),0) -> 0.087703787
B25: Return On Assets (ROA) | C25: - | D25: =HistoricalFS!D40/'Data Sheet'!C78 -> 0.0016625408 | E25: =HistoricalFS!E40/'Data Sheet'!D78 -> 0.026138027 | F25: =HistoricalFS!F40/'Data Sheet'!E78 -> 0.026445362 | G25: =HistoricalFS!G40/'Data Sheet'!F78 -> -0.010080045 | H25: =HistoricalFS!H40/'Data Sheet'!G78 -> -0.067767784 | I25: =HistoricalFS!I40/'Data Sheet'!H78 -> -0.017481366 | J25: =HistoricalFS!J40/'Data Sheet'!I78 -> 0.0067094521 | K25: =HistoricalFS!K40/'Data Sheet'!J78 -> 0.064100377 | L25: =HistoricalFS!L40/'Data Sheet'!K78 -> 0.14828069 | N25: =IFERROR(AVERAGE(C25:L25),0) -> 0.019778584 | O25: =IFERROR(MEDIAN(C25:L25),0) -> 0.0067094521
B27: Leverage Ratio
B28: Interest Coverage Ratio | C28: =HistoricalFS!C28/HistoricalFS!C31 -> 1.0720721 | D28: =HistoricalFS!D28/HistoricalFS!D31 -> 2.0250274 | E28: =HistoricalFS!E28/HistoricalFS!E31 -> 3.722476 | F28: =HistoricalFS!F28/HistoricalFS!F31 -> 3.7316351 | G28: =HistoricalFS!G28/HistoricalFS!G31 -> 1.0697118 | H28: =HistoricalFS!H28/HistoricalFS!H31 -> -0.54998274 | I28: =HistoricalFS!I28/HistoricalFS!I31 -> 0.87396872 | J28: =HistoricalFS!J28/HistoricalFS!J31 -> 1.5170542 | ... L28: =HistoricalFS!L28/HistoricalFS!L31 -> 9.6190905 | N28: =IFERROR(AVERAGE(C28:L28),0) -> 2.6615786 | O28: =IFERROR(MEDIAN(C28:L28),0) -> 1.7710408
B29: Debt to Equity Ratio | C29: =HistoricalFS!C59/SUM(HistoricalFS!C57:C58) -> 0.2730147 | D29: =HistoricalFS!D59/SUM(HistoricalFS!D57:D58) -> 0.2531127 | E29: =HistoricalFS!E59/SUM(HistoricalFS!E57:E58) -> 0.24535374 | F29: =HistoricalFS!F59/SUM(HistoricalFS!F57:F58) -> 0.30011357 | G29: =HistoricalFS!G59/SUM(HistoricalFS!G57:G58) -> 0.12553135 | H29: =HistoricalFS!H59/SUM(HistoricalFS!H57:H58) -> 0.12966974 | I29: =HistoricalFS!I59/SUM(HistoricalFS!I57:I58) -> 1.9988832 | J29: =HistoricalFS!J59/SUM(HistoricalFS!J57:J58) -> 1.7199604 | ... L29: =HistoricalFS!L59/SUM(HistoricalFS!L57:L58) -> 0.40961122 | N29: =IFERROR(AVERAGE(C29:L29),0) -> 0.58862001 | O29: =IFERROR(MEDIAN(C29:L29),0) -> 0.28656414
B30: Debt to Asset | C30: =HistoricalFS!C59/HistoricalFS!C74 -> 0.18538526 | D30: =HistoricalFS!D59/HistoricalFS!D74 -> 0.1762808 | E30: =HistoricalFS!E59/HistoricalFS!E74 -> 0.16757426 | F30: =HistoricalFS!F59/HistoricalFS!F74 -> 0.19311698 | G30: =HistoricalFS!G59/HistoricalFS!G74 -> 0.054432072 | H30: =HistoricalFS!H59/HistoricalFS!H74 -> 0.052401144 | I30: =HistoricalFS!I59/HistoricalFS!I74 -> 0.61161633 | J30: =HistoricalFS!J59/HistoricalFS!J74 -> 0.55238798 | ... L30: =HistoricalFS!L59/HistoricalFS!L74 -> 0.23750271 | N30: =IFERROR(AVERAGE(C30:L30),0) -> 0.24754687 | O30: =IFERROR(MEDIAN(C30:L30),0) -> 0.18925112
B31: Financial Leverage Ratio | D31: =HistoricalFS!D72/'Data Sheet'!C79 -> 0.22944942 | E31: =HistoricalFS!E72/'Data Sheet'!D79 -> 0.24987114 | F31: =HistoricalFS!F72/'Data Sheet'!E79 -> 0.35027823 | G31: =HistoricalFS!G72/'Data Sheet'!F79 -> 0.34025402 | H31: =HistoricalFS!H72/'Data Sheet'!G79 -> 0.22576157 | I31: =HistoricalFS!I72/'Data Sheet'!H79 -> 0.41565267 | J31: =HistoricalFS!J72/'Data Sheet'!I79 -> 0.59758161 | K31: =HistoricalFS!K72/'Data Sheet'!J79 -> 0.58891258 | L31: =HistoricalFS!L72/'Data Sheet'!K79 -> 0.51374052 | N31: =IFERROR(AVERAGE(D31:L31),0) -> 0.39016686 | O31: =IFERROR(MEDIAN(D31:L31),0) -> 0.35027823
B33: Efficiency Ratio
B34: Receivables Turnover Ratio | D34: =HistoricalFS!D10/'Data Sheet'!C74 -> 191.69117 | E34: =HistoricalFS!E10/'Data Sheet'!D74 -> 205.27688 | F34: =HistoricalFS!F10/'Data Sheet'!E74 -> 166.26043 | G34: =HistoricalFS!G10/'Data Sheet'!F74 -> 207.12894 | H34: =HistoricalFS!H10/'Data Sheet'!G74 -> 136.86778 | I34: =HistoricalFS!I10/'Data Sheet'!H74 -> 230.49039 | J34: =HistoricalFS!J10/'Data Sheet'!I74 -> 313.08718 | K34: =HistoricalFS!K10/'Data Sheet'!J74 -> 213.12512 | L34: =HistoricalFS!L10/'Data Sheet'!K74 -> 236.84581 | N34: =IFERROR(AVERAGE(C34:L34),0) -> 211.19708 | O34: =IFERROR(MEDIAN(C34:L34),0) -> 207.12894
B35: Creditor Turnover Ratio | C35: =IFERROR(HistoricalFS!C10/HistoricalFS!C60,0) -> 5.7666553 | D35: =IFERROR(HistoricalFS!D10/HistoricalFS!D60,0) -> 6.4084577 | E35: =IFERROR(HistoricalFS!E10/HistoricalFS!E60,0) -> 6.1807712 | F35: =IFERROR(HistoricalFS!F10/HistoricalFS!F60,0) -> 6.2907847 | G35: =IFERROR(HistoricalFS!G10/HistoricalFS!G60,0) -> 1.2365271 | H35: =IFERROR(HistoricalFS!H10/HistoricalFS!H60,0) -> 0.83354282 | I35: =IFERROR(HistoricalFS!I10/HistoricalFS!I60,0) -> 7.0650269 | J35: =IFERROR(HistoricalFS!J10/HistoricalFS!J60,0) -> 8.065388 | ... L35: =IFERROR(HistoricalFS!L10/HistoricalFS!L60,0) -> 9.957872 | N35: =IFERROR(AVERAGE(C35:L35),0) -> 6.1033158 | O35: =IFERROR(MEDIAN(C35:L35),0) -> 6.3496212
B36: Inventory Turnover | C36: =IFERROR(HistoricalFS!C10/HistoricalFS!C70,0) -> 6.0395071 | D36: =IFERROR(HistoricalFS!D10/HistoricalFS!D70,0) -> 5.9354205 | E36: =IFERROR(HistoricalFS!E10/HistoricalFS!E70,0) -> 6.257679 | F36: =IFERROR(HistoricalFS!F10/HistoricalFS!F70,0) -> 5.2921269 | G36: =IFERROR(HistoricalFS!G10/HistoricalFS!G70,0) -> 5.735312 | H36: =IFERROR(HistoricalFS!H10/HistoricalFS!H70,0) -> 6.0528024 | I36: =IFERROR(HistoricalFS!I10/HistoricalFS!I70,0) -> 5.1833644 | J36: =IFERROR(HistoricalFS!J10/HistoricalFS!J70,0) -> 6.0551441 | ... L36: =IFERROR(HistoricalFS!L10/HistoricalFS!L70,0) -> 8.3785775 | N36: =IFERROR(AVERAGE(C36:L36),0) -> 6.2748772 | O36: =IFERROR(MEDIAN(C36:L36),0) -> 6.0461547
B37: Fixed Asset Turnover | C37: =IFERROR(HistoricalFS!C10/HistoricalFS!C63,0) -> 3.5365045 | D37: =IFERROR(HistoricalFS!D10/HistoricalFS!D63,0) -> 3.3030927 | E37: =IFERROR(HistoricalFS!E10/HistoricalFS!E63,0) -> 3.5222112 | F37: =IFERROR(HistoricalFS!F10/HistoricalFS!F63,0) -> 3.9720922 | G37: =IFERROR(HistoricalFS!G10/HistoricalFS!G63,0) -> 1.2729849 | H37: =IFERROR(HistoricalFS!H10/HistoricalFS!H63,0) -> 0.84908737 | I37: =IFERROR(HistoricalFS!I10/HistoricalFS!I63,0) -> 0.95973935 | J37: =IFERROR(HistoricalFS!J10/HistoricalFS!J63,0) -> 1.8206563 | ... L37: =IFERROR(HistoricalFS!L10/HistoricalFS!L63,0) -> 4.3989828 | N37: =IFERROR(AVERAGE(C37:L37),0) -> 2.8686582 | O37: =IFERROR(MEDIAN(C37:L37),0) -> 3.4126519
B38: Capital Turnover Ratio | C38: =IFERROR(HistoricalFS!C10/SUM(HistoricalFS!C57:C58),0) -> 1.1514487 | D38: =IFERROR(HistoricalFS!D10/SUM(HistoricalFS!D57:D58),0) -> 1.1710614 | E38: =IFERROR(HistoricalFS!E10/SUM(HistoricalFS!E57:E58),0) -> 1.3523258 | F38: =IFERROR(HistoricalFS!F10/SUM(HistoricalFS!F57:F58),0) -> 1.5974637 | G38: =IFERROR(HistoricalFS!G10/SUM(HistoricalFS!G57:G58),0) -> 1.4599312 | H38: =IFERROR(HistoricalFS!H10/SUM(HistoricalFS!H57:H58),0) -> 1.1210231 | I38: =IFERROR(HistoricalFS!I10/SUM(HistoricalFS!I57:I58),0) -> 1.9027157 | J38: =IFERROR(HistoricalFS!J10/SUM(HistoricalFS!J57:J58),0) -> 3.175516 | ... L38: =IFERROR(HistoricalFS!L10/SUM(HistoricalFS!L57:L58),0) -> 3.1372072 | N38: =IFERROR(AVERAGE(C38:L38),0) -> 1.911095 | O38: =IFERROR(MEDIAN(C38:L38),0) -> 1.5286975
B39: Debtor Days | C39: =IFERROR(365/C34,0) -> 0 | D39: =IFERROR(365/D34,0) -> 1.9041044 | E39: =IFERROR(365/E34,0) -> 1.7780863 | F39: =IFERROR(365/F34,0) -> 2.195351 | G39: =IFERROR(365/G34,0) -> 1.7621874 | H39: =IFERROR(365/H34,0) -> 2.6668074 | I39: =IFERROR(365/I34,0) -> 1.5835801 | J39: =IFERROR(365/J34,0) -> 1.1658095 | ... L39: =IFERROR(365/L34,0) -> 1.541087 | N39: =IFERROR(AVERAGE(C39:L39),0) -> 1.6309622 | O39: =IFERROR(AVERAGE(D39:M39),0) -> 1.8121802
B40: Creditor Days | C40: =IFERROR(365/C35,0) -> 63.294923 | D40: =IFERROR(365/D35,0) -> 56.955982 | E40: =IFERROR(365/E35,0) -> 59.054119 | F40: =IFERROR(365/F35,0) -> 58.021378 | G40: =IFERROR(365/G35,0) -> 295.18157 | H40: =IFERROR(365/H35,0) -> 437.88992 | I40: =IFERROR(365/I35,0) -> 51.662932 | J40: =IFERROR(365/J35,0) -> 45.255107 | ... L40: =IFERROR(365/L35,0) -> 36.654418 | N40: =IFERROR(AVERAGE(C40:L40),0) -> 114.35233 | O40: =IFERROR(AVERAGE(D40:M40),0) -> 120.02538
B41: Inventor Days | C41: =IFERROR(365/C36,0) -> 60.435395 | D41: =IFERROR(365/D36,0) -> 61.495222 | E41: =IFERROR(365/E36,0) -> 58.328335 | F41: =IFERROR(365/F36,0) -> 68.970379 | G41: =IFERROR(365/G36,0) -> 63.640827 | H41: =IFERROR(365/H36,0) -> 60.302646 | I41: =IFERROR(365/I36,0) -> 70.417584 | J41: =IFERROR(365/J36,0) -> 60.279325 | ... L41: =IFERROR(365/L36,0) -> 43.563481 | N41: =IFERROR(AVERAGE(C41:L41),0) -> 59.411532 | O41: =IFERROR(AVERAGE(D41:M41),0) -> 59.297769
B42: Cash Conversion Cycle(in days) | C42: =SUM(C39/C41)-C40 -> -63.294923 | D42: =SUM(D39/D41)-D40 -> -56.925019 | E42: =SUM(E39/E41)-E40 -> -59.023635 | F42: =SUM(F39/F41)-F40 -> -57.989548 | G42: =SUM(G39/G41)-G40 -> -295.15388 | H42: =SUM(H39/H41)-H40 -> -437.8457 | I42: =SUM(I39/I41)-I40 -> -51.640443 | J42: =SUM(J39/J41)-J40 -> -45.235767 | ... L42: =SUM(L39/L41)-L40 -> -36.619042 | N42: =IFERROR(AVERAGE(C42:L42),0) -> -114.32442 | O42: =IFERROR(AVERAGE(D42:M42),0) -> -119.99437
B44: CFO/Sales | C44: =IFERROR(HistoricalFS!C88/HistoricalFS!C10,0) -> 1.4482525 | D44: =IFERROR(HistoricalFS!D88/HistoricalFS!D10,0) -> 0.51036172 | E44: =IFERROR(HistoricalFS!E88/HistoricalFS!E10,0) -> 0.94231179 | F44: =IFERROR(HistoricalFS!F88/HistoricalFS!F10,0) -> 0.7828183 | G44: =IFERROR(HistoricalFS!G88/HistoricalFS!G10,0) -> 0.7762523 | H44: =IFERROR(HistoricalFS!H88/HistoricalFS!H10,0) -> 1.3409385 | I44: =IFERROR(HistoricalFS!I88/HistoricalFS!I10,0) -> -0.40195464 | J44: =IFERROR(HistoricalFS!J88/HistoricalFS!J10,0) -> 0.41518948 | ... L44: =IFERROR(HistoricalFS!L88/HistoricalFS!L10,0) -> 0.22498324 | N44: =IFERROR(AVERAGE(C44:L44),0) -> 0.65332095 | O44: =IFERROR(AVERAGE(D44:M44),0) -> 0.56499522
B45: CFO/Total Assests | C45: =IFERROR(HistoricalFS!C88/HistoricalFS!C74,0) -> 1.1323432 | D45: =IFERROR(HistoricalFS!D88/HistoricalFS!D74,0) -> 0.4162448 | E45: =IFERROR(HistoricalFS!E88/HistoricalFS!E74,0) -> 0.87034326 | F45: =IFERROR(HistoricalFS!F88/HistoricalFS!F74,0) -> 0.80468665 | G45: =IFERROR(HistoricalFS!G88/HistoricalFS!G74,0) -> 0.49140317 | H45: =IFERROR(HistoricalFS!H88/HistoricalFS!H74,0) -> 0.607471 | I45: =IFERROR(HistoricalFS!I88/HistoricalFS!I74,0) -> -0.23401441 | J45: =IFERROR(HistoricalFS!J88/HistoricalFS!J74,0) -> 0.42343467 | ... L45: =IFERROR(HistoricalFS!L88/HistoricalFS!L74,0) -> 0.40925131 | N45: =IFERROR(AVERAGE(C45:L45),0) -> 0.57748656 | O45: =IFERROR(AVERAGE(D45:M45),0) -> 0.51583582
C46: =IFERROR(HistoricalFS!C88/HistoricalFS!C59,0) -> 6.108054 | D46: =IFERROR(HistoricalFS!D88/HistoricalFS!D59,0) -> 2.36126 | E46: =IFERROR(HistoricalFS!E88/HistoricalFS!E59,0) -> 5.1937767 | F46: =IFERROR(HistoricalFS!F88/HistoricalFS!F59,0) -> 4.1668353 | G46: =IFERROR(HistoricalFS!G88/HistoricalFS!G59,0) -> 9.0278241 | H46: =IFERROR(HistoricalFS!H88/HistoricalFS!H59,0) -> 11.592705 | I46: =IFERROR(HistoricalFS!I88/HistoricalFS!I59,0) -> -0.38261635 | J46: =IFERROR(HistoricalFS!J88/HistoricalFS!J59,0) -> 0.76655302 | ... L46: =IFERROR(HistoricalFS!L88/HistoricalFS!L59,0) -> 1.7231438 | N46: =IFERROR(AVERAGE(C46:L46),0) -> 4.4045291 | O46: =IFERROR(AVERAGE(D46:M46),0) -> 4.2152485

Sheet Forcasting
B4: ='Ration Analysis'!B4 -> TRENT LTD
B5: ='Ration Analysis'!B5 -> ( TRENT | BSE Code: 500251)
B7: ='Data Sheet'!B1&" - "&'Data Sheet'!A42 -> TRENT LTD - Sales | G7: ='Data Sheet'!B1&" - "&HistoricalFS!B22 -> TRENT LTD - EBITDA | L7: ='Data Sheet'!B1&" - "&HistoricalFS!B45 -> TRENT LTD - EPS
B9: Years Weight | C9: Year | D9: Sales | E9: Sales Growth | G9: Years Weight | H9: Year | I9: =HistoricalFS!B22 -> EBITDA | J9: EBITDA Growth | L9: Years Weight | M9: Year | N9: =HistoricalFS!B45 -> EPS | O9: EPS Growth
B11: 1 | C11: 2016 | D11: {=TRANSPOSE('Data Sheet'!B17:K17)} -> 1686.17 | G11: 1 | H11: 2016 | I11: {=TRANSPOSE(HistoricalFS!C22:L22)} -> 89.76 | L11: 1 | M11: 2016 | N11: {=TRANSPOSE(HistoricalFS!C45:L45)} -> -0.94101715
B12: =B11+1 -> 2 | C12: =C11+1 -> 2017 | D12: 1812.44 | E12: =D12/D11-1 -> 0.074885688 | G12: =G11+1 -> 2 | H12: =H11+1 -> 2017 | I12: 133.53 | J12: =I12/I11-1 -> 0.48763369 | L12: =L11+1 -> 2 | M12: =M11+1 -> 2017 | N12: 0.10953957 | O12: =N12/N11-1 -> -1.1164055
B13: =B12+1 -> 3 | C13: =C12+1 -> 2018 | D13: 2157.46 | E13: =D13/D12-1 -> 0.19036216 | G13: =G12+1 -> 3 | H13: =H12+1 -> 2018 | I13: 208.5 | J13: =I13/I12-1 -> 0.56144687 | L13: =L12+1 -> 3 | M13: =M12+1 -> 2018 | N13: 1.7926572 | O13: =N13/N12-1 -> 15.365385
B14: =B13+1 -> 4 | C14: =C13+1 -> 2019 | D14: 2630.24 | E14: =D14/D13-1 -> 0.21913732 | G14: =G13+1 -> 4 | H14: =H13+1 -> 2019 | I14: 240.64 | J14: =I14/I13-1 -> 0.15414868 | L14: =L13+1 -> 4 | M14: =M13+1 -> 2019 | N14: 1.9476377 | O14: =N14/N13-1 -> 0.086452913
B15: =B14+1 -> 5 | C15: =C14+1 -> 2020 | D15: 3485.98 | E15: =D15/D14-1 -> 0.32534674 | G15: =G14+1 -> 5 | H15: =H14+1 -> 2020 | I15: 528.97 | J15: =I15/I14-1 -> 1.1981799 | L15: =L14+1 -> 5 | M15: =M14+1 -> 2020 | N15: -1.1434599 | O15: =N15/N14-1 -> -1.5871009
B16: =B15+1 -> 6 | C16: =C15+1 -> 2021 | D16: 2592.96 | E16: =D16/D15-1 -> -0.25617473 | G16: =G15+1 -> 6 | H16: =H15+1 -> 2021 | I16: 113.87 | J16: =I16/I15-1 -> -0.78473259 | L16: =L15+1 -> 6 | M16: =M15+1 -> 2021 | N16: -10.704079 | O16: =N16/N15-1 -> 8.3611316
B17: =B16+1 -> 7 | C17: =C16+1 -> 2022 | D17: 4498.02 | E17: =D17/D16-1 -> 0.73470474 | G17: =G16+1 -> 7 | H17: =H16+1 -> 2022 | I17: 594.72 | J17: =I17/I16-1 -> 4.2227979 | L17: =L16+1 -> 7 | M17: =M16+1 -> 2022 | N17: -3.3068917 | O17: =N17/N16-1 -> -0.69106247
B18: =B17+1 -> 8 | C18: =C17+1 -> 2023 | D18: 8242.02 | E18: =D18/D17-1 -> 0.83236624 | G18: =G17+1 -> 8 | H18: =H17+1 -> 2023 | I18: 1114.15 | J18: =I18/I17-1 -> 0.87340261 | L18: =L17+1 -> 8 | M18: =M17+1 -> 2023 | N18: 1.4917018 | O18: =N18/N17-1 -> -1.4510888
B19: =B18+1 -> 9 | C19: =C18+1 -> 2024 | D19: 12375.11 | E19: =D19/D18-1 -> 0.50146566 | G19: =G18+1 -> 9 | H19: =H18+1 -> 2024 | I19: 1970.69 | J19: =I19/I18-1 -> 0.76878338 | L19: =L18+1 -> 9 | M19: =M18+1 -> 2024 | N19: 13.742616 | O19: =N19/N18-1 -> 8.2127098
B20: =B19+1 -> 10 | C20: =C19+1 -> 2025 | D20: 17134.61 | E20: =D20/D19-1 -> 0.38460264 | G20: =G19+1 -> 10 | H20: =H19+1 -> 2025 | I20: 2819.96 | J20: =I20/I19-1 -> 0.43095058 | L20: =L19+1 -> 10 | M20: =M19+1 -> 2025 | N20: 34.580872 | O20: =N20/N19-1 -> 1.5163238
B21: =B20+1 -> 11 | C21: =C20+1 -> 2026 | D21: =FORECAST(B21,$D$11:$D$20,$B$11:$B$20) -> 13931.76 | E21: =D21/D20-1 -> -0.18692284 | G21: =G20+1 -> 11 | H21: =H20+1 -> 2026 | I21: =FORECAST(G21,$I$11:$I$20,$G$11:$G$20) -> 2201.7227 | J21: =I21/I20-1 -> -0.21923621 | L21: =L20+1 -> 11 | M21: =M20+1 -> 2026 | N21: =FORECAST(L21,$N$11:$N$20,$L$11:$L$20) -> 16.700276 | O21: =N21/N20-1 -> -0.51706608
B22: =B21+1 -> 12 | C22: =C21+1 -> 2027 | D22: =FORECAST(B22,$D$11:$D$20,$B$11:$B$20) -> 15435.443 | E22: =D22/D21-1 -> 0.10793205 | G22: =G21+1 -> 12 | H22: =H21+1 -> 2027 | I22: =FORECAST(G22,$I$11:$I$20,$G$11:$G$20) -> 2459.9488 | J22: =I22/I21-1 -> 0.11728367 | L22: =L21+1 -> 12 | M22: =M21+1 -> 2027 | N22: =FORECAST(L22,$N$11:$N$20,$L$11:$L$20) -> 19.053607 | O22: =N22/N21-1 -> 0.14091567
B23: =B22+1 -> 13 | C23: =C22+1 -> 2028 | D23: =FORECAST(B23,$D$11:$D$20,$B$11:$B$20) -> 16939.127 | E23: =D23/D22-1 -> 0.097417574 | G23: =G22+1 -> 13 | H23: =H22+1 -> 2028 | I23: =FORECAST(G23,$I$11:$I$20,$G$11:$G$20) -> 2718.1749 | J23: =I23/I22-1 -> 0.10497215 | L23: =L22+1 -> 13 | M23: =M22+1 -> 2028 | N23: =FORECAST(L23,$N$11:$N$20,$L$11:$L$20) -> 21.406937 | O23: =N23/N22-1 -> 0.12351103
B24: =B23+1 -> 14 | C24: =C23+1 -> 2029 | D24: =FORECAST(B24,$D$11:$D$20,$B$11:$B$20) -> 18442.81 | E24: =D24/D23-1 -> 0.088769832 | G24: =G23+1 -> 14 | H24: =H23+1 -> 2029 | I24: =FORECAST(G24,$I$11:$I$20,$G$11:$G$20) -> 2976.401 | J24: =I24/I23-1 -> 0.094999818 | L24: =L23+1 -> 14 | M24: =M23+1 -> 2029 | N24: =FORECAST(L24,$N$11:$N$20,$L$11:$L$20) -> 23.760268 | O24: =N24/N23-1 -> 0.10993308
B25: =B24+1 -> 15 | C25: =C24+1 -> 2030 | D25: =FORECAST(B25,$D$11:$D$20,$B$11:$B$20) -> 19946.494 | E25: =D25/D24-1 -> 0.08153223 | G25: =G24+1 -> 15 | H25: =H24+1 -> 2030 | I25: =FORECAST(G25,$I$11:$I$20,$G$11:$G$20) -> 3234.6272 | J25: =I25/I24-1 -> 0.086757839 | L25: =L24+1 -> 15 | M25: =M24+1 -> 2030 | N25: =FORECAST(L25,$N$11:$N$20,$L$11:$L$20) -> 26.113599 | O25: =N25/N24-1 -> 0.099044785

Sheet Common Size Statement 
B4: ='Altman Z Score'!B3 -> TRENT LTD
B5: ='Dupont Analysis'!B4 -> ( TRENT | BSE Code: 500251)
B7: ="Common Size Incom Statement"&" - "&'Data Sheet'!$B$1 -> Common Size Incom Statement - TRENT LTD
B9: Particulars | C9: ='Data Sheet'!B56 -> 42460 | D9: ='Data Sheet'!C56 -> 42825 | E9: ='Data Sheet'!D56 -> 43190 | F9: ='Data Sheet'!E56 -> 43555 | G9: ='Data Sheet'!F56 -> 43921 | H9: ='Data Sheet'!G56 -> 44286 | I9: ='Data Sheet'!H56 -> 44651 | J9: ='Data Sheet'!I56 -> 45016 | ... L9: ='Data Sheet'!K56 -> 45747
B11: ='Data Sheet'!A17 -> Sales | C11: ='Data Sheet'!B17/'Data Sheet'!B$17 -> 1 | D11: ='Data Sheet'!C17/'Data Sheet'!C$17 -> 1 | E11: ='Data Sheet'!D17/'Data Sheet'!D$17 -> 1 | F11: ='Data Sheet'!E17/'Data Sheet'!E$17 -> 1 | G11: ='Data Sheet'!F17/'Data Sheet'!F$17 -> 1 | H11: ='Data Sheet'!G17/'Data Sheet'!G$17 -> 1 | I11: ='Data Sheet'!H17/'Data Sheet'!H$17 -> 1 | J11: ='Data Sheet'!I17/'Data Sheet'!I$17 -> 1 | ... L11: ='Data Sheet'!K17/'Data Sheet'!K$17 -> 1
B12: ='Data Sheet'!A18 -> Raw Material Cost | C12: ='Data Sheet'!B18/'Data Sheet'!B$17 -> 0.48049722 | D12: ='Data Sheet'!C18/'Data Sheet'!C$17 -> 0.50275871 | E12: ='Data Sheet'!D18/'Data Sheet'!D$17 -> 0.49596285 | F12: ='Data Sheet'!E18/'Data Sheet'!E$17 -> 0.55495696 | G12: ='Data Sheet'!F18/'Data Sheet'!F$17 -> 0.55985404 | H12: ='Data Sheet'!G18/'Data Sheet'!G$17 -> 0.52898618 | I12: ='Data Sheet'!H18/'Data Sheet'!H$17 -> 0.64925901 | J12: ='Data Sheet'!I18/'Data Sheet'!I$17 -> 0.63225399 | ... L12: ='Data Sheet'!K18/'Data Sheet'!K$17 -> 0.59198254
B13: ='Data Sheet'!A19 -> Change in Inventory | C13: ='Data Sheet'!B19/'Data Sheet'!B$17 -> 0.0086527456 | D13: ='Data Sheet'!C19/'Data Sheet'!C$17 -> 0.016475028 | E13: ='Data Sheet'!D19/'Data Sheet'!D$17 -> 0.017849694 | F13: ='Data Sheet'!E19/'Data Sheet'!E$17 -> 0.056356074 | G13: ='Data Sheet'!F19/'Data Sheet'!F$17 -> 0.020048882 | H13: ='Data Sheet'!G19/'Data Sheet'!G$17 -> -0.062615698 | I13: ='Data Sheet'!H19/'Data Sheet'!H$17 -> 0.097562928 | J13: ='Data Sheet'!I19/'Data Sheet'!I$17 -> 0.059610387 | ... L13: ='Data Sheet'!K19/'Data Sheet'!K$17 -> 0.026510671
B14: ='Data Sheet'!A20 -> Power and Fuel | C14: ='Data Sheet'!B20/'Data Sheet'!B$17 -> 0.029012496 | D14: ='Data Sheet'!C20/'Data Sheet'!C$17 -> 0.02829335 | E14: ='Data Sheet'!D20/'Data Sheet'!D$17 -> 0.024450048 | F14: ='Data Sheet'!E20/'Data Sheet'!E$17 -> 0.022499848 | G14: ='Data Sheet'!F20/'Data Sheet'!F$17 -> 0.019116576 | H14: ='Data Sheet'!G20/'Data Sheet'!G$17 -> 0.019055442 | I14: ='Data Sheet'!H20/'Data Sheet'!H$17 -> 0.015982588 | J14: ='Data Sheet'!I20/'Data Sheet'!I$17 -> 0.017505417 | ... L14: ='Data Sheet'!K20/'Data Sheet'!K$17 -> 0.020418907
B15: ='Data Sheet'!A21 -> Other Mfr. Exp | C15: ='Data Sheet'!B21/'Data Sheet'!B$17 -> 0.045321646 | D15: ='Data Sheet'!C21/'Data Sheet'!C$17 -> 0.04519322 | E15: ='Data Sheet'!D21/'Data Sheet'!D$17 -> 0.042077258 | F15: ='Data Sheet'!E21/'Data Sheet'!E$17 -> 0.046417817 | G15: ='Data Sheet'!F21/'Data Sheet'!F$17 -> 0.027972048 | H15: ='Data Sheet'!G21/'Data Sheet'!G$17 -> 0.035480686 | I15: ='Data Sheet'!H21/'Data Sheet'!H$17 -> 0.02826577 | J15: ='Data Sheet'!I21/'Data Sheet'!I$17 -> 0.025720636 | ... L15: ='Data Sheet'!K21/'Data Sheet'!K$17 -> 0.021581466
B16: ='Data Sheet'!A22 -> Employee Cost | C16: ='Data Sheet'!B22/'Data Sheet'!B$17 -> 0.098264113 | D16: ='Data Sheet'!C22/'Data Sheet'!C$17 -> 0.10743528 | E16: ='Data Sheet'!D22/'Data Sheet'!D$17 -> 0.10800664 | F16: ='Data Sheet'!E22/'Data Sheet'!E$17 -> 0.10983408 | G16: ='Data Sheet'!F22/'Data Sheet'!F$17 -> 0.10356055 | H16: ='Data Sheet'!G22/'Data Sheet'!G$17 -> 0.11700913 | I16: ='Data Sheet'!H22/'Data Sheet'!H$17 -> 0.089577192 | J16: ='Data Sheet'!I22/'Data Sheet'!I$17 -> 0.07996462 | ... L16: ='Data Sheet'!K22/'Data Sheet'!K$17 -> 0.076776769
B17: ='Data Sheet'!A23 -> Selling and admin | C17: ='Data Sheet'!B23/'Data Sheet'!B$17 -> 0.26335423 | D17: ='Data Sheet'!C23/'Data Sheet'!C$17 -> 0.22459778 | E17: ='Data Sheet'!D23/'Data Sheet'!D$17 -> 0.20886135 | F17: ='Data Sheet'!E23/'Data Sheet'!E$17 -> 0.19557531 | G17: ='Data Sheet'!F23/'Data Sheet'!F$17 -> 0.12530766 | H17: ='Data Sheet'!G23/'Data Sheet'!G$17 -> 0.14061922 | I17: ='Data Sheet'!H23/'Data Sheet'!H$17 -> 0.1567423 | J17: ='Data Sheet'!I23/'Data Sheet'!I$17 -> 0.15196881 | ... L17: ='Data Sheet'!K23/'Data Sheet'!K$17 -> 0.13556363
B18: ='Data Sheet'!A24 -> Other Expenses | C18: ='Data Sheet'!B24/'Data Sheet'!B$17 -> 0.038969973 | D18: ='Data Sheet'!C24/'Data Sheet'!C$17 -> 0.034522522 | E18: ='Data Sheet'!D24/'Data Sheet'!D$17 -> 0.041850139 | F18: ='Data Sheet'!E24/'Data Sheet'!E$17 -> 0.035582304 | G18: ='Data Sheet'!F24/'Data Sheet'!F$17 -> 0.032495884 | H18: ='Data Sheet'!G24/'Data Sheet'!G$17 -> 0.052318586 | I18: ='Data Sheet'!H24/'Data Sheet'!H$17 -> 0.025517895 | J18: ='Data Sheet'!I24/'Data Sheet'!I$17 -> 0.017017673 | ... L18: ='Data Sheet'!K24/'Data Sheet'!K$17 -> 0.01561051
B19: ='Data Sheet'!A25 -> Other Income | C19: ='Data Sheet'!B25/'Data Sheet'!B$17 -> 0.051264107 | D19: ='Data Sheet'!C25/'Data Sheet'!C$17 -> 0.044862175 | E19: ='Data Sheet'!D25/'Data Sheet'!D$17 -> 0.012732565 | F19: ='Data Sheet'!E25/'Data Sheet'!E$17 -> 0.01145903 | G19: ='Data Sheet'!F25/'Data Sheet'!F$17 -> 0.042062777 | H19: ='Data Sheet'!G25/'Data Sheet'!G$17 -> 0.076900531 | I19: ='Data Sheet'!H25/'Data Sheet'!H$17 -> 0.033828218 | J19: ='Data Sheet'!I25/'Data Sheet'!I$17 -> 0.041324821 | ... L19: ='Data Sheet'!K25/'Data Sheet'!K$17 -> 0.017803732
B20: ='Data Sheet'!A26 -> Depreciation | C20: ='Data Sheet'!B26/'Data Sheet'!B$17 -> 0.022886186 | D20: ='Data Sheet'!C26/'Data Sheet'!C$17 -> 0.022781444 | E20: ='Data Sheet'!D26/'Data Sheet'!D$17 -> 0.02110352 | F20: ='Data Sheet'!E26/'Data Sheet'!E$17 -> 0.019644595 | G20: ='Data Sheet'!F26/'Data Sheet'!F$17 -> 0.070924102 | H20: ='Data Sheet'!G26/'Data Sheet'!G$17 -> 0.099230223 | I20: ='Data Sheet'!H26/'Data Sheet'!H$17 -> 0.069101516 | J20: ='Data Sheet'!I26/'Data Sheet'!I$17 -> 0.059899151 | ... L20: ='Data Sheet'!K26/'Data Sheet'!K$17 -> 0.052243967
B21: ='Data Sheet'!A27 -> Interest | C21: ='Data Sheet'!B27/'Data Sheet'!B$17 -> 0.028306754 | D21: ='Data Sheet'!C27/'Data Sheet'!C$17 -> 0.025131866 | E21: ='Data Sheet'!D27/'Data Sheet'!D$17 -> 0.020292381 | F21: ='Data Sheet'!E27/'Data Sheet'!E$17 -> 0.019252996 | G21: ='Data Sheet'!F27/'Data Sheet'!F$17 -> 0.075551208 | H21: ='Data Sheet'!G27/'Data Sheet'!G$17 -> 0.10057618 | I21: ='Data Sheet'!H27/'Data Sheet'!H$17 -> 0.072218443 | J21: ='Data Sheet'!I27/'Data Sheet'!I$17 -> 0.049622544 | ... L21: ='Data Sheet'!K27/'Data Sheet'!K$17 -> 0.011678118
B22: ='Data Sheet'!A28 -> Profit before tax | C22: ='Data Sheet'!B28/'Data Sheet'!B$17 -> 0.053304234 | D22: ='Data Sheet'!C28/'Data Sheet'!C$17 -> 0.070623028 | E22: ='Data Sheet'!D28/'Data Sheet'!D$17 -> 0.067978085 | F22: ='Data Sheet'!E28/'Data Sheet'!E$17 -> 0.064051189 | G22: ='Data Sheet'!F28/'Data Sheet'!F$17 -> 0.047329589 | H22: ='Data Sheet'!G28/'Data Sheet'!G$17 -> -0.078990806 | I22: ='Data Sheet'!H28/'Data Sheet'!H$17 -> 0.024726435 | J22: ='Data Sheet'!I28/'Data Sheet'!I$17 -> 0.066982366 | ... L22: ='Data Sheet'!K28/'Data Sheet'!K$17 -> 0.11845849
... B25: ='Data Sheet'!A31 -> Dividend Amount | C25: ='Data Sheet'!B31/'Data Sheet'!B$17 -> 0.017738425 | D25: ='Data Sheet'!C31/'Data Sheet'!C$17 -> 0.0183344 | E25: ='Data Sheet'!D31/'Data Sheet'!D$17 -> 0.017710641 | F25: ='Data Sheet'!E31/'Data Sheet'!E$17 -> 0.016424357 | G25: ='Data Sheet'!F31/'Data Sheet'!F$17 -> 0.010197993 | H25: ='Data Sheet'!G31/'Data Sheet'!G$17 -> 0.00822612 | I25: ='Data Sheet'!H31/'Data Sheet'!H$17 -> 0.013437023 | J25: ='Data Sheet'!I31/'Data Sheet'!I$17 -> 0.0094891786 | ... L25: ='Data Sheet'!K31/'Data Sheet'!K$17 -> 0.0045644459
B26: ='Data Sheet'!A33 -> EBITDA | C26: ='Data Sheet'!B33/'Data Sheet'!B$17 -> 0.10445566 | D26: ='Data Sheet'!C33/'Data Sheet'!C$17 -> 0.11848668 | E26: ='Data Sheet'!D33/'Data Sheet'!D$17 -> 0.10934154 | F26: ='Data Sheet'!E33/'Data Sheet'!E$17 -> 0.10374719 | G26: ='Data Sheet'!F33/'Data Sheet'!F$17 -> 0.19864428 | H26: ='Data Sheet'!G33/'Data Sheet'!G$17 -> 0.13429825 | I26: ='Data Sheet'!H33/'Data Sheet'!H$17 -> 0.18188225 | J26: ='Data Sheet'!I33/'Data Sheet'!I$17 -> 0.18269186 | K26: ='Data Sheet'!J33/'Data Sheet'!J$17 -> 0.23991221 | L26: ='Data Sheet'!K32/'Data Sheet'!K$17 -> 0
B28: ="Common Size Balance Sheet"&" - "&'Data Sheet'!$B$1 -> Common Size Balance Sheet - TRENT LTD
B30: Particulars | C30: =C9 -> 42460 | D30: =D9 -> 42825 | E30: =E9 -> 43190 | F30: =F9 -> 43555 | G30: =G9 -> 43921 | H30: =H9 -> 44286 | I30: =I9 -> 44651 | J30: =J9 -> 45016 | ... L30: =L9 -> 45747
B32: Total Liabilities | C32: ='Data Sheet'!B61/'Data Sheet'!B$61 -> 1 | D32: ='Data Sheet'!C61/'Data Sheet'!C$61 -> 1 | E32: ='Data Sheet'!D61/'Data Sheet'!D$61 -> 1 | F32: ='Data Sheet'!E61/'Data Sheet'!E$61 -> 1 | G32: ='Data Sheet'!F61/'Data Sheet'!F$61 -> 1 | H32: ='Data Sheet'!G61/'Data Sheet'!G$61 -> 1 | I32: ='Data Sheet'!H61/'Data Sheet'!H$61 -> 1 | J32: ='Data Sheet'!I61/'Data Sheet'!I$61 -> 1 | ... L32: ='Data Sheet'!K61/'Data Sheet'!K$61 -> 1
B33: ='Data Sheet'!A57 -> Equity Share Capital | C33: ='Data Sheet'!B57/'Data Sheet'!B$61 -> 0.015408585 | D33: ='Data Sheet'!C57/'Data Sheet'!C$61 -> 0.014953313 | E33: ='Data Sheet'!D57/'Data Sheet'!D$61 -> 0.014226024 | F33: ='Data Sheet'!E57/'Data Sheet'!E$61 -> 0.012986759 | G33: ='Data Sheet'!F57/'Data Sheet'!F$61 -> 0.0064557955 | H33: ='Data Sheet'!G57/'Data Sheet'!G$61 -> 0.0062109848 | I33: ='Data Sheet'!H57/'Data Sheet'!H$61 -> 0.0046013342 | J33: ='Data Sheet'!I57/'Data Sheet'!I$61 -> 0.0043989195 | ... L33: ='Data Sheet'!K57/'Data Sheet'!K$61 -> 0.0037740296
B34: ='Data Sheet'!A58 -> Reserves | C34: ='Data Sheet'!B58/'Data Sheet'!B$61 -> 0.66362174 | D34: ='Data Sheet'!C58/'Data Sheet'!C$61 -> 0.68149848 | E34: ='Data Sheet'!D58/'Data Sheet'!D$61 -> 0.6687644 | F34: ='Data Sheet'!E58/'Data Sheet'!E$61 -> 0.63049289 | G34: ='Data Sheet'!F58/'Data Sheet'!F$61 -> 0.42715756 | H34: ='Data Sheet'!G58/'Data Sheet'!G$61 -> 0.39790137 | I34: ='Data Sheet'!H58/'Data Sheet'!H$61 -> 0.30137768 | J34: ='Data Sheet'!I58/'Data Sheet'!I$61 -> 0.31676428 | ... L34: ='Data Sheet'!K58/'Data Sheet'!K$61 -> 0.57605068
B35: ='Data Sheet'!A59 -> Borrowings | C35: ='Data Sheet'!B59/'Data Sheet'!B$61 -> 0.18538526 | D35: ='Data Sheet'!C59/'Data Sheet'!C$61 -> 0.1762808 | E35: ='Data Sheet'!D59/'Data Sheet'!D$61 -> 0.16757426 | F35: ='Data Sheet'!E59/'Data Sheet'!E$61 -> 0.19311698 | G35: ='Data Sheet'!F59/'Data Sheet'!F$61 -> 0.054432072 | H35: ='Data Sheet'!G59/'Data Sheet'!G$61 -> 0.052401144 | I35: ='Data Sheet'!H59/'Data Sheet'!H$61 -> 0.61161633 | J35: ='Data Sheet'!I59/'Data Sheet'!I$61 -> 0.55238798 | ... L35: ='Data Sheet'!K59/'Data Sheet'!K$61 -> 0.23750271
B36: ='Data Sheet'!A60 -> Other Liabilities | C36: ='Data Sheet'!B60/'Data Sheet'!B$61 -> 0.13558442 | D36: ='Data Sheet'!C60/'Data Sheet'!C$61 -> 0.12726741 | E36: ='Data Sheet'!D60/'Data Sheet'!D$61 -> 0.14943533 | F36: ='Data Sheet'!E60/'Data Sheet'!E$61 -> 0.16340337 | G36: ='Data Sheet'!F60/'Data Sheet'!F$61 -> 0.51195457 | H36: ='Data Sheet'!G60/'Data Sheet'!G$61 -> 0.5434865 | I36: ='Data Sheet'!H60/'Data Sheet'!H$61 -> 0.082404653 | J36: ='Data Sheet'!I60/'Data Sheet'!I$61 -> 0.12644883 | ... L36: ='Data Sheet'!K60/'Data Sheet'!K$61 -> 0.18267259
B38: Total Assets | C38: ='Data Sheet'!B77/'Data Sheet'!B$77 -> 1 | D38: ='Data Sheet'!C77/'Data Sheet'!C$77 -> 1 | E38: ='Data Sheet'!D77/'Data Sheet'!D$77 -> 1 | F38: ='Data Sheet'!E77/'Data Sheet'!E$77 -> 1 | G38: ='Data Sheet'!F77/'Data Sheet'!F$77 -> 1 | H38: ='Data Sheet'!G77/'Data Sheet'!G$77 -> 1 | I38: ='Data Sheet'!H77/'Data Sheet'!H$77 -> 1 | J38: ='Data Sheet'!I77/'Data Sheet'!I$77 -> 1 | ... L38: ='Data Sheet'!K77/'Data Sheet'!K$77 -> 1
B39: ='Data Sheet'!A62 -> Net Block | C39: ='Data Sheet'!B62/'Data Sheet'!B$77 -> 0.22108514 | D39: ='Data Sheet'!C62/'Data Sheet'!C$77 -> 0.24691641 | E39: ='Data Sheet'!D62/'Data Sheet'!D$77 -> 0.2622289 | F39: ='Data Sheet'!E62/'Data Sheet'!E$77 -> 0.25878941 | G39: ='Data Sheet'!F62/'Data Sheet'!F$77 -> 0.49729238 | H39: ='Data Sheet'!G62/'Data Sheet'!G$77 -> 0.5335367 | I39: ='Data Sheet'!H62/'Data Sheet'!H$77 -> 0.60661375 | J39: ='Data Sheet'!I62/'Data Sheet'!I$77 -> 0.56016002 | ... L39: ='Data Sheet'!K62/'Data Sheet'!K$77 -> 0.41351156
B40: ='Data Sheet'!A63 -> Capital Work in Progress | C40: ='Data Sheet'!B63/'Data Sheet'!B$77 -> 0.025438308 | D40: ='Data Sheet'!C63/'Data Sheet'!C$77 -> 0.0024659692 | E40: ='Data Sheet'!D63/'Data Sheet'!D$77 -> 0.0041055543 | F40: ='Data Sheet'!E63/'Data Sheet'!E$77 -> 0.034071191 | G40: ='Data Sheet'!F63/'Data Sheet'!F$77 -> 0.0042348566 | H40: ='Data Sheet'!G63/'Data Sheet'!G$77 -> 0.01886532 | I40: ='Data Sheet'!H63/'Data Sheet'!H$77 -> 0.013554197 | J40: ='Data Sheet'!I63/'Data Sheet'!I$77 -> 0.012586726 | ... L40: ='Data Sheet'!K63/'Data Sheet'!K$77 -> 0.01905593
B41: ='Data Sheet'!A64 -> Investments | C41: ='Data Sheet'!B64/'Data Sheet'!B$77 -> 0.49474865 | D41: ='Data Sheet'!C64/'Data Sheet'!C$77 -> 0.48597593 | E41: ='Data Sheet'!D64/'Data Sheet'!D$77 -> 0.43790296 | F41: ='Data Sheet'!E64/'Data Sheet'!E$77 -> 0.34502259 | G41: ='Data Sheet'!F64/'Data Sheet'!F$77 -> 0.27508045 | H41: ='Data Sheet'!G64/'Data Sheet'!G$77 -> 0.25984629 | I41: ='Data Sheet'!H64/'Data Sheet'!H$77 -> 0.16615541 | J41: ='Data Sheet'!I64/'Data Sheet'!I$77 -> 0.13733414 | ... L41: ='Data Sheet'!K64/'Data Sheet'!K$77 -> 0.15714507
B42: ='Data Sheet'!A65 -> Other Assets | C42: ='Data Sheet'!B76/'Data Sheet'!B$77 -> 0.1107721 | D42: ='Data Sheet'!C76/'Data Sheet'!C$77 -> 0.10914164 | E42: ='Data Sheet'!D76/'Data Sheet'!D$77 -> 0.1276532 | F42: ='Data Sheet'!E76/'Data Sheet'!E$77 -> 0.14022026 | G42: ='Data Sheet'!F76/'Data Sheet'!F$77 -> 0.098754603 | H42: ='Data Sheet'!G76/'Data Sheet'!G$77 -> 0.095044665 | I42: ='Data Sheet'!H76/'Data Sheet'!H$77 -> 0.087866715 | J42: ='Data Sheet'!I76/'Data Sheet'!I$77 -> 0.10655656 | ... L42: ='Data Sheet'!K76/'Data Sheet'!K$77 -> 0.15042188
B43: ='Data Sheet'!A67 -> Receivables | C43: ='Data Sheet'!B67/'Data Sheet'!B$77 -> 0.006023398 | D43: ='Data Sheet'!C67/'Data Sheet'!C$77 -> 0.0026639667 | E43: ='Data Sheet'!D67/'Data Sheet'!D$77 -> 0.0064644285 | F43: ='Data Sheet'!E67/'Data Sheet'!E$77 -> 0.0064640685 | G43: ='Data Sheet'!F67/'Data Sheet'!F$77 -> 0.0031089513 | H43: ='Data Sheet'!G67/'Data Sheet'!G$77 -> 0.0036287526 | I43: ='Data Sheet'!H67/'Data Sheet'!H$77 -> 0.002363442 | J43: ='Data Sheet'!I67/'Data Sheet'!I$77 -> 0.0042553823 | ... L43: ='Data Sheet'!K67/'Data Sheet'!K$77 -> 0.0066828456
B44: ='Data Sheet'!A68 -> Inventory | C44: ='Data Sheet'!B68/'Data Sheet'!B$77 -> 0.12945901 | D44: ='Data Sheet'!C68/'Data Sheet'!C$77 -> 0.13741028 | E44: ='Data Sheet'!D68/'Data Sheet'!D$77 -> 0.14759874 | F44: ='Data Sheet'!E68/'Data Sheet'!E$77 -> 0.19423862 | G44: ='Data Sheet'!F68/'Data Sheet'!F$77 -> 0.11037685 | H44: ='Data Sheet'!G68/'Data Sheet'!G$77 -> 0.074844551 | I44: ='Data Sheet'!H68/'Data Sheet'!H$77 -> 0.11231915 | J44: ='Data Sheet'!I68/'Data Sheet'!I$77 -> 0.1684285 | ... L44: ='Data Sheet'!K68/'Data Sheet'!K$77 -> 0.2171049
B45: ='Data Sheet'!A69 -> Cash & Bank | C45: ='Data Sheet'!B69/'Data Sheet'!B$77 -> 0.012473395 | D45: ='Data Sheet'!C69/'Data Sheet'!C$77 -> 0.015425807 | E45: ='Data Sheet'!D69/'Data Sheet'!D$77 -> 0.014046219 | F45: ='Data Sheet'!E69/'Data Sheet'!E$77 -> 0.02119386 | G45: ='Data Sheet'!F69/'Data Sheet'!F$77 -> 0.01115191 | H45: ='Data Sheet'!G69/'Data Sheet'!G$77 -> 0.014233725 | I45: ='Data Sheet'!H69/'Data Sheet'!H$77 -> 0.011127333 | J45: ='Data Sheet'!I69/'Data Sheet'!I$77 -> 0.010678671 | ... L45: ='Data Sheet'!K69/'Data Sheet'!K$77 -> 0.036077812

Sheet DCF>

Sheet DCF
B2: ='Intrisic Growth'!B4 -> TRENT LTD
B3: ='Intrisic Growth'!B5 -> ( TRENT | BSE Code: 500251)
B5: Company Overview
B15: Revenue Projections & Growth Assumptions
I16: ₹ in Crores
B18: Year | E18: =E27 -> 46083 | F18: =366+E18 -> 46449 | G18: =366+F18 -> 46815 | H18: =366+G18 -> 47181 | I18: =366+H18 -> 47547
B19: Revenue Growth % | E19: {=CHOOSE(F21,E22:I22,E23:I23,E24:I24)} -> 0.2 | F19: 0.18 | G19: 0.16 | H19: 0.14 | I19: 0.12
B20: Revenue (in Cr) | E20: =D28*(1+E19) -> 20561.532 | F20: =E28*(1+F19) -> 24262.608 | G20: =F28*(1+G19) -> 28144.625 | H20: =G28*(1+H19) -> 32084.873 | I20: =H28*(1+I19) -> 35935.057
B21: Chosen | E21: Base Case | F21: =MATCH(E21,B22:B24) -> 1
B22: Base Case | E22: =WACC!C16 -> 0.2 | F22: =E22-Taper_rate -> 0.18 | G22: =F22-Taper_rate -> 0.16 | H22: =G22-Taper_rate -> 0.14 | I22: =H22-Taper_rate -> 0.12
B23: Best Case | E23: =E22+5% -> 0.25 | F23: =E23-Taper_rate -> 0.23 | G23: =F23-Taper_rate -> 0.21 | H23: =G23-Taper_rate -> 0.19 | I23: =H23-Taper_rate -> 0.17
B24: Worst Case | E24: =E22-5% -> 0.15 | F24: =E24-Taper_rate -> 0.13 | G24: =F24-Taper_rate -> 0.11 | H24: =G24-Taper_rate -> 0.09 | I24: =H24-Taper_rate -> 0.07
B27: Calculation of PV of FCFF | D27: ='Intrisic Growth'!K8 -> 45717 | E27: =366+D27 -> 46083 | F27: =366+E27 -> 46449 | G27: =366+F27 -> 46815 | H27: =366+G27 -> 47181 | I27: =366+H27 -> 47547
B28: Revenue | D28: =HistoricalFS!L10 -> 17134.61 | E28: =E20 -> 20561.532 | F28: =F20 -> 24262.608 | G28: =G20 -> 28144.625 | H28: =H20 -> 32084.873 | I28: =I20 -> 35935.057
B29: EBITDA Margin % | D29: =HistoricalFS!L23 -> 0.16457684 | E29: =D29 -> 0.16457684 | F29: =E29 -> 0.16457684 | G29: =F29 -> 0.16457684 | H29: =G29 -> 0.16457684 | I29: =H29 -> 0.16457684
B30: EBITDA | D30: =D28*D29 -> 2819.96 | E30: =E28*E29 -> 3383.952 | F30: =F28*F29 -> 3993.0634 | G30: =G28*G29 -> 4631.9535 | H30: =H28*H29 -> 5280.427 | I30: =I28*I29 -> 5914.0782
B31: Less: Deperciation | D31: =D28*AVERAGE(HistoricalFS!$H$26:$L$26) -> 1147.0096 | E31: =E28*AVERAGE(HistoricalFS!$H$26:$L$26) -> 1376.4115 | F31: =F28*AVERAGE(HistoricalFS!$H$26:$L$26) -> 1624.1656 | G31: =G28*AVERAGE(HistoricalFS!$H$26:$L$26) -> 1884.0321 | H31: =H28*AVERAGE(HistoricalFS!$H$26:$L$26) -> 2147.7966 | I31: =I28*AVERAGE(HistoricalFS!$H$26:$L$26) -> 2405.5322
B32: EBIT | D32: =HistoricalFS!L28 -> 1924.78 | E32: =E30-E31 -> 2007.5405 | F32: =F30-F31 -> 2368.8978 | G32: =G30-G31 -> 2747.9214 | H32: =H30-H31 -> 3132.6304 | I32: =I30-I31 -> 3508.5461
B33: Tax | D33: =D32*Tax_rate -> 481.195 | E33: =E32*Tax_rate -> 501.88512 | F33: =F32*Tax_rate -> 592.22444 | G33: =G32*Tax_rate -> 686.98035 | H33: =H32*Tax_rate -> 783.1576 | I33: =I32*Tax_rate -> 877.13652 | M33: 46083 | N33: 46449 | O33: 46815 | P33: 47181 | Q33: 47547
B34: NOPAT | D34: =D32-D33 -> 1443.585 | E34: =E32-E33 -> 1505.6554 | F34: =F32-F33 -> 1776.6733 | G34: =G32-G33 -> 2060.9411 | H34: =H32-H33 -> 2349.4728 | I34: =I32-I33 -> 2631.4096 | M34: 2019.4721 | N34: 2382.977 | O34: 2764.2533 | P34: 3151.2488 | Q34: 3529.3987
B35: Add: Deperication | D35: =D31 -> 1147.0096 | E35: =E31 -> 1376.4115 | F35: =F31 -> 1624.1656 | G35: =G31 -> 1884.0321 | H35: =H31 -> 2147.7966 | I35: =I31 -> 2405.5322
B36: Less Reinvestment | D36: =-D34*'Intrisic Growth'!$K$54 -> -827.03451 | E36: =-E34*'Intrisic Growth'!$K$54 -> -862.59483 | F36: =-F34*'Intrisic Growth'!$K$54 -> -1017.8619 | G36: =-G34*'Intrisic Growth'!$K$54 -> -1180.7198 | H36: =-H34*'Intrisic Growth'!$K$54 -> -1346.0206 | I36: =-I34*'Intrisic Growth'!$K$54 -> -1507.543 | M36: 1911.2658 | N36: 2020.0847 | O36: 2098.9112 | P36: 2143.2133 | Q36: 2150.0567
B37: Free Cash Flow of From | D37: =SUM(D34:D36) -> 1763.5601 | E37: =SUM(E34:E36) -> 2019.4721 | F37: =SUM(F34:F36) -> 2382.977 | G37: =SUM(G34:G36) -> 2764.2533 | H37: =SUM(H34:H36) -> 3151.2488 | I37: =SUM(I34:I36) -> 3529.3987
B38: Mid Year Convention | E38: 0.5 | F38: =E38+1 -> 1.5 | G38: =F38+1 -> 2.5 | H38: =G38+1 -> 3.5 | I38: =H38+1 -> 4.5
B39: Discounting Factor | E39: =1/(1+$C$45)^E38 -> 0.94641855 | F39: =1/(1+$C$45)^F38 -> 0.84771474 | G39: =1/(1+$C$45)^G38 -> 0.75930493 | H39: =1/(1+$C$45)^H38 -> 0.68011556 | I39: =1/(1+$C$45)^I38 -> 0.609185
B41: PV of FCFF | E41: =E37*E39 -> 1911.2658 | F41: =F37*F39 -> 2020.0847 | G41: =G37*G39 -> 2098.9112 | H41: =H37*H39 -> 2143.2133 | I41: =I37*I39 -> 2150.0567
B43: Expected Growth | C43: ='Intrisic Growth'!K64 -> 0.24828276
B44: Terminal Growth | C44: =WACC!C18 -> 0.065 | K44: 1
B45: WACC | C45: =WACC!J61 -> 0.11643518 | K45: reinvestment grwot take it from intrisic griwth table as a median
B47: Calulation of Terminal Value | E47: Sensitivity Analysis
B49: FCFF (FY30) | C49: =I37 -> 3529.3987 | E49: Terminal Growth / WACC
B50: WACC | C50: =C45 -> 0.11643518 | E50: =C64 -> 1528.4734 | F50: 0.16 | G50: 0.1164 | H50: 0.18 | I50: 0.19
B51: Terminal Growth Rate | C51: =C44 -> 0.065 | E51: =E52-1% -> 0.04 | F51: 690.34047 | G51: 1099.4358 | H51: 588.38031 | I51: 547.6846
B52: Terminal Value | C52: =C49*(1+C51)/(C50-C51) -> 73078.58 | E52: 0.05 | F52: 735.09887 | G52: 1232.6102 | H52: 618.95717 | I52: 573.41329
E53: =C44 -> 0.065 | F53: 819.90425 | G53: 1529.5319 | H53: 674.79319 | I53: 619.72494
B54: Calulation of Present Value | E54: 0.07 | F54: 854.45459 | G54: 1671.1671 | H54: 696.7892 | I54: 637.73503
E55: =E54+1% -> 0.08 | F55: 936.51165 | G55: 2071.1695 | H55: 747.38002 | I55: 678.66704
B56: PV of FCFF (Fy 26-30) | C56: =SUM(E41:I41) -> 10323.532
B57: PV of Terminal Value | C57: =C52*I39 -> 44518.374
B58: Enterprice Value | C58: =SUM(C56:C57) -> 54841.906
B60: Add: Cash & Investment | C60: ='Data Sheet'!K69+'Data Sheet'!K64 -> 1820.09
B61: Less: Debt | C61: =WACC!D29 -> 2348.57
B62: Value of Equity | C62: =C58+C60-C61 -> 54313.426
B63: No. of share | C63: ='Data Sheet'!B6 -> 35.534427
B64: Equity value of per share | C64: =C62/C63 -> 1528.4734 | D64: =C65/C64-1 -> 1.8038434
B65: Current Market Price | C65: ='Data Sheet'!B8 -> 4285.6
B66: Upside/Downside | C66: =C64/C65-1 -> -0.6433467
B68: Key Risks & Considerations
B70: Upside Risks:
B71: Faster Store Expansion: Company may exceed planned store additions, especially for Zudio format
B72: Market Share Gains: Continued market share gains from unorganized retail
B73: Margin Expansion: Higher private label penetration could drive margins beyond projections
B74: Digital Growth: Omnichannel integration could accelerate revenue growth
B76: Downside Risks:
B77: Competition: Intensifying competition from global fast fashion brands and e-commerce
B78: Execution Risk: Challenges in maintaining quality and brand positioning during rapid expansion
B79: Economic Slowdown: Consumer discretionary spending could be impacted by economic headwinds
B80: Real Estate Costs: Rising rental costs in prime locations could pressure margins
B81: Inventory Management: Working capital requirements may increase with scale
... B91: However, current valuation apprears stretched with PE of ~102x of trailing earnings.

Sheet Data>

Sheet WACC
B6: ='Beta-Regression'!B2 -> TRENT LTD
B7: ='Beta-Regression'!B3 -> ( TRENT | BSE Code: 500251)
B9: Weighted Average Cost of Capital
B11: Key Assumptions & Methodology
B13: Parameter | C13: Value | D13: Rationale
B15: Valuation Date | C15: 46067
B16: Revenue Growth% | C16: 0.2 | D16: Based on Management Guidance
C17: 0.02
B18: Terminal Growth Rate | C18: 0.065 | D18: Conservative long term growth considering India's GDP and retail sector potential
B19: Risk-Free Rate (Rf) | C19: 0.0676 | D19: 10-years Government Bond Yield
B20: Equity Risk Premium (ERP) | C20: =12%-C19 -> 0.0524 | D20: Expected return over risk free rate for equity investors
B21: Tax Rate | C21: 0.25 | D21: Effective tax rate based on historical data
B24: Peer Comps
J25: ₹ in Crores
G26: Debt/ | H26: Debt/ | I26: Levered | J26: Unlevered
B27: Name of the Comps | C27: Country | D27: Total Debt | E27: Total Equity | F27: Tax Rate 1 | G27: Equity | H27: Capital | I27: Beta2 | J27: Beta3
B29: ='Beta-comps'!C3 -> Trent | C29: India | D29: ='Beta-comps'!G3 -> 2348.57 | E29: ='Beta-comps'!E3 -> 151462.5 | F29: =Tax_rate -> 0.25 | G29: =D29/E29 -> 0.01550595 | H29: =D29/(D29+E29) -> 0.015269187 | I29: ='Beta-Regression'!K11 -> 1.3748374 | J29: =I29/(1+G29*(1-Tax_rate)) -> 1.3590326
B30: ='Beta-comps'!C4 -> Avenue Super. | C30: India | D30: ='Beta-comps'!G4 -> 1609.19 | E30: ='Beta-comps'!E4 -> 254384.57 | F30: =F29 -> 0.25 | G30: =D30/E30 -> 0.0063258161 | H30: =D30/(D30+E30) -> 0.0062860517 | I30: 1.25 | J30: =I30/(1+G30*(1-Tax_rate)) -> 1.2440976
B31: ='Beta-comps'!C5 -> Page Industries | C31: India | D31: ='Beta-comps'!G5 -> 268.13 | E31: ='Beta-comps'!E5 -> 37398.94 | F31: =F30 -> 0.25 | G31: =D31/E31 -> 0.0071694545 | H31: =D31/(D31+E31) -> 0.0071184194 | I31: 0.39 | J31: =I31/(1+G31*(1-Tax_rate)) -> 0.38791415
B32: ='Beta-comps'!C6 -> Vedant Fashions | C32: India | D32: ='Beta-comps'!G6 -> 463.76 | E32: ='Beta-comps'!E6 -> 11062.57 | F32: =F31 -> 0.25 | G32: =D32/E32 -> 0.041921543 | H32: =D32/(D32+E32) -> 0.040234836 | I32: 0.67 | J32: =I32/(1+G32*(1-Tax_rate)) -> 0.64957656
B33: ='Beta-comps'!C7 -> V2 Retail | C33: India | D33: ='Beta-comps'!G7 -> 1312.5 | E33: ='Beta-comps'!E7 -> 7406.52 | F33: =F32 -> 0.25 | G33: =D33/E33 -> 0.17720873 | H33: =D33/(D33+E33) -> 0.15053297 | I33: 1.8 | J33: =I33/(1+G33*(1-Tax_rate)) -> 1.5888336
E35: Average | F35: =AVERAGE(F29:F33) -> 0.25 | G35: =AVERAGE(G29:G33) -> 0.049626299 | H35: =AVERAGE(H29:H33) -> 0.043888293 | I35: =AVERAGE(I29:I33) -> 1.0969675 | J35: =AVERAGE(J29:J33) -> 1.0458909
E36: Median | F36: =MEDIAN(F29:F33) -> 0.25 | G36: =MEDIAN(G29:G33) -> 0.01550595 | H36: =MEDIAN(H29:H33) -> 0.015269187 | I36: =MEDIAN(I29:I33) -> 1.25 | J36: =MEDIAN(J29:J33) -> 1.2440976
B39: Cost of debt | H39: Cost of Equity
B41: Pre-Tax Cost of Debt | F41: =200/D29 -> 0.085158203 | H41: Risk Free Rate | J41: =C19 -> 0.0676
B42: Tax Rate | F42: =F33 -> 0.25 | H42: Equity Risk Premium | J42: =C20 -> 0.0524
B43: After Tax Cost of Debt | F43: =F41*(1-F42) -> 0.063868652 | H43: Levered Beta4 | J43: =J51 -> 0.94776923
H44: Cost of Equity | J44: =J41+J42*J43 -> 0.11726311
B46: Capital Struture | H46: Levered Beta
E48: Current | F48: Target | H48: Comps Median Unlivered Beta | J48: =J36 -> 1.2440976
B49: Total Debt | D49: =D29 -> 2348.57 | E49: =D49/$D$51 -> 0.015269187 | F49: =G36 -> 0.01550595 | H49: Target Debt/Equity | J49: =F53 -> 0.015750172
B50: Market Capitalization | D50: =E29 -> 151462.5 | E50: =D50/$D$51 -> 0.98473081 | F50: =F51-F49 -> 0.98449405 | H50: Tax Rate | J50: =F42 -> 0.25
B51: Total Capitalization | D51: =SUM(D49:D50) -> 153811.07 | E51: =D51/$D$51 -> 1 | F51: 1 | H51: Levered Beta | J51: =J36*(1+F53)*(1-Tax_rate) -> 0.94776923
B53: Debt/Equity | E53: =E49/E50 -> 0.01550595 | F53: =F49/F50 -> 0.015750172
H54: Weighted Averager Cost of Capital
B55: 1. Tax Rate considered as Marginal Tax Rate for the country
B56: 2. Levered Beta is based on 2 year weekly data | H56: Cost of Equity | J56: =J44 -> 0.11726311
B57: 3. Unlevered Beta = Levered Beta/(1+(1-Tax Rate) x Debt/Equity) | H57: Equity Weight | J57: =F50 -> 0.98449405
B58: 3. Levered Beta = Unlevered Beta/(1+(1-Tax Rate) x Debt/Equity) | H58: Cost of debt | J58: =F43 -> 0.063868652
H59: debt Weight | J59: =F49 -> 0.01550595
H61: WACC | J61: =(J56*J57)+(J58*J59) -> 0.11643518

Sheet Beta-Regression
B2: ='Ration Analysis'!$B$4 -> TRENT LTD
B3: =Forcasting!B5 -> ( TRENT | BSE Code: 500251)
B5: Beta Regression
B7: Regression Beta - 2 Years Weekly
B8: Trent Weekly Returns | G8: NIFTY 50 - Weekly Returns | J8: Beta Drifting
B11: Date | C11: Close Price | D11: Returns | E11: Diffrence | G11: Closing Price | H11: Returns | J11: Levered Raw Beta | K11: =SLOPE(D13:D116,H13:H116) -> 1.3748374
B12: 02/13/2026 | C12: 4251.35 | G12: 25471.1 | J12: Raw Beta Weight | K12: 0.25
B13: 46175 | C13: 4118.9 | D13: =C13/C12-1 -> -0.03115481 | E13: =H13-D13 -> 0.039894126 | G13: 25693.7 | H13: =G13/G12-1 -> 0.0087393163
B14: 01/30/2026 | C14: 3785.6 | D14: =C14/C13-1 -> -0.080919663 | E14: =H14-D14 -> 0.06640054 | G14: 25320.65 | H14: =G14/G13-1 -> -0.014519123 | J14: Market Beta | K14: 1
B15: 01/23/2026 | C15: 3754.9 | D15: =C15/C14-1 -> -0.0081096788 | E15: =H15-D15 -> -0.0026325415 | G15: 25048.65 | H15: =G15/G14-1 -> -0.01074222 | J15: Market Beta Weight | K15: 0.75
B16: 01/16/2026 | C16: 3901.75 | D16: =C16/C15-1 -> 0.039108898 | E16: =H16-D16 -> -0.013331061 | G16: 25694.35 | H16: =G16/G15-1 -> 0.025777836 | J16: Adjusted Beta | K16: =(K11*K12)+(K14*K15) -> 1.0937094
B17: 46266 | C17: 3975.8 | D17: =C17/C16-1 -> 0.018978663 | E17: =H17-D17 -> -0.019408719 | G17: 25683.3 | H17: =G17/G16-1 -> -0.00043005563
B18: 46054 | C18: 4408.8 | D18: =C18/C17-1 -> 0.1089089 | E18: =H18-D18 -> -0.08378557 | G18: 26328.55 | H18: =G18/G17-1 -> 0.025123329
B19: 12/26/2025 | C19: 4283.8 | D19: =C19/C18-1 -> -0.028352386 | E19: =H19-D19 -> 0.017480158 | G19: 26042.3 | H19: =G19/G18-1 -> -0.010872228
B20: 12/19/2025 | C20: 4061.75 | D20: =C20/C19-1 -> -0.05183482 | E20: =H20-D20 -> 0.04892033 | G20: 25966.4 | H20: =G20/G19-1 -> -0.0029144891
B21: 46003 | C21: 4072.95 | D21: =C21/C20-1 -> 0.0027574321 | E21: =H21-D21 -> 0.00034465363 | G21: 26046.95 | H21: =G21/G20-1 -> 0.0031020858
B22: 45789 | C22: 4189.35 | D22: =C22/C21-1 -> 0.028578794 | E22: =H22-D22 -> -0.023223081 | G22: 26186.45 | H22: =G22/G21-1 -> 0.0053557134
B23: 11/28/2025 | C23: 4250.85 | D23: =C23/C22-1 -> 0.014680082 | E23: =H23-D23 -> -0.014049985 | G23: 26202.95 | H23: =G23/G22-1 -> 0.00063009686
B24: 11/21/2025 | C24: 4360.4 | D24: =C24/C23-1 -> 0.025771316 | E24: =H24-D24 -> -0.030915775 | G24: 26068.15 | H24: =G24/G23-1 -> -0.0051444589
B25: 11/14/2025 | C25: 4389.4 | D25: =C25/C24-1 -> 0.006650766 | E25: =H25-D25 -> -0.012715638 | G25: 25910.05 | H25: =G25/G24-1 -> -0.0060648723
B26: 45849 | C26: 4624.85 | D26: =C26/C25-1 -> 0.053640589 | E26: =H26-D26 -> -0.069763676 | G26: 25492.3 | H26: =G26/G25-1 -> -0.016123087
B27: 10/31/2025 | C27: 4693.6 | D27: =C27/C26-1 -> 0.014865347 | E27: =H27-D27 -> -0.0058508603 | G27: 25722.1 | H27: =G27/G26-1 -> 0.0090144867
B28: 10/24/2025 | C28: 4788.55 | D28: =C28/C27-1 -> 0.020229674 | E28: =H28-D28 -> -0.017389704 | G28: 25795.15 | H28: =G28/G27-1 -> 0.0028399703
B29: 10/17/2025 | C29: 4810.5 | D29: =C29/C28-1 -> 0.0045838511 | E29: =H29-D29 -> -0.0078906742 | G29: 25709.85 | H29: =G29/G28-1 -> -0.0033068232
B30: 45940 | C30: 4689.55 | D30: =C30/C29-1 -> -0.025142917 | E30: =H30-D30 -> 0.008631735 | G30: 25285.35 | H30: =G30/G29-1 -> -0.016511182
B31: 45726 | C31: 4814.9 | D31: =C31/C30-1 -> 0.026729644 | E31: =H31-D31 -> -0.042197098 | G31: 24894.25 | H31: =G31/G30-1 -> -0.015467454
B32: 09/26/2025 | C32: 4681.35 | D32: =C32/C31-1 -> -0.027736817 | E32: =H32-D32 -> 0.018114113 | G32: 24654.7 | H32: =G32/G31-1 -> -0.009622704
B33: 09/19/2025 | C33: 5079.45 | D33: =C33/C32-1 -> 0.085039572 | E33: =H33-D33 -> -0.05776891 | G33: 25327.05 | H33: =G33/G32-1 -> 0.027270662
B34: 46000 | C34: 5128.75 | D34: =C34/C33-1 -> 0.0097057752 | E34: =H34-D34 -> -0.01811773 | G34: 25114 | H34: =G34/G33-1 -> -0.0084119548
B35: 45786 | C35: 5523.8 | D35: =C35/C34-1 -> 0.077026566 | E35: =H35-D35 -> -0.09187884 | G35: 24741 | H35: =G35/G34-1 -> -0.014852274
B36: 08/29/2025 | C36: 5305 | D36: =C36/C35-1 -> -0.039610413 | E36: =H36-D36 -> 0.026912867 | G36: 24426.85 | H36: =G36/G35-1 -> -0.012697547
B37: 08/22/2025 | C37: 5414.6 | D37: =C37/C36-1 -> 0.020659755 | E37: =H37-D37 -> -0.0025137394 | G37: 24870.1 | H37: =G37/G36-1 -> 0.018146016
B38: 08/14/2025 | C38: 5369.15 | D38: =C38/C37-1 -> -0.0083939719 | E38: =H38-D38 -> -0.0012079196 | G38: 24631.3 | H38: =G38/G37-1 -> -0.0096018914
B39: 45877 | C39: 5312 | D39: =C39/C38-1 -> -0.010644143 | E39: =H39-D39 -> -0.00023632217 | G39: 24363.3 | H39: =G39/G38-1 -> -0.010880465
B40: 45665 | C40: 5182.05 | D40: =C40/C39-1 -> -0.024463479 | E40: =H40-D40 -> 0.03275669 | G40: 24565.35 | H40: =G40/G39-1 -> 0.0082932115
B41: 07/25/2025 | C41: 5041.15 | D41: =C41/C40-1 -> -0.027190012 | E41: =H41-D41 -> 0.038248271 | G41: 24837 | H41: =G41/G40-1 -> 0.011058259
B42: 07/18/2025 | C42: 5370.65 | D42: =C42/C41-1 -> 0.06536207 | E42: =H42-D42 -> -0.060071576 | G42: 24968.4 | H42: =G42/G41-1 -> 0.005290494
B43: 45968 | C43: 5352.4 | D43: =C43/C42-1 -> -0.0033980989 | E43: =H43-D43 -> 0.010665285 | G43: 25149.85 | H43: =G43/G42-1 -> 0.0072671857
B44: 45754 | C44: 5448.65 | D44: =C44/C43-1 -> 0.017982587 | E44: =H44-D44 -> -0.0056107441 | G44: 25461 | H44: =G44/G43-1 -> 0.012371843
B45: 06/27/2025 | C45: 6018.2 | D45: =C45/C44-1 -> 0.10453048 | E45: =H45-D45 -> -0.097586527 | G45: 25637.8 | H45: =G45/G44-1 -> 0.0069439535
B46: 06/20/2025 | C46: 5906.95 | D46: =C46/C45-1 -> -0.018485594 | E46: =H46-D46 -> -0.0020075843 | G46: 25112.4 | H46: =G46/G45-1 -> -0.020493178
B47: 06/13/2025 | C47: 5588.65 | D47: =C47/C46-1 -> -0.053885677 | E47: =H47-D47 -> 0.038204181 | G47: 24718.6 | H47: =G47/G46-1 -> -0.015681496
B48: 45814 | C48: 5775.65 | D48: =C48/C47-1 -> 0.033460675 | E48: =H48-D48 -> -0.021953146 | G48: 25003.05 | H48: =G48/G47-1 -> 0.011507529
B49: 05/30/2025 | C49: 5641.65 | D49: =C49/C48-1 -> -0.023200852 | E49: =H49-D49 -> 0.013108083 | G49: 24750.7 | H49: =G49/G48-1 -> -0.010092769
B50: 05/23/2025 | C50: 5433.85 | D50: =C50/C49-1 -> -0.036833196 | E50: =H50-D50 -> 0.040972473 | G50: 24853.15 | H50: =G50/G49-1 -> 0.0041392769
B51: 05/16/2025 | C51: 5584.15 | D51: =C51/C50-1 -> 0.027659946 | E51: =H51-D51 -> -0.020954559 | G51: 25019.8 | H51: =G51/G50-1 -> 0.0067053874
B52: 45905 | C52: 5114.15 | D52: =C52/C51-1 -> -0.084166794 | E52: =H52-D52 -> 0.043726822 | G52: 24008 | H52: =G52/G51-1 -> -0.040439972
B53: 45693 | C53: 5145.75 | D53: =C53/C52-1 -> 0.0061789349 | E53: =H53-D53 -> 0.0079288625 | G53: 24346.7 | H53: =G53/G52-1 -> 0.014107797
B54: 04/25/2025 | C54: 5139.4 | D54: =C54/C53-1 -> -0.0012340281 | E54: =H54-D54 -> -0.011389859 | G54: 24039.35 | H54: =G54/G53-1 -> -0.012623887
B55: 04/17/2025 | C55: 5130.55 | D55: =C55/C54-1 -> -0.0017219909 | E55: =H55-D55 -> -0.0060860405 | G55: 23851.65 | H55: =G55/G54-1 -> -0.0078080314
B56: 45965 | C56: 4780.05 | D56: =C56/C55-1 -> -0.068316262 | E56: =H56-D56 -> 0.025421955 | G56: 22828.55 | H56: =G56/G55-1 -> -0.042894307
B57: 45751 | C57: 5561.25 | D57: =C57/C56-1 -> 0.16342925 | E57: =H57-D57 -> -0.16010447 | G57: 22904.45 | H57: =G57/G56-1 -> 0.0033247841
B58: 03/28/2025 | C58: 5311.05 | D58: =C58/C57-1 -> -0.044989885 | E58: =H58-D58 -> 0.071836197 | G58: 23519.35 | H58: =G58/G57-1 -> 0.026846312
B59: 03/21/2025 | C59: 5147.65 | D59: =C59/C58-1 -> -0.030766044 | E59: =H59-D59 -> 0.023582598 | G59: 23350.4 | H59: =G59/G58-1 -> -0.0071834468
B60: 03/13/2025 | C60: 5025.5 | D60: =C60/C59-1 -> -0.023729275 | E60: =H60-D60 -> -0.017092296 | G60: 22397.2 | H60: =G60/G59-1 -> -0.040821571
B61: 45841 | C61: 4997.35 | D61: =C61/C60-1 -> -0.0056014327 | E61: =H61-D61 -> 0.012535335 | G61: 22552.5 | H61: =G61/G60-1 -> 0.0069339025
B62: 02/28/2025 | C62: 4853.3 | D62: =C62/C61-1 -> -0.028825277 | E62: =H62-D62 -> 0.0098562052 | G62: 22124.7 | H62: =G62/G61-1 -> -0.018969072
B63: 02/21/2025 | C63: 5045.85 | D63: =C63/C62-1 -> 0.039674036 | E63: =H63-D63 -> -0.0093369017 | G63: 22795.9 | H63: =G63/G62-1 -> 0.030337135
B64: 02/14/2025 | C64: 5116.75 | D64: =C64/C63-1 -> 0.014051151 | E64: =H64-D64 -> -0.0082014148 | G64: 22929.25 | H64: =G64/G63-1 -> 0.0058497361
B65: 45840 | C65: 5455.5 | D65: =C65/C64-1 -> 0.066204133 | E65: =H65-D65 -> -0.038697782 | G65: 23559.95 | H65: =G65/G64-1 -> 0.027506351
B66: 01/31/2025 | C66: 5753.8 | D66: =C66/C65-1 -> 0.054678765 | E66: =H66-D66 -> -0.0568668 | G66: 23508.4 | H66: =G66/G65-1 -> -0.0021880352
B67: 01/24/2025 | C67: 5489.7 | D67: =C67/C66-1 -> -0.045900101 | E67: =H67-D67 -> 0.028195791 | G67: 23092.2 | H67: =G67/G66-1 -> -0.01770431
B68: 01/17/2025 | C68: 6214.2 | D68: =C68/C67-1 -> 0.13197442 | E68: =H68-D68 -> -0.12716761 | G68: 23203.2 | H68: =G68/G67-1 -> 0.0048068179
B69: 45931 | C69: 6581.95 | D69: =C69/C68-1 -> 0.059178977 | E69: =H69-D69 -> -0.049339817 | G69: 23431.5 | H69: =G69/G68-1 -> 0.0098391601
B70: 45717 | C70: 7306.6 | D70: =C70/C69-1 -> 0.11009655 | E70: =H70-D70 -> -0.085631622 | G70: 24004.75 | H70: =G70/G69-1 -> 0.02446493
B71: 12/27/2024 | C71: 7118.8 | D71: =C71/C70-1 -> -0.025702789 | E71: =H71-D71 -> 0.01773145 | G71: 23813.4 | H71: =G71/G70-1 -> -0.007971339
B72: 12/20/2024 | C72: 6829 | D72: =C72/C71-1 -> -0.040709108 | E72: =H72-D72 -> 0.031222853 | G72: 23587.5 | H72: =G72/G71-1 -> -0.0094862556
B73: 12/13/2024 | C73: 6998.2 | D73: =C73/C72-1 -> 0.024776688 | E73: =H73-D73 -> 0.025283726 | G73: 24768.3 | H73: =G73/G72-1 -> 0.050060413
B74: 45455 | C74: 7000.4 | D74: =C74/C73-1 -> 0.00031436655 | E74: =H74-D74 -> -0.0039682306 | G74: 24677.8 | H74: =G74/G73-1 -> -0.003653864
B75: 11/29/2024 | C75: 6794.75 | D75: =C75/C74-1 -> -0.029376893 | E75: =H75-D75 -> 0.0072233783 | G75: 24131.1 | H75: =G75/G74-1 -> -0.022153514
B76: 11/22/2024 | C76: 6652.45 | D76: =C76/C75-1 -> -0.02094264 | E76: =H76-D76 -> 0.011666229 | G76: 23907.25 | H76: =G76/G75-1 -> -0.0092764109
B77: 11/14/2024 | C77: 6460.75 | D77: =C77/C76-1 -> -0.028816451 | E77: =H77-D77 -> 0.013149655 | G77: 23532.7 | H77: =G77/G76-1 -> -0.015666796
B78: 45515 | C78: 6299.6 | D78: =C78/C77-1 -> -0.024942925 | E78: =H78-D78 -> 0.051098019 | G78: 24148.2 | H78: =G78/G77-1 -> 0.026155095
B79: 45302 | C79: 7136.75 | D79: =C79/C78-1 -> 0.13288939 | E79: =H79-D79 -> -0.12642307 | G79: 24304.35 | H79: =G79/G78-1 -> 0.0064663205
B80: 10/25/2024 | C80: 7358.9 | D80: =C80/C79-1 -> 0.031127614 | E80: =H80-D80 -> -0.036211066 | G80: 24180.8 | H80: =G80/G79-1 -> -0.0050834521
B81: 10/18/2024 | C81: 7770.3 | D81: =C81/C80-1 -> 0.055905095 | E81: =H81-D81 -> -0.028062757 | G81: 24854.05 | H81: =G81/G80-1 -> 0.027842338
B82: 45606 | C82: 8238.9 | D82: =C82/C81-1 -> 0.060306552 | E82: =H82-D82 -> -0.055872667 | G82: 24964.25 | H82: =G82/G81-1 -> 0.004433885
B83: 45392 | C83: 7361.15 | D83: =C83/C82-1 -> -0.10653728 | E83: =H83-D83 -> 0.10855416 | G83: 25014.6 | H83: =G83/G82-1 -> 0.0020168841
B84: 09/27/2024 | C84: 7823 | D84: =C84/C83-1 -> 0.062741555 | E84: =H84-D84 -> -0.016194739 | G84: 26178.95 | H84: =G84/G83-1 -> 0.046546817
B85: 09/20/2024 | C85: 7479.35 | D85: =C85/C84-1 -> -0.043928161 | E85: =H85-D85 -> 0.029107092 | G85: 25790.95 | H85: =G85/G84-1 -> -0.014821068
B86: 09/13/2024 | C86: 7228.15 | D86: =C86/C85-1 -> -0.033585806 | E86: =H86-D86 -> 0.01674075 | G86: 25356.5 | H86: =G86/G85-1 -> -0.016845056
B87: 45452 | C87: 7092.6 | D87: =C87/C86-1 -> -0.01875307 | E87: =H87-D87 -> -0.0011372938 | G87: 24852.15 | H87: =G87/G86-1 -> -0.019890363
B88: 08/30/2024 | C88: 7167.15 | D88: =C88/C87-1 -> 0.010510955 | E88: =H88-D88 -> 0.0049303649 | G88: 25235.9 | H88: =G88/G87-1 -> 0.01544132
B89: 08/23/2024 | C89: 6950.05 | D89: =C89/C88-1 -> -0.03029098 | E89: =H89-D89 -> 0.013935312 | G89: 24823.15 | H89: =G89/G88-1 -> -0.016355668
B90: 08/16/2024 | C90: 6512.95 | D90: =C90/C89-1 -> -0.062891634 | E90: =H90-D90 -> 0.051531271 | G90: 24541.15 | H90: =G90/G89-1 -> -0.011360363
B91: 45543 | C91: 6276.9 | D91: =C91/C90-1 -> -0.036243177 | E91: =H91-D91 -> 0.029167307 | G91: 24367.5 | H91: =G91/G90-1 -> -0.0070758705
B92: 45330 | C92: 5536.55 | D92: =C92/C91-1 -> -0.11794835 | E92: =H92-D92 -> 0.13231995 | G92: 24717.7 | H92: =G92/G91-1 -> 0.014371602
B93: 07/26/2024 | C93: 5394.9 | D93: =C93/C92-1 -> -0.025584525 | E93: =H93-D93 -> 0.030324043 | G93: 24834.85 | H93: =G93/G92-1 -> 0.0047395186
B94: 07/19/2024 | C94: 5166 | D94: =C94/C93-1 -> -0.042428961 | E94: =H94-D94 -> 0.030190111 | G94: 24530.9 | H94: =G94/G93-1 -> -0.01223885
B95: 45633 | C95: 5647.95 | D95: =C95/C94-1 -> 0.093292683 | E95: =H95-D95 -> -0.094464674 | G95: 24502.15 | H95: =G95/G94-1 -> -0.0011719912
B96: 45419 | C96: 5618.55 | D96: =C96/C95-1 -> -0.0052054285 | E96: =H96-D96 -> -0.0020714839 | G96: 24323.85 | H96: =G96/G95-1 -> -0.0072769124
B97: 06/28/2024 | C97: 5478.45 | D97: =C97/C96-1 -> -0.024935259 | E97: =H97-D97 -> 0.012056952 | G97: 24010.6 | H97: =G97/G96-1 -> -0.012878307
B98: 06/21/2024 | C98: 5266.95 | D98: =C98/C97-1 -> -0.03860581 | E98: =H98-D98 -> 0.017386015 | G98: 23501.1 | H98: =G98/G97-1 -> -0.021219795
B99: 06/14/2024 | C99: 5253.05 | D99: =C99/C98-1 -> -0.0026390985 | E99: =H99-D99 -> 0.0011285309 | G99: 23465.6 | H99: =G99/G98-1 -> -0.0015105676
B100: 45479 | C100: 4971.05 | D100: =C100/C99-1 -> -0.053683098 | E100: =H100-D100 -> 0.046206196 | G100: 23290.15 | H100: =G100/G99-1 -> -0.0074769024
B101: 05/31/2024 | C101: 4551.55 | D101: =C101/C100-1 -> -0.08438861 | E101: =H101-D101 -> 0.051780404 | G101: 22530.7 | H101: =G101/G100-1 -> -0.032608206
B102: 05/24/2024 | C102: 4723.65 | D102: =C102/C101-1 -> 0.037811295 | E102: =H102-D102 -> -0.018886006 | G102: 22957.1 | H102: =G102/G101-1 -> 0.018925289
B103: 05/17/2024 | C103: 4634.45 | D103: =C103/C102-1 -> -0.018883702 | E103: =H103-D103 -> -0.0025040166 | G103: 22466.1 | H103: =G103/G102-1 -> -0.021387719
B104: 45570 | C104: 4471.05 | D104: =C104/C103-1 -> -0.03525769 | E104: =H104-D104 -> 0.016967911 | G104: 22055.2 | H104: =G104/G103-1 -> -0.018289779
B105: 45356 | C105: 4523.05 | D105: =C105/C104-1 -> 0.011630378 | E105: =H105-D105 -> 0.007442222 | G105: 22475.85 | H105: =G105/G104-1 -> 0.0190726
...

Sheet Intrisic Growth
B4: ='Beta-Regression'!$B$2 -> TRENT LTD
B5: ='Beta-Regression'!$B$3 -> ( TRENT | BSE Code: 500251)
B7: ₹ in Crores
B8: Calculation of ROIC | G8: ='Raw FS'!J3 -> 44256 | H8: ='Raw FS'!K3 -> 44621 | I8: ='Raw FS'!L3 -> 44986 | J8: ='Raw FS'!M3 -> 45352 | K8: ='Raw FS'!N3 -> 45717
B10: Current Assets
B11: ='Raw FS'!B35 -> Inventories | G11: ='Raw FS'!J35 -> 428 | H11: ='Raw FS'!K35 -> 868 | I11: ='Raw FS'!L35 -> 1361 | J11: ='Raw FS'!M35 -> 1583 | K11: ='Raw FS'!N35 -> 2045 | M11: roic = return on investment capital
B12: ='Raw FS'!B36 -> Trade receivables | G12: ='Raw FS'!J36 -> 21 | H12: ='Raw FS'!K36 -> 18 | I12: ='Raw FS'!L36 -> 34 | J12: ='Raw FS'!M36 -> 82 | K12: ='Raw FS'!N36 -> 63 | M12: in simple word
B13: ='Raw FS'!B38 -> Loans n Advances | G13: ='Raw FS'!J38 -> 25 | H13: ='Raw FS'!K38 -> 29 | I13: ='Raw FS'!L38 -> 29 | J13: ='Raw FS'!M38 -> 35 | K13: ='Raw FS'!N38 -> 17 | M13: reinvest
B14: ='Raw FS'!B39 -> Other asset items | G14: ='Raw FS'!J39 -> 519 | H14: ='Raw FS'!K39 -> 650 | I14: ='Raw FS'!L39 -> 832 | J14: ='Raw FS'!M39 -> 1075 | K14: ='Raw FS'!N39 -> 1400 | M14: growth | O14: BxR | P14: growth for equity share
B15: Total Current Assets | G15: =SUM(G11:G14) -> 993 | H15: =SUM(H11:H14) -> 1565 | I15: =SUM(I11:I14) -> 2256 | J15: =SUM(J11:J14) -> 2775 | K15: =SUM(K11:K14) -> 3525 | M15: ROC>COC
B17: Current Liabilties
B18: ='Raw FS'!B14 -> Trade Payables | G18: ='Raw FS'!J14 -> 275 | H18: ='Raw FS'!K14 -> 378 | I18: ='Raw FS'!L14 -> 665 | J18: ='Raw FS'!M14 -> 774 | K18: ='Raw FS'!N14 -> 928
B19: ='Raw FS'!B15 -> Other liability items | G19: ='Raw FS'!J15 -> 2792 | H19: ='Raw FS'!K15 -> 213 | I19: ='Raw FS'!L15 -> 289 | J19: ='Raw FS'!M15 -> 532 | K19: ='Raw FS'!N15 -> 671
B20: Total Current Liabilties | G20: =SUM(G18:G19) -> 3067 | H20: =SUM(H18:H19) -> 591 | I20: =SUM(I18:I19) -> 954 | J20: =SUM(J18:J19) -> 1306 | K20: =SUM(K18:K19) -> 1599
A22: # | B22: Net Working Capital | G22: =G15-G20 -> -2074 | H22: =H15-H20 -> 974 | I22: =I15-I20 -> 1302 | J22: =J15-J20 -> 1469 | K22: =K15-K20 -> 1926
B24: Non Current Assets
B25: ='Raw FS'!B19 -> Land | G25: ='Raw FS'!J19 -> 63 | H25: ='Raw FS'!K19 -> 62 | I25: ='Raw FS'!L19 -> 77 | J25: ='Raw FS'!M19 -> 86 | K25: ='Raw FS'!N19 -> 86
B26: ='Raw FS'!B20 -> Building | G26: ='Raw FS'!J20 -> 3117 | H26: ='Raw FS'!K20 -> 4893 | I26: ='Raw FS'!L20 -> 4855 | J26: ='Raw FS'!M20 -> 2162 | K26: ='Raw FS'!N20 -> 3664
B27: ='Raw FS'!B21 -> Plant Machinery | G27: ='Raw FS'!J21 -> 168 | H27: ='Raw FS'!K21 -> 221 | I27: ='Raw FS'!L21 -> 287 | J27: ='Raw FS'!M21 -> 437 | K27: ='Raw FS'!N21 -> 825
B28: ='Raw FS'!B22 -> Equipments | G28: ='Raw FS'!J22 -> 30 | H28: ='Raw FS'!K22 -> 33 | I28: ='Raw FS'!L22 -> 39 | J28: ='Raw FS'!M22 -> 44 | K28: ='Raw FS'!N22 -> 56
B29: ='Raw FS'!B23 -> Computers | G29: ='Raw FS'!J23 -> 59 | H29: ='Raw FS'!K23 -> 70 | I29: ='Raw FS'!L23 -> 98 | J29: ='Raw FS'!M23 -> 112 | K29: ='Raw FS'!N23 -> 175
B30: ='Raw FS'!B24 -> Furniture n fittings | G30: ='Raw FS'!J24 -> 192 | H30: ='Raw FS'!K24 -> 225 | I30: ='Raw FS'!L24 -> 328 | J30: ='Raw FS'!M24 -> 486 | K30: ='Raw FS'!N24 -> 758
B31: ='Raw FS'!B25 -> Vehicles | G31: ='Raw FS'!J25 -> 3 | H31: ='Raw FS'!K25 -> 3 | I31: ='Raw FS'!L25 -> 3 | J31: ='Raw FS'!M25 -> 3 | K31: ='Raw FS'!N25 -> 4
B32: ='Raw FS'!B26 -> Intangible Assets | G32: ='Raw FS'!J26 -> 62 | H32: ='Raw FS'!K26 -> 62 | I32: ='Raw FS'!L26 -> 62 | J32: ='Raw FS'!M26 -> 62 | K32: ='Raw FS'!N26 -> 62
B33: ='Raw FS'!B27 -> Other fixed assets | G33: ='Raw FS'!J27 -> 70 | H33: ='Raw FS'!K27 -> 78 | I33: ='Raw FS'!L27 -> 92 | J33: ='Raw FS'!M27 -> 92 | K33: ='Raw FS'!N27 -> 98
B34: ='Raw FS'!B28 -> Gross Block | G34: =SUM(G25:G33) -> 3764 | H34: =SUM(H25:H33) -> 5647 | I34: =SUM(I25:I33) -> 5841 | J34: =SUM(J25:J33) -> 3484 | K34: =SUM(K25:K33) -> 5728
B35: ='Raw FS'!B29 -> Accumulated Depreciation | G35: =-'Raw FS'!J29 -> -711 | H35: =-'Raw FS'!K29 -> -961 | I35: =-'Raw FS'!L29 -> -1314 | J35: =-'Raw FS'!M29 -> -1035 | K35: =-'Raw FS'!N29 -> -1835
A36: # | B36: Net Non Current Assets | G36: =SUM(G34:G35) -> 3053 | H36: =SUM(H34:H35) -> 4686 | I36: =SUM(I34:I35) -> 4527 | J36: =SUM(J34:J35) -> 2449 | K36: =SUM(K34:K35) -> 3893
B38: Invested Capital | G38: =G22+G36 -> 979 | H38: =H22+H36 -> 5660 | I38: =I22+I36 -> 5829 | J38: =J22+J36 -> 3918 | K38: =K22+K36 -> 5819
B39: EBIT | G39: =HistoricalFS!H28 -> -143.43 | H39: =HistoricalFS!I34+HistoricalFS!I25 -> 269.88 | I39: =HistoricalFS!J34+HistoricalFS!J25 -> 705.16 | J39: =HistoricalFS!K34+HistoricalFS!K25 -> 1603.03 | K39: =HistoricalFS!L34+HistoricalFS!L25 -> 2619.86
B41: ROIC | G41: =G39/G38 -> -0.14650664 | H41: =H39/H38 -> 0.047681979 | I41: =I39/I38 -> 0.12097444 | J41: =J39/J38 -> 0.40914497 | K41: =K39/K38 -> 0.45022512
B43: Calculation Of Reinvestment Rate | G43: =G8 -> 44256 | H43: =H8 -> 44621 | I43: =I8 -> 44986 | J43: =J8 -> 45352 | K43: =K8 -> 45717
B45: Net Capex | G45: =-SUM('Raw FS'!J55:J56) -> 91 | H45: =-SUM('Raw FS'!K55:K56) -> 210 | I45: =-SUM('Raw FS'!L55:L56) -> 223 | J45: =-SUM('Raw FS'!M55:M56) -> 394 | K45: =-SUM('Raw FS'!N55:N56) -> 861
B46: Change in capital working | H46: =H22-G22 -> 3048 | I46: =I45-H45 -> 13 | J46: =J45-I45 -> 171 | K46: =K45-J45 -> 467
B47: EBIT | H47: =H39 -> 269.88 | I47: =I39 -> 705.16 | J47: =J39 -> 1603.03 | K47: =K39 -> 2619.86
B48: Marginal Tax Rate | H48: =Tax_rate -> 0.25 | I48: =Tax_rate -> 0.25 | J48: =Tax_rate -> 0.25 | K48: =Tax_rate -> 0.25
B49: EBIT(1- T) | H49: =H47*(1-H48) -> 202.41 | I49: =I47*(1-I48) -> 528.87 | J49: =J47*(1-J48) -> 1202.2725 | K49: =K47*(1-K48) -> 1964.895
B50: Reinvestment | H50: =SUM(H45:H46) -> 3258 | I50: =SUM(I45:I46) -> 236 | J50: =SUM(J45:J46) -> 565 | K50: =SUM(K45:K46) -> 1328
B51: Reinvestmet Rate | H51: =H50/H49 -> 16.096043 | I51: =I50/I49 -> 0.44623442 | J51: =J50/J49 -> 0.46994338 | K51: =K50/K49 -> 0.67586309
J53: 4Years Avarage | K53: =AVERAGE(H51:K51) -> 4.4220209
J54: 4Years Median | K54: =MEDIAN(H51:K51) -> 0.57290323
B56: Caliculation Of Growth Rate | G56: =G43 -> 44256 | H56: =H43 -> 44621 | I56: =I43 -> 44986 | J56: =J43 -> 45352 | K56: =K43 -> 45717
B58: =B51 -> Reinvestmet Rate | H58: =H51 -> 16.096043 | I58: =I51 -> 0.44623442 | J58: =J51 -> 0.46994338 | K58: =K51 -> 0.67586309
B59: =B41 -> ROIC | H59: =H41 -> 0.047681979 | I59: =I41 -> 0.12097444 | J59: =J41 -> 0.40914497 | K59: =K41 -> 0.45022512
B61: Inrensic Growth | H61: =H58*H59 -> 0.76749117 | I61: =I58*I59 -> 0.053982959 | J61: =J58*J59 -> 0.19227497 | K61: =K58*K59 -> 0.30429054
J63: 4years Avarage | K63: =AVERAGE(H61:K61) -> 0.32950991
J64: 4years median | K64: =MEDIAN(H61:K61) -> 0.24828276

Sheet Raw FS
B3: Particular | C3: 41699 | D3: 42064 | E3: 42430 | F3: 42795 | G3: 43160 | H3: 43525 | I3: 43891 | J3: 44256 | K3: 44621 | L3: 44986 | M3: 45352 | N3: 45717 | O3: 45901
B4: - | C4: - | D4: - | E4: - | F4: - | G4: - | H4: - | I4: - | J4: - | K4: - | L4: - | M4: - | N4: - | O4: -
B5: Equity Capital | C5: 33 | D5: 33 | E5: 33 | F5: 33 | G5: 33 | H5: 33 | I5: 36 | J5: 36 | K5: 36 | L5: 36 | M5: 36 | N5: 36 | O5: 36
B6: Reserves | C6: 958 | D6: 1389 | E6: 1431 | F6: 1514 | G6: 1562 | H6: 1613 | I6: 2352 | J6: 2277 | K6: 2328 | L6: 2560 | M6: 4032 | N6: 5426 | O6: 6066
B7: Borrowings -
B8: Long term Borrowings | C8: 325 | D8: 112 | E8: 96 | H8: 300 | I8: 300 | J8: 0 | K8: 497 | L8: 498 | M8: 499 | N8: 499 | O8: 0
B9: Short term Borrowings | C9: 7 | D9: 4 | E9: 4 | H9: 95 | I9: 0 | J9: 300 | K9: 0 | L9: 0 | M9: 0 | N9: 0 | O9: 500
B10: Lease Liabilities | C10: 0 | D10: 0 | E10: 0 | F10: 0 | G10: 0 | H10: 0 | I10: 0 | J10: 2664 | K10: 4228 | L10: 3966 | M10: 1254 | N10: 1738 | O10: 1849
B11: Other Borrowings | C11: 0 | D11: 150 | E11: 300 | F11: 392 | G11: 391 | H11: 100 | I11: 0 | J11: -2664 | K11: 0 | L11: 0 | M11: 0 | N11: 0
B12: Other Liabilities -
B13: Non controlling int | C13: 3 | D13: 3 | E13: 10 | F13: 1 | G13: 1 | H13: -3 | I13: 80 | J13: 44 | K13: 46 | L13: 67 | M13: 35 | N13: 122 | O13: 113
B14: Trade Payables | C14: 331 | D14: 221 | E14: 166 | F14: 169 | G14: 208 | H14: 245 | I14: 298 | J14: 275 | K14: 378 | L14: 665 | M14: 774 | N14: 928 | O14: 1486
B15: Other liability items | C15: 280 | D15: 294 | E15: 116 | F15: 113 | G15: 140 | H15: 176 | I15: 2442 | J15: 2792 | K15: 213 | L15: 289 | M15: 532 | N15: 671 | O15: 686
B16: Total Liabilities | C16: 1936 | D16: 2207 | E16: 2157 | F16: 2222 | G16: 2336 | H16: 2559 | I16: 5507 | J16: 5724 | K16: 7726 | L16: 8082 | M16: 7162 | N16: 9420 | O16: 10735
B18: Fixed Assets -
B19: Land | C19: 63 | D19: 101 | E19: 58 | F19: 58 | G19: 61 | H19: 63 | I19: 63 | J19: 63 | K19: 62 | L19: 77 | M19: 86 | N19: 86
B20: Building | C20: 272 | D20: 232 | E20: 291 | F20: 326 | G20: 360 | H20: 382 | I20: 2622 | J20: 3117 | K20: 4893 | L20: 4855 | M20: 2162 | N20: 3664
B21: Plant Machinery | C21: 158 | D21: 99 | E21: 105 | F21: 116 | G21: 119 | H21: 134 | I21: 158 | J21: 168 | K21: 221 | L21: 287 | M21: 437 | N21: 825 | O21: -
B22: Equipments | C22: 10 | D22: 9 | E22: 11 | F22: 14 | G22: 16 | H22: 23 | I22: 29 | J22: 30 | K22: 33 | L22: 39 | M22: 44 | N22: 56 | O22: -
B23: Computers | C23: 50 | D23: 38 | E23: 38 | F23: 40 | G23: 42 | H23: 49 | I23: 58 | J23: 59 | K23: 70 | L23: 98 | M23: 112 | N23: 175 | O23: -
B24: Furniture n fittings | C24: 160 | D24: 122 | E24: 132 | F24: 138 | G24: 145 | H24: 164 | I24: 183 | J24: 192 | K24: 225 | L24: 328 | M24: 486 | N24: 758 | O24: -
B25: Vehicles | C25: 1 | D25: 1 | E25: 1 | F25: 1 | G25: 1 | H25: 1 | I25: 3 | J25: 3 | K25: 3 | L25: 3 | M25: 3 | N25: 4 | O25: -
B26: Intangible Assets | C26: 81 | D26: 26 | E26: 26 | F26: 26 | G26: 55 | H26: 55 | I26: 62 | J26: 62 | K26: 62 | L26: 62 | M26: 62 | N26: 62 | O26: 72
B27: Other fixed assets | C27: 150 | D27: 322 | E27: 18 | F27: 56 | G27: 63 | H27: 66 | I27: 69 | J27: 70 | K27: 78 | L27: 92 | M27: 92 | N27: 98 | O27: -
B28: Gross Block | C28: 946 | D28: 951 | E28: 680 | F28: 775 | G28: 860 | H28: 938 | I28: 3246 | J28: 3764 | K28: 5647 | L28: 5840 | M28: 3485 | N28: 5730 | O28: -
B29: Accumulated Depreciation | C29: 226 | D29: 282 | E29: 203 | F29: 227 | G29: 248 | H29: 276 | I29: 508 | J29: 711 | K29: 961 | L29: 1314 | M29: 1035 | N29: 1835 | O29: -
B30: Net Block | C30: =C28-C29 -> 720 | D30: =D28-D29 -> 669 | E30: =E28-E29 -> 477 | F30: =F28-F29 -> 548 | G30: =G28-G29 -> 612 | H30: =H28-H29 -> 662 | I30: =I28-I29 -> 2738 | J30: =J28-J29 -> 3053 | ... N30: =N28-N29 -> 3895 | O30: -
B31: - | C31: - | D31: - | E31: - | F31: - | G31: - | H31: - | I31: - | J31: - | K31: - | L31: - | M31: - | N31: - | O31: -
B32: CWIP | C32: 138 | D32: 92 | E32: 55 | F32: 5 | G32: 10 | H32: 87 | I32: 23 | J32: 108 | K32: 105 | L32: 102 | M32: 224 | N32: 180 | O32: 196
B33: Investments | C33: 300 | D33: 740 | E33: 1067 | F33: 1080 | G33: 1023 | H33: 883 | I33: 1515 | J33: 1487 | K33: 1284 | L33: 1110 | M33: 1416 | N33: 1480 | O33: 1559
B34: Other Assets - | C34: - | D34: - | E34: - | F34: - | G34: - | H34: - | I34: - | J34: - | K34: - | L34: - | M34: - | N34: - | O34: -
B35: Inventories | C35: 356 | D35: 330 | E35: 279 | F35: 305 | G35: 345 | H35: 497 | I35: 608 | J35: 428 | K35: 868 | L35: 1361 | M35: 1583 | N35: 2045 | O35: 2242
B36: Trade receivables | C36: 18 | D36: 18 | E36: 13 | F36: 6 | G36: 15 | H36: 17 | I36: 17 | J36: 21 | K36: 18 | L36: 34 | M36: 82 | N36: 63 | O36: 59
B37: Cash Equivalents | C37: 62 | D37: 56 | E37: 27 | F37: 34 | G37: 33 | H37: 54 | I37: 61 | J37: 81 | K37: 86 | L37: 86 | M37: 298 | N37: 340 | O37: 195
B38: Loans n Advances | C38: 59 | D38: 31 | E38: 16 | F38: 9 | G38: 12 | H38: 26 | I38: 102 | J38: 25 | K38: 29 | L38: 29 | M38: 35 | N38: 17 | O38: 687
B39: Other asset items | C39: 283 | D39: 272 | E39: 223 | F39: 233 | G39: 286 | H39: 332 | I39: 442 | J39: 519 | K39: 650 | L39: 832 | M39: 1075 | N39: 1400 | O39: 1211
B40: Total Assets | C40: 1936 | D40: 2207 | E40: 2157 | F40: 2222 | G40: 2336 | H40: 2559 | I40: 5507 | J40: 5724 | K40: 7726 | L40: 8082 | M40: 7162 | N40: 9420 | O40: 10735
C44: 41699 | D44: 42064 | E44: 42430 | F44: 42795 | G44: 43160 | H44: 43525 | I44: 43891 | J44: 44256 | K44: 44621 | L44: 44986 | M44: 45352 | N44: 45717
B45: Cash from Operating Activity - | C45: -46 | D45: -10 | E45: 109 | F45: 102 | G45: 77 | H45: 21 | I45: 361 | J45: 285 | K45: 58 | L45: 595 | M45: 1349 | N45: 1661
B46: Profit from operations | C46: 32 | D46: 65 | E46: 98 | F46: 165 | G46: 191 | H46: 233 | I46: 542 | J46: 180 | K46: 569 | L46: 1079 | M46: 1919 | N46: 2723
B47: Receivables | C47: -8 | D47: -19 | E47: -1 | F47: 24 | G47: -54 | H47: -11 | I47: -20 | J47: -39 | K47: -103 | L47: -101 | M47: -208 | N47: -203
B48: Inventory | C48: -25 | D48: -3 | E48: -19 | F48: -26 | G48: -39 | H48: -152 | I48: -89 | J48: 179 | K48: -439 | L48: -494 | M48: -222 | N48: -462
B49: Payables | C49: -14 | D49: -6 | E49: 27 | F49: -9 | G49: 43 | H49: 49 | I49: 26 | J49: -11 | K49: 134 | L49: 332 | M49: 178 | N49: 212
B50: Other WC items | C50: -7 | D50: -34 | E50: 24 | F50: -12 | G50: -13 | H50: -21 | I50: -15 | J50: -23 | K50: -22 | L50: -30 | M50: -20 | N50: -115
B51: Working capital changes | C51: -54 | D51: -61 | E51: 31 | F51: -24 | G51: -64 | H51: -135 | I51: -97 | J51: 106 | K51: -430 | L51: -293 | M51: -272 | N51: -568
B52: Interest paid | C52: 0 | D52: 0 | E52: 0 | F52: 0 | G52: 0 | H52: 0 | I52: 0 | J52: 0 | K52: 0 | L52: 0 | M52: 0 | N52: 0
B53: Direct taxes | C53: -23 | D53: -13 | E53: -20 | F53: -38 | G53: -50 | H53: -77 | I53: -83 | J53: -1 | K53: -82 | L53: -191 | M53: -299 | N53: -494
B54: Cash from Investing Activity - | C54: -48 | D54: -306 | E54: -98 | F54: -44 | G54: -4 | H54: -37 | I54: -809 | J54: 18 | K54: 56 | L54: -103 | M54: -508 | N54: -923
B55: Fixed assets purchased | C55: -136 | D55: -158 | E55: -139 | F55: -71 | G55: -107 | H55: -203 | I55: -156 | J55: -113 | K55: -271 | L55: -503 | M55: -737 | N55: -1268
B56: Fixed assets sold | C56: 0 | D56: 2 | E56: 8 | F56: 2 | G56: 1 | H56: 7 | I56: 42 | J56: 22 | K56: 61 | L56: 280 | M56: 343 | N56: 407
... B74: Net Cash Flow | C74: -145 | D74: -6 | E74: -2 | F74: 7 | G74: -1 | H74: 21 | I74: 5 | J74: 20 | K74: 6 | L74: 1 | M74: 211 | N74: 44

Sheet Comps Analysis
B6: ='Historical Apporoach'!B4 -> TRENT LTD
B7: ='Historical Apporoach'!B5 -> ( TRENT | BSE Code: 500251)
B9: Comparable Company Valuation
F11: Market Data | K11: Financials | O11: Valuation
B12: Company | C12: Ticker | D12: Share Price | E12: Share Outstanding | F12: Equity Vaule | G12: Net Debt | H12: Enterprice Vlaue | J12: Revenue | K12: EBITDA | L12: Net Income | N12: EV/Revenue | O12: EV/EBITDA | P12: P/E
B14: ='Realtive Data'!C3 -> Trent | C14: TRENT | D14: =IFERROR('Realtive Data'!D3,0) -> 4252 | E14: =IFERROR('Realtive Data'!E3,0) -> 35.55 | F14: =E14*D14 -> 151158.6 | G14: ='Realtive Data'!I3 -> 2008.73 | H14: =F14+G14 -> 153167.33 | J14: ='Realtive Data'!K3 -> 19263.16 | K14: ='Realtive Data'!M3 -> 4100 | L14: ='Realtive Data'!N3 -> 1619.83 | N14: =$H14/J14 -> 7.9513086 | O14: =$H14/K14 -> 37.357885 | P14: =F14/L14 -> 93.31757
B15: ='Realtive Data'!C4 -> Avenue Super. | C15: DMART | D15: =IFERROR('Realtive Data'!D4,0) -> 3909.2 | E15: =IFERROR('Realtive Data'!E4,0) -> 65.07 | F15: =E15*D15 -> 254371.64 | G15: ='Realtive Data'!I4 -> 255783.91 | H15: =F15+G15 -> 510155.55 | J15: ='Realtive Data'!K4 -> 66008.74 | K15: ='Realtive Data'!M4 -> 9600 | L15: ='Realtive Data'!N4 -> 2864.23 | N15: =$H15/J15 -> 7.7286062 | O15: =$H15/K15 -> 53.141204 | P15: =F15/L15 -> 88.809783
B16: ='Realtive Data'!C5 -> Page Industries | C16: PAGEIND | D16: =IFERROR('Realtive Data'!D5,0) -> 33530 | E16: =IFERROR('Realtive Data'!E5,0) -> 1.12 | F16: =E16*D16 -> 37553.6 | G16: ='Realtive Data'!I5 -> -203.25 | H16: =F16+G16 -> 37350.35 | J16: ='Realtive Data'!K5 -> 5092.25 | K16: ='Realtive Data'!M5 -> 1250 | L16: ='Realtive Data'!N5 -> 749.11 | N16: =$H16/J16 -> 7.334744 | O16: =$H16/K16 -> 29.88028 | P16: =F16/L16 -> 50.130955
B17: ='Realtive Data'!C6 -> Vedant Fashions | C17: MANYAVAR | D17: =IFERROR('Realtive Data'!D6,0) -> 455.3 | E17: =IFERROR('Realtive Data'!E6,0) -> 24.3 | F17: =E17*D17 -> 11063.79 | G17: ='Realtive Data'!I6 -> 446.53 | H17: =F17+G17 -> 11510.32 | J17: ='Realtive Data'!K6 -> 1403.49 | K17: ='Realtive Data'!M6 -> 730 | L17: ='Realtive Data'!N6 -> 362.35 | N17: =$H17/J17 -> 8.2012127 | O17: =$H17/K17 -> 15.767562 | P17: =F17/L17 -> 30.533435
B18: ='Realtive Data'!C7 -> V2 Retail | C18: V2RETAIL | D18: =IFERROR('Realtive Data'!D7,0) -> 2031.2 | E18: =IFERROR('Realtive Data'!E7,0) -> 3.65 | F18: =E18*D18 -> 7413.88 | G18: ='Realtive Data'!I7 -> 1303.1 | H18: =F18+G18 -> 8716.98 | J18: ='Realtive Data'!K7 -> 2768.55 | K18: ='Realtive Data'!M7 -> 320 | L18: ='Realtive Data'!N7 -> 150.4 | N18: =$H18/J18 -> 3.1485724 | O18: =$H18/K18 -> 27.240562 | P18: =F18/L18 -> 49.294415
B21: High | N21: =MAX(N14:N19) -> 8.2012127 | O21: =MAX(O14:O19) -> 53.141204 | P21: =MAX(P14:P19) -> 93.31757
B22: 75th percentile | N22: =QUARTILE(N14:N19,3) -> 7.9513086 | O22: =QUARTILE(O14:O19,3) -> 37.357885 | P22: =QUARTILE(P14:P19,3) -> 88.809783
B23: Average | N23: =AVERAGE(N14:N18) -> 6.8728888 | O23: =AVERAGE(O14:O18) -> 32.677499 | P23: =AVERAGE(P14:P18) -> 62.417232
B24: Median | N24: =MEDIAN(N14:N18) -> 7.7286062 | O24: =MEDIAN(O14:O18) -> 29.88028 | P24: =MEDIAN(P14:P18) -> 50.130955
B25: 25th percentile | N25: =QUARTILE(N14:N19,1) -> 7.334744 | O25: =QUARTILE(O14:O19,1) -> 27.240562 | P25: =QUARTILE(P14:P19,1) -> 49.294415
B26: Low | N26: =MIN(N14:N19) -> 3.1485724 | O26: =MIN(O14:O19) -> 15.767562 | P26: =MIN(P14:P19) -> 30.533435
B29: Trent Comparble Valuation | N29: EV/Revenue | O29: EV/EBITDA | P29: P/E
B31: Implied Enterprise Value | N31: =J14*N24 -> 148877.38 | O31: =K14*O24 -> 122509.15 | P31: =P33+P32 -> 83212.355
B32: Net Debt | N32: =$G$14 -> 2008.73 | O32: =$G$14 -> 2008.73 | P32: =$G$14 -> 2008.73
B33: Implied Equity Value | N33: =N31-N32 -> 146868.65 | O33: =O31-O32 -> 120500.42 | P33: =P24*L14 -> 81203.625
B34: Share Outstanding | N34: =$E$14 -> 35.55 | O34: =$E$14 -> 35.55 | P34: =$E$14 -> 35.55
B36: Implied Value per share | N36: =N33/N34 -> 4131.3262 | O36: =O33/O34 -> 3389.6039 | P36: =P33/P34 -> 2284.2089
B38: Sourse: screnner | N38: =IF(N36>$D14,"Undervalued","Overvalued") -> Overvalued | O38: =IF(O36>$D14,"Undervalued","Overvalued") -> Overvalued | P38: =IF(P36>$D14,"Undervalued","Overvalued") -> Overvalued

Sheet Football Field
L4: Football Field Analysis - Data
M5: OpenLow | N5: Low | O5: OpenHigh | P5: High
L6: Comps | M6: ='Comps Analysis'!P36 -> 2284.2089 | N6: =M6 -> 2284.2089 | O6: =P6 -> 4131.3262 | P6: ='Comps Analysis'!N36 -> 4131.3262
L7: DCF Bear | M7: =N7 -> 547.6846 | N7: =DCF!I51 -> 547.6846 | O7: =P7 -> 678.66704 | P7: =DCF!I55 -> 678.66704
L8: DCF Base | M8: =N8 -> 1099.4358 | N8: =DCF!G51 -> 1099.4358 | O8: =P8 -> 2071.1695 | P8: =DCF!G55 -> 2071.1695
L9: DCF Bull | M9: =N9 -> 690.34047 | N9: =DCF!F51 -> 690.34047 | O9: =P9 -> 936.51165 | P9: =DCF!F55 -> 936.51165
L10: 52W H/L | M10: =N10 -> 3645 | N10: 3645 | O10: =P10 -> 6261 | P10: 6261

Sheet Dupont Analysis
B3: ='List of Stock'!A388 -> TRENT LTD
B4: =CONCATENATE("( ",VLOOKUP(B3,'List of Stock'!A2:C5442,3,1)," | ","BSE Code: ",VLOOKUP(B3,'List of Stock'!A2:B5442,2,1),")") -> ( TRENT | BSE Code: 500251) | K4: ( TRENT | BSE Code: 500251)
B5: =CONCATENATE(" ","INR "&'Data Sheet'!B8) -> INR 4285.6
B6: 52 Week (High - INR 6,261 & Low - 3,645)
B8: About the Company
B9: Trent Ltd is engaged in retailing of apparels, footwear, accessories, toys, games, food, grocery & non food products through various of its retail formats/ concepts
B11: Financial Summary
O49: 1
O54: average shareholder equity = take data from balance sheet
O55: ((current year EQ capital + Reserve)+(last years EQ capital + Reserve)/2
O56: 2
O57: ROE = AVE - net profit
O58: 3
O59: NPM = net profit / revenue
O60: 4
B61: Rreturn on Equity (ROE) | O61: average total asset = (current years total asset + last years)/2
C62: =HistoricalFS!F7 -> 43555 | D62: =HistoricalFS!G7 -> 43921 | E62: =HistoricalFS!H7 -> 44286 | F62: =HistoricalFS!I7 -> 44651 | G62: =HistoricalFS!J7 -> 45016 | H62: =HistoricalFS!K7 -> 45382 | I62: =HistoricalFS!L7 -> 45747 | O62: B) Asset turnover ratio = revenue/ATA
B63: Net Profit | C63: ='Data Sheet'!E30 -> 96.96 | D63: ='Data Sheet'!F30 -> 122.85 | E63: ='Data Sheet'!G30 -> -146.17 | F63: ='Data Sheet'!H30 -> 105.83 | G63: ='Data Sheet'!I30 -> 444.63 | H63: ='Data Sheet'!J30 -> 1486.8 | I63: ='Data Sheet'!K30 -> 1546.72 | O63: whatever percentage will get convert into numver and then but "x"end that numbers
B64: Average Shareholder Equity | C64: =(('Data Sheet'!E57+'Data Sheet'!E58)+('Data Sheet'!D57+'Data Sheet'!D58))/2 -> 1620.94 | D64: =(('Data Sheet'!F57+'Data Sheet'!F58)+('Data Sheet'!E57+'Data Sheet'!E58))/2 -> 2017.14 | E64: =(('Data Sheet'!G57+'Data Sheet'!G58)+('Data Sheet'!F57+'Data Sheet'!F58))/2 -> 2350.4 | F64: =(('Data Sheet'!H57+'Data Sheet'!H58)+('Data Sheet'!G57+'Data Sheet'!G58))/2 -> 2338.515 | G64: =(('Data Sheet'!I57+'Data Sheet'!I58)+('Data Sheet'!H57+'Data Sheet'!H58))/2 -> 2479.745 | H64: =(('Data Sheet'!J57+'Data Sheet'!J58)+('Data Sheet'!I57+'Data Sheet'!I58))/2 -> 3331.615 | I64: =(('Data Sheet'!K57+'Data Sheet'!K58)+('Data Sheet'!J57+'Data Sheet'!J58))/2 -> 4764.74
B65: Return on Equity (ROE) | C65: =C63/C64 -> 0.059817143 | D65: =D63/D64 -> 0.060903061 | E65: =E63/E64 -> -0.062189415 | F65: =F63/F64 -> 0.045255215 | G65: =G63/G64 -> 0.17930473 | H65: =H63/H64 -> 0.44627005 | I65: =I63/I64 -> 0.32461792
B67: ROE - Dupont Equation
C68: =C62 -> 43555 | D68: =D62 -> 43921 | E68: =E62 -> 44286 | F68: =F62 -> 44651 | G68: =G62 -> 45016 | H68: =H62 -> 45382 | I68: =I62 -> 45747
B69: =B63 -> Net Profit | C69: =C63 -> 96.96 | D69: =D63 -> 122.85 | E69: =E63 -> -146.17 | F69: =F63 -> 105.83 | G69: =G63 -> 444.63 | H69: =H63 -> 1486.8 | I69: =I63 -> 1546.72
B70: Revenue | C70: ='Data Sheet'!E17 -> 2630.24 | D70: ='Data Sheet'!F17 -> 3485.98 | E70: ='Data Sheet'!G17 -> 2592.96 | F70: ='Data Sheet'!H17 -> 4498.02 | G70: ='Data Sheet'!I17 -> 8242.02 | H70: ='Data Sheet'!J17 -> 12375.11 | I70: ='Data Sheet'!K17 -> 17134.61
B71: Net Profit Margin (A) | C71: =C69/C70 -> 0.036863556 | D71: =D69/D70 -> 0.035241166 | E71: =E69/E70 -> -0.056371868 | F71: =F69/F70 -> 0.02352813 | G71: =G69/G70 -> 0.053946727 | H71: =H69/H70 -> 0.12014439 | I71: =I69/I70 -> 0.09026876
B73: Revenue | C73: =C70 -> 2630.24 | D73: =D70 -> 3485.98 | E73: =E70 -> 2592.96 | F73: =F70 -> 4498.02 | G73: =G70 -> 8242.02 | H73: =H70 -> 12375.11 | I73: =I70 -> 17134.61
B74: Average Totoal Asset | C74: =('Data Sheet'!E66+'Data Sheet'!D66)/2 -> 2447.31 | D74: =('Data Sheet'!F66+'Data Sheet'!E66)/2 -> 4032.72 | E74: =('Data Sheet'!G66+'Data Sheet'!F66)/2 -> 5615.205 | F74: =('Data Sheet'!H66+'Data Sheet'!G66)/2 -> 6724.875 | G74: =('Data Sheet'!I66+'Data Sheet'!H66)/2 -> 7903.775 | H74: =('Data Sheet'!J66+'Data Sheet'!I66)/2 -> 7621.64 | I74: =('Data Sheet'!K66+'Data Sheet'!J66)/2 -> 8290.695
B75: Asset Turnover Ratio (B) | C75: =C73/C74 -> 1.0747474 | D75: =D73/D74 -> 0.86442401 | E75: =E73/E74 -> 0.46177477 | F75: =F73/F74 -> 0.66886299 | G75: =G73/G74 -> 1.0427954 | H75: =H73/H74 -> 1.6236807 | I75: =I73/I74 -> 2.0667278
B77: =B74 -> Average Totoal Asset | C77: =C74 -> 2447.31 | D77: =D74 -> 4032.72 | E77: =E74 -> 5615.205 | F77: =F74 -> 6724.875 | G77: =G74 -> 7903.775 | H77: =H74 -> 7621.64 | I77: =I74 -> 8290.695
B78: =B64 -> Average Shareholder Equity | C78: =C64 -> 1620.94 | D78: =D64 -> 2017.14 | E78: =E64 -> 2350.4 | F78: =F64 -> 2338.515 | G78: =G64 -> 2479.745 | H78: =H64 -> 3331.615 | I78: =I64 -> 4764.74
B79: Equity Multiplier (C) | C79: =C77/C78 -> 1.5098091 | D79: =D77/D78 -> 1.9992266 | E79: =E77/E78 -> 2.3890423 | F79: =F77/F78 -> 2.8757032 | G79: =G77/G78 -> 3.1873338 | H79: =H77/H78 -> 2.2876713 | I79: =I77/I78 -> 1.7400099
B81: Return on Equity (A*B*C) | C81: =C71*C75*C79 -> 0.059817143 | D81: =D71*D75*D79 -> 0.060903061 | E81: =E71*E75*E79 -> -0.062189415 | F81: =F71*F75*F79 -> 0.045255215 | G81: =G71*G75*G79 -> 0.17930473 | H81: =H71*H75*H79 -> 0.44627005 | I81: =I71*I75*I79 -> 0.32461792
B83: Rreturn on Asset (ROA)
C84: =C62 -> 43555 | D84: =D62 -> 43921 | E84: =E62 -> 44286 | F84: =F62 -> 44651 | G84: =G62 -> 45016 | H84: =H62 -> 45382 | I84: =I62 -> 45747
B85: =B69 -> Net Profit | C85: =C69 -> 96.96 | D85: =D69 -> 122.85 | E85: =E69 -> -146.17 | F85: =F69 -> 105.83 | G85: =G69 -> 444.63 | H85: =H69 -> 1486.8 | I85: =I69 -> 1546.72
B86: =B77 -> Average Totoal Asset | C86: =C74 -> 2447.31 | D86: =D74 -> 4032.72 | E86: =E74 -> 5615.205 | F86: =F74 -> 6724.875 | G86: =G74 -> 7903.775 | H86: =H74 -> 7621.64 | I86: =I74 -> 8290.695
B87: Return on Asset (ROA) | C87: =C85/C86 -> 0.03961901 | D87: =D85/D86 -> 0.03046331 | E87: =E85/E86 -> -0.026031107 | F87: =F85/F86 -> 0.015737095 | G87: =G85/G86 -> 0.056255397 | H87: =H85/H86 -> 0.19507613 | I87: =I85/I86 -> 0.18656096
B89: ROA - Dupont Equation
C90: =C84 -> 43555 | D90: =D84 -> 43921 | E90: =E84 -> 44286 | F90: =F84 -> 44651 | G90: =G84 -> 45016 | H90: =H84 -> 45382 | I90: =I84 -> 45747
B91: =B85 -> Net Profit | C91: =C69 -> 96.96 | D91: =D69 -> 122.85 | E91: =E69 -> -146.17 | F91: =F69 -> 105.83 | G91: =G69 -> 444.63 | H91: =H69 -> 1486.8 | I91: =I69 -> 1546.72
B92: Revenue | C92: =C70 -> 2630.24 | D92: =D70 -> 3485.98 | E92: =E70 -> 2592.96 | F92: =F70 -> 4498.02 | G92: =G70 -> 8242.02 | H92: =H70 -> 12375.11 | I92: =I70 -> 17134.61
B93: Net Profit Margin (A) | C93: =C91/C92 -> 0.036863556 | D93: =D91/D92 -> 0.035241166 | E93: =E91/E92 -> -0.056371868 | F93: =F91/F92 -> 0.02352813 | G93: =G91/G92 -> 0.053946727 | H93: =H91/H92 -> 0.12014439 | I93: =I91/I92 -> 0.09026876
B95: Revenue | C95: =C92 -> 2630.24 | D95: =D92 -> 3485.98 | E95: =E92 -> 2592.96 | F95: =F92 -> 4498.02 | G95: =G92 -> 8242.02 | H95: =H92 -> 12375.11 | I95: =I92 -> 17134.61
B96: Average Totoal Asset | C96: =C86 -> 2447.31 | D96: =D86 -> 4032.72 | E96: =E86 -> 5615.205 | F96: =F86 -> 6724.875 | G96: =G86 -> 7903.775 | H96: =H86 -> 7621.64 | I96: =I86 -> 8290.695
B97: Asset Turnover Ratio (B) | C97: =C95/C96 -> 1.0747474 | D97: =D95/D96 -> 0.86442401 | E97: =E95/E96 -> 0.46177477 | F97: =F95/F96 -> 0.66886299 | G97: =G95/G96 -> 1.0427954 | H97: =H95/H96 -> 1.6236807 | I97: =I95/I96 -> 2.0667278
B99: Return on Asset (A*B) | C99: =C93*C97 -> 0.03961901 | D99: =D93*D97 -> 0.03046331 | E99: =E93*E97 -> -0.026031107 | F99: =F93*F97 -> 0.015737095 | G99: =G93*G97 -> 0.056255397 | H99: =H93*H97 -> 0.19507613 | I99: =I93*I97 -> 0.18656096

Sheet Altman Z Score
B3: ='Data Sheet'!B1 -> TRENT LTD
B4: ='Dupont Analysis'!$B$4 -> ( TRENT | BSE Code: 500251)
B5: =CONCATENATE(" ","INR "&'Data Sheet'!B8) -> INR 4285.6
B6: 52 Week (High - INR 6,261 & Low - 3,645)
B8: Altman's Z Score Analysis
B9: Asian Paints Ltd is an Indian multinational paint company, headquartered in Mumbai. The company is engaged in the business of manufacturing, selling and distribution of paints, coatings, products related to home décor, bath fittings and providing related services.Asian Paints is India's largest paints company by market share.The company has 27 paint manufacturing facilities in 15 countries, servicing consumers in over 60 countries. Asian Paints is also present in the home improvement and décor space in India.
B11: Financial Summary
O49: 1
B62: Working Capital/ Total Assets
C63: =HistoricalFS!F7 -> 43555 | D63: =HistoricalFS!G7 -> 43921 | E63: =HistoricalFS!H7 -> 44286 | F63: =HistoricalFS!I7 -> 44651 | G63: =HistoricalFS!J7 -> 45016 | H63: =HistoricalFS!K7 -> 45382 | I63: =HistoricalFS!L7 -> 45747
B64: Working Capital | C64: ='Data Sheet'!E65-'Data Sheet'!E60 -> 508.46 | D64: ='Data Sheet'!F65-'Data Sheet'!F60 -> -1589.02 | E64: ='Data Sheet'!G65-'Data Sheet'!G60 -> -2036.13 | F64: ='Data Sheet'!H65-'Data Sheet'!H60 -> 1014.21 | G64: ='Data Sheet'!I65-'Data Sheet'!I60 -> 1321.09 | H64: ='Data Sheet'!J65-'Data Sheet'!J60 -> 1731 | I64: ='Data Sheet'!K65-'Data Sheet'!K60 -> 2144.05 | L64: 1
B65: Total Assets | C65: ='Data Sheet'!E66 -> 2558.76 | D65: ='Data Sheet'!F66 -> 5506.68 | E65: ='Data Sheet'!G66 -> 5723.73 | F65: ='Data Sheet'!H66 -> 7726.02 | G65: ='Data Sheet'!I66 -> 8081.53 | H65: ='Data Sheet'!J66 -> 7161.75 | I65: ='Data Sheet'!K66 -> 9419.64 | L65: working capital
B66: Working Capital / Total Assets (A) | C66: =C64/C65 -> 0.19871344 | D66: =D64/D65 -> -0.28856226 | E66: =E64/E65 -> -0.35573481 | F66: =F64/F65 -> 0.13127199 | G66: =G64/G65 -> 0.16347028 | H66: =H64/H65 -> 0.2417007 | I66: =I64/I65 -> 0.22761486 | L66: total assets - total liablities
L67: 2
B68: Retained Earnings/ Total Assets | L68: Retained Earning = no of shares*EPS*Retained earnings
C69: =C63 -> 43555 | D69: =D63 -> 43921 | E69: =E63 -> 44286 | F69: =F63 -> 44651 | G69: =G63 -> 45016 | H69: =H63 -> 45382 | I69: =I63 -> 45747 | L69: 3
B70: Retained Earnings | C70: =HistoricalFS!F43*HistoricalFS!F45*HistoricalFS!F51 -> 21.52 | D70: =HistoricalFS!G43*HistoricalFS!G45*HistoricalFS!G51 -> 0 | E70: =HistoricalFS!H43*HistoricalFS!H45*HistoricalFS!H51 -> 0 | F70: =HistoricalFS!I43*HistoricalFS!I45*HistoricalFS!I51 -> 0 | G70: =HistoricalFS!J43*HistoricalFS!J45*HistoricalFS!J51 -> 0 | H70: =HistoricalFS!K43*HistoricalFS!K45*HistoricalFS!K51 -> 410.34 | I70: =HistoricalFS!L43*HistoricalFS!L45*HistoricalFS!L51 -> 1151.14 | L70: Market Cap =(no of Equity share * Price)/10000000
B71: Total Assets | C71: =C65 -> 2558.76 | D71: =D65 -> 5506.68 | E71: =E65 -> 5723.73 | F71: =F65 -> 7726.02 | G71: =G65 -> 8081.53 | H71: =H65 -> 7161.75 | I71: =I65 -> 9419.64
B72: Retained Earning / Total Assets (B) | C72: =C70/C71 -> 0.0084103238 | D72: =D70/D71 -> 0 | E72: =E70/E71 -> 0 | F72: =F70/F71 -> 0 | G72: =G70/G71 -> 0 | H72: =H70/H71 -> 0.057296052 | I72: =I70/I71 -> 0.12220637
B74: EBIT/ Total Assets
B75: EBIT | C75: =HistoricalFS!F28 -> 188.97 | D75: =HistoricalFS!G28 -> 281.73 | E75: =HistoricalFS!H28 -> -143.43 | F75: =HistoricalFS!I28 -> 283.9 | G75: =HistoricalFS!J28 -> 620.46 | H75: =HistoricalFS!K28 -> 1299.58 | I75: =HistoricalFS!L28 -> 1924.78
B76: Total Assets | C76: =C71 -> 2558.76 | D76: =D71 -> 5506.68 | E76: =E71 -> 5723.73 | F76: =F71 -> 7726.02 | G76: =G71 -> 8081.53 | H76: =H71 -> 7161.75 | I76: =I71 -> 9419.64
B77: EBIT / Total Assets (C) | C77: =C75/C76 -> 0.073852178 | D77: =D75/D76 -> 0.051161498 | E77: =E75/E76 -> -0.025058834 | F77: =F75/F76 -> 0.036745957 | G77: =G75/G76 -> 0.076775066 | H77: =H75/H76 -> 0.18146124 | I77: =I75/I76 -> 0.2043369
B79: Market Cap/ Long term Liabilities
B80: Market Cap | C80: =('Data Sheet'!E70*'Data Sheet'!E97)/10000000 -> 12026.542 | D80: =('Data Sheet'!F70*'Data Sheet'!F97)/10000000 -> 17218.035 | E80: =('Data Sheet'!G70*'Data Sheet'!G97)/10000000 -> 26698.886 | F80: =('Data Sheet'!H70*'Data Sheet'!H97)/10000000 -> 45342.426 | G80: =('Data Sheet'!I70*'Data Sheet'!I97)/10000000 -> 48877.748 | H80: =('Data Sheet'!J70*'Data Sheet'!J97)/10000000 -> 140346.45 | I80: =('Data Sheet'!K70*'Data Sheet'!K97)/10000000 -> 189302.41
B81: Long Term Liabilities | C81: ='Data Sheet'!E59 -> 494.14 | D81: ='Data Sheet'!F59 -> 299.74 | E81: ='Data Sheet'!G59 -> 299.93 | F81: ='Data Sheet'!H59 -> 4725.36 | G81: ='Data Sheet'!I59 -> 4464.14 | H81: ='Data Sheet'!J59 -> 1752.99 | I81: ='Data Sheet'!K59 -> 2237.19
B82: Market Cap/ Long term Liabilities (D) | C82: =C80/C81 -> 24.33833 | D82: =D80/D81 -> 57.443235 | E82: =E80/E81 -> 89.017057 | F82: =F80/F81 -> 9.5955495 | G82: =G80/G81 -> 10.948973 | H82: =H80/H81 -> 80.061181 | I82: =I80/I81 -> 84.61615
B84: Sales/ Total Assets
C85: =C63 -> 43555 | D85: =D63 -> 43921 | E85: =E63 -> 44286 | F85: =F63 -> 44651 | G85: =G63 -> 45016 | H85: =H63 -> 45382 | I85: =I63 -> 45747
B86: Total Sales | C86: ='Data Sheet'!E17 -> 2630.24 | D86: ='Data Sheet'!F17 -> 3485.98 | E86: ='Data Sheet'!G17 -> 2592.96 | F86: ='Data Sheet'!H17 -> 4498.02 | G86: ='Data Sheet'!I17 -> 8242.02 | H86: ='Data Sheet'!J17 -> 12375.11 | I86: ='Data Sheet'!K17 -> 17134.61
B87: Total Assets | C87: =C71 -> 2558.76 | D87: =D71 -> 5506.68 | E87: =E71 -> 5723.73 | F87: =F71 -> 7726.02 | G87: =G71 -> 8081.53 | H87: =H71 -> 7161.75 | I87: =I71 -> 9419.64
B88: Sales/ Total Assets (E) | C88: =C86/C87 -> 1.0279354 | D88: =D86/D87 -> 0.63304568 | E88: =E86/E87 -> 0.45301927 | F88: =F86/F87 -> 0.58219109 | G88: =G86/G87 -> 1.0198589 | H88: =H86/H87 -> 1.727945 | I88: =I86/I87 -> 1.8190302
B90: Altman Z Score
C91: =C85 -> 43555 | D91: =D85 -> 43921 | E91: =E85 -> 44286 | F91: =F85 -> 44651 | G91: =G85 -> 45016 | H91: =H85 -> 45382 | I91: =I85 -> 45747
B93: Final Score | C93: =(C66*1.2)+(C72*1.4)+(C77*3.3)+(C82*0.6)+(C88*1) -> 16.124876 | D93: =(D66*1.2)+(D72*1.4)+(D77*3.3)+(D82*0.6)+(D88*1) -> 34.921545 | E93: =(E66*1.2)+(E72*1.4)+(E77*3.3)+(E82*0.6)+(E88*1) -> 53.353677 | F93: =(F66*1.2)+(F72*1.4)+(F77*3.3)+(F82*0.6)+(F88*1) -> 6.6183088 | G93: =(G66*1.2)+(G72*1.4)+(G77*3.3)+(G82*0.6)+(G88*1) -> 8.0387647 | H93: =(H66*1.2)+(H72*1.4)+(H77*3.3)+(H82*0.6)+(H88*1) -> 50.733731 | I93: =(I66*1.2)+(I72*1.4)+(I77*3.3)+(I82*0.6)+(I88*1) -> 53.707259
B94: Financial sability | C94: =IF(C93<1.81,"Distressed",IF(C93>3,"Strong","Grey Zone")) -> Strong | D94: =IF(D93<1.81,"Distressed",IF(D93>3,"Strong","Grey Zone")) -> Strong | E94: =IF(E93<1.81,"Distressed",IF(E93>3,"Strong","Grey Zone")) -> Strong | F94: =IF(F93<1.81,"Distressed",IF(F93>3,"Strong","Grey Zone")) -> Strong | G94: =IF(G93<1.81,"Distressed",IF(G93>3,"Strong","Grey Zone")) -> Strong | H94: =IF(H93<1.81,"Distressed",IF(H93>3,"Strong","Grey Zone")) -> Strong | I94: =IF(I93<1.81,"Distressed",IF(I93>3,"Strong","Grey Zone")) -> Strong

Sheet VAR>

Sheet Historical Apporoach
B4: ='Intrisic Growth'!$B$4 -> TRENT LTD
B5: =DCF!B3 -> ( TRENT | BSE Code: 500251)
B7: Date | C7: Close | D7: Return | E7: Sorted Returns | G7: Calcualtion of Value at Risk - Trent (Historical)
B9: 02/13/2026 | C9: 4251.35 | D9: =(C9-C10)/C10 -> -0.0077835088 | E9: -0.0077835088
B10: 46083 | C10: 4284.7 | D10: =(C10-C11)/C11 -> 0.015187414 | E10: 0.015187414 | G10: Mean | K10: =AVERAGE(E9:E499) -> 0.0003651798 | N10: 1
B11: 46144 | C11: 4220.6 | D11: =(C11-C12)/C12 -> 0.00856682 | E11: 0.00856682 | G11: Standered Deviation | K11: =_xlfn.STDEV.S(E9:E502) -> 0.022835115
B12: 01/29/2026 | C12: 4184.75 | D12: =(C12-C13)/C13 -> 0.0029358898 | E12: 0.0029358898 | G12: Min | K12: =MIN(E9:E502) -> -0.14757474
B13: 01/28/2026 | C13: 4172.5 | D13: =(C13-C14)/C14 -> 0.013013183 | E13: 0.013013183 | G13: Max | K13: =MAX(E9:E502) -> 0.11237329
B14: 01/23/2026 | C14: 4118.9 | D14: =(C14-C15)/C15 -> -0.0030738697 | E14: -0.0030738697 | G14: CMP | K14: ='Data Sheet'!B8 -> 4285.6
B15: 02/27/2024 | C15: 4131.6 | D15: =(C15-C16)/C16 -> 0.029502641 | E15: 0.029502641
B16: 02/14/2024 | C16: 4013.2 | D16: =(C16-C17)/C17 -> 0.049847619 | E16: 0.049847619 | G16: Percentile | H16: Confidence | I16: VAR% | J16: Stock Price | K16: VAR(INR)
B17: 45569 | C17: 3822.65 | D17: =(C17-C18)/C18 -> 0.027842758 | E17: 0.027842758 | G17: 0.05 | H17: =100%-G17 -> 0.95 | I17: =_xlfn.PERCENTILE.INC($E$9:$E$499,G17) -> -0.031639774 | J17: =$K$14*(1-I17) -> 4421.1954 | K17: =$K$14-J17 -> -135.59542
B18: 45476 | C18: 3719.1 | D18: =(C18-C19)/C19 -> -0.017566568 | E18: -0.017566568 | G18: 0.01 | H18: =100%-G18 -> 0.99 | I18: =_xlfn.PERCENTILE.INC($E$9:$E$499,G18) -> -0.066248887 | J18: =$K$14*(1-I18) -> 4569.5162 | K18: =$K$14-J18 -> -283.91623
B19: 03/28/2024 | C19: 3785.6 | D19: =(C19-C20)/C20 -> -0.0097958436 | E19: -0.0097958436 | G19: 0.005 | H19: =100%-G19 -> 0.995 | I19: =_xlfn.PERCENTILE.INC($E$9:$E$499,G19) -> -0.084672298 | J19: =$K$14*(1-I19) -> 4648.4716 | K19: =$K$14-J19 -> -362.8716
B20: 01/20/2026 | C20: 3823.05 | D20: =(C20-C21)/C21 -> -0.010418554 | E20: -0.010418554 | G20: 0.1 | H20: =100%-G20 -> 0.9 | I20: =_xlfn.PERCENTILE.INC($E$9:$E$499,G20) -> -0.021823746 | J20: =$K$14*(1-I20) -> 4379.1278 | K20: =$K$14-J20 -> -93.527846
B21: 03/14/2024 | C21: 3863.3 | D21: =(C21-C22)/C22 -> 0.019071485 | E21: 0.019071485
B22: 45446 | C22: 3791 | D22: =(C22-C23)/C23 -> 0.0096141042 | E22: 0.0096141042
B23: 02/22/2024 | C23: 3754.9 | D23: =(C23-C24)/C24 -> -0.012595982 | E23: -0.012595982
B24: 45355 | C24: 3802.8 | D24: =(C24-C25)/C25 -> 0.010106913 | E24: 0.010106913
B25: 45386 | C25: 3764.75 | D25: =(C25-C26)/C26 -> -0.017805896 | E25: -0.017805896
B26: 45294 | C26: 3833 | D26: =(C26-C27)/C27 -> -0.028858091 | E26: -0.028858091
B27: 46175 | C27: 3946.9 | D27: =(C27-C28)/C28 -> 0.011571731 | E27: 0.011571731
B28: 01/27/2026 | C28: 3901.75 | D28: =(C28-C29)/C29 -> -0.0073019629 | E28: -0.0073019629
B29: 01/22/2026 | C29: 3930.45 | D29: =(C29-C30)/C30 -> 0.0027937237 | E29: 0.0027937237
B30: 46114 | C30: 3919.5 | D30: =(C30-C31)/C31 -> -0.033927757 | E30: -0.033927757
B31: 45326 | C31: 4057.15 | D31: =(C31-C32)/C32 -> 0.020461291 | E31: 0.020461291
B32: 45385 | C32: 3975.8 | D32: =(C32-C33)/C33 -> -0.0032466312 | E32: -0.0032466312
B33: 02/16/2024 | C33: 3988.75 | D33: =(C33-C34)/C34 -> -0.017500862 | E33: -0.017500862
B34: 04/18/2024 | C34: 4059.8 | D34: =(C34-C35)/C35 -> 0.002989352 | E34: 0.002989352
B35: 03/27/2024 | C35: 4047.7 | D35: =(C35-C36)/C36 -> -0.086184515 | E35: -0.086184515
B36: 45599 | C36: 4429.45 | D36: =(C36-C37)/C37 -> 0.0046838142 | E36: 0.0046838142
B37: 46055 | C37: 4408.8 | D37: =(C37-C38)/C38 -> 0.025827167 | E37: 0.025827167 | G37: Note : VAR is calculated using 2 years Daily Returns
B38: 01/30/2026 | C38: 4297.8 | D38: =(C38-C39)/C39 -> 0.0046165893 | E38: 0.0046165893
B39: 02/15/2024 | C39: 4278.05 | D39: =(C39-C40)/C40 -> 0.01632081 | E39: 0.01632081
B40: 01/13/2026 | C40: 4209.35 | D40: =(C40-C41)/C41 -> -0.0038691814 | E40: -0.0038691814
B41: 01/19/2026 | C41: 4225.7 | D41: =(C41-C42)/C42 -> -0.013562725 | E41: -0.013562725
B42: 02/26/2024 | C42: 4283.8 | D42: =(C42-C43)/C43 -> -0.0011891161 | E42: -0.0011891161
B43: 01/16/2026 | C43: 4288.9 | D43: =(C43-C44)/C44 -> 0.023616034 | E43: 0.023616034
B44: 03/21/2024 | C44: 4189.95 | D44: =(C44-C45)/C45 -> -0.0038988672 | E44: -0.0038988672
B45: 04/16/2024 | C45: 4206.35 | D45: =(C45-C46)/C46 -> 0.035600419 | E45: 0.035600419
B46: 12/23/2025 | C46: 4061.75 | D46: =(C46-C47)/C47 -> 0.0080535081 | E46: 0.0080535081
B47: 45508 | C47: 4029.3 | D47: =(C47-C48)/C48 -> -0.0035118091 | E47: -0.0035118091
B48: 03/20/2024 | C48: 4043.5 | D48: =(C48-C49)/C49 -> -0.016120202 | E48: -0.016120202
B49: 02/28/2024 | C49: 4109.75 | D49: =(C49-C50)/C50 -> 0.0010961574 | E49: 0.0010961574
B50: 02/29/2024 | C50: 4105.25 | D50: =(C50-C51)/C51 -> 0.0079303699 | E50: 0.0079303699
B51: 45539 | C51: 4072.95 | D51: =(C51-C52)/C52 -> 0.0068475372 | E51: 0.0068475372
B52: 12/16/2025 | C52: 4045.25 | D52: =(C52-C53)/C53 -> 0.0067819811 | E52: 0.0067819811
B53: 12/22/2025 | C53: 4018 | D53: =(C53-C54)/C54 -> -0.016569988 | E53: -0.016569988
B54: 45415 | C54: 4085.7 | D54: =(C54-C55)/C55 -> -0.0012833205 | E54: -0.0012833205
B55: 45630 | C55: 4090.95 | D55: =(C55-C56)/C56 -> -0.023488131 | E55: -0.023488131
B56: 46357 | C56: 4189.35 | D56: =(C56-C57)/C57 -> -0.0060854093 | E56: -0.0060854093
B57: 02/19/2024 | C57: 4215 | D57: =(C57-C58)/C58 -> 0.0062908097 | E57: 0.0062908097
B58: 45629 | C58: 4188.65 | D58: =(C58-C59)/C59 -> -0.0090843496 | E58: -0.0090843496
B59: 45295 | C59: 4227.05 | D59: =(C59-C60)/C60 -> 0.0020386635 | E59: 0.0020386635
B60: 46003 | C60: 4218.45 | D60: =(C60-C61)/C61 -> -0.007622005 | E60: -0.007622005
B61: 03/26/2024 | C61: 4250.85 | D61: =(C61-C62)/C62 -> -0.004134942 | E61: -0.004134942
B62: 02/23/2024 | C62: 4268.5 | D62: =(C62-C63)/C63 -> -0.0055332285 | E62: -0.0055332285
B63: 04/19/2024 | C63: 4292.25 | D63: =(C63-C64)/C64 -> 0.011297505 | E63: 0.011297505
B64: 12/19/2025 | C64: 4244.3 | D64: =(C64-C65)/C65 -> -0.015186496 | E64: -0.015186496
B65: 45942 | C65: 4309.75 | D65: =(C65-C66)/C66 -> -0.011615907 | E65: -0.011615907
B66: 46235 | C66: 4360.4 | D66: =(C66-C67)/C67 -> -0.0064823359 | E66: -0.0064823359
B67: 03/22/2024 | C67: 4388.85 | D67: =(C67-C68)/C68 -> 0.0070558271 | E67: 0.0070558271
B68: 03/18/2024 | C68: 4358.1 | D68: =(C68-C69)/C69 -> -0.0031109179 | E68: -0.0031109179
B69: 46297 | C69: 4371.7 | D69: =(C69-C70)/C70 -> -0.0085948839 | E69: -0.0085948839
B70: 45416 | C70: 4409.6 | D70: =(C70-C71)/C71 -> 0.0046019957 | E70: 0.0046019957
B71: 45973 | C71: 4389.4 | D71: =(C71-C72)/C72 -> 0.015606381 | E71: 0.015606381
B72: 02/20/2024 | C72: 4321.95 | D72: =(C72-C73)/C73 -> -0.011865976 | E72: -0.011865976
B73: 03/13/2024 | C73: 4373.85 | D73: =(C73-C74)/C74 -> 0.013356656 | E73: 0.013356656
B74: 04/24/2024 | C74: 4316.2 | D74: =(C74-C75)/C75 -> 0.0079045384 | E74: 0.0079045384
B75: 01/21/2026 | C75: 4282.35 | D75: =(C75-C76)/C76 -> -0.074056456 | E75: -0.074056456
B76: 12/15/2025 | C76: 4624.85 | D76: =(C76-C77)/C77 -> -0.011509607 | E76: -0.011509607
B77: 03/15/2024 | C77: 4678.7 | D77: =(C77-C78)/C78 -> 0.0039697867 | E77: 0.0039697867
B78: 12/26/2025 | C78: 4660.2 | D78: =(C78-C79)/C79 -> -0.011161093 | E78: -0.011161093
B79: 46266 | C79: 4712.8 | D79: =(C79-C80)/C80 -> 0.0040906767 | E79: 0.0040906767
B80: 04/25/2024 | C80: 4693.6 | D80: =(C80-C81)/C81 -> -0.010613518 | E80: -0.010613518
B81: 04/22/2024 | C81: 4743.95 | D81: =(C81-C82)/C82 -> -0.0076767804 | E81: -0.0076767804
B82: 46267 | C82: 4780.65 | D82: =(C82-C83)/C83 -> 0.011649314 | E82: 0.011649314
B83: 04/15/2024 | C83: 4725.6 | D83: =(C83-C84)/C84 -> -0.015366664 | E83: -0.015366664
B84: 46023 | C84: 4799.35 | D84: =(C84-C85)/C85 -> 0.00225538 | E84: 0.00225538
B85: 46328 | C85: 4788.55 | D85: =(C85-C86)/C86 -> 0.0008778622 | E85: 0.0008778622
B86: 12/17/2025 | C86: 4784.35 | D86: =(C86-C87)/C87 -> -0.0012003925 | E86: -0.0012003925
B87: 02/21/2024 | C87: 4790.1 | D87: =(C87-C88)/C88 -> -0.0023534802 | E87: -0.0023534802
B88: 01/14/2026 | C88: 4801.4 | D88: =(C88-C89)/C89 -> -0.0018916952 | E88: -0.0018916952
B89: 11/27/2025 | C89: 4810.5 | D89: =(C89-C90)/C90 -> 0.0044684805 | E89: 0.0044684805
B90: 12/18/2025 | C90: 4789.1 | D90: =(C90-C91)/C91 -> 0.014844089 | E90: 0.014844089
B91: 45789 | C91: 4719.05 | D91: =(C91-C92)/C92 -> 0.021892831 | E91: 0.021892831
B92: 04/23/2024 | C92: 4617.95 | D92: =(C92-C93)/C93 -> -0.013795902 | E92: -0.013795902
B93: 45327 | C93: 4682.55 | D93: =(C93-C94)/C94 -> -0.0014926805 | E93: -0.0014926805
B94: 03/19/2024 | C94: 4689.55 | D94: =(C94-C95)/C95 -> 0.0052194976 | E94: 0.0052194976
B95: 46358 | C95: 4665.2 | D95: =(C95-C96)/C96 -> 0.010264628 | E95: 0.010264628
B96: 46143 | C96: 4617.8 | D96: =(C96-C97)/C97 -> -0.014638102 | E96: -0.014638102
B97: 45418 | C97: 4686.4 | D97: =(C97-C98)/C98 -> -0.017763013 | E97: -0.017763013
B98: 12/31/2025 | C98: 4771.15 | D98: =(C98-C99)/C99 -> -0.0090863777 | E98: -0.0090863777
B99: 45881 | C99: 4814.9 | D99: =(C99-C100)/C100 -> -0.0038481432 | E99: -0.0038481432
B100: 12/24/2025 | C100: 4833.5 | D100: =(C100-C101)/C101 -> 0.033108195 | E100: 0.033108195
B101: 45728 | C101: 4678.6 | D101: =(C101-C102)/C102 -> -0.011305763 | E101: -0.011305763
B102: 11/13/2025 | C102: 4732.1 | D102: =(C102-C103)/C103 -> 0.01084089 | E102: 0.01084089
B103: 46054 | C103: 4681.35 | D103: =(C103-C104)/C104 -> -0.012685859 | E103: -0.012685859
B104: 45759 | C104: 4741.5 | D104: =(C104-C105)/C105 -> -0.031852986 | E104: -0.031852986
B105: 04/29/2024 | C105: 4897.5 | D105: =(C105-C106)/C106 -> 0.0011242845 | E105: 0.0011242845
...

Sheet Monte Carlo Simulation
B9: Date | C9: Close | D9: Return | E9: Sorted Returns | G9: Replication | H9: Simulatd Return | J9: Calcualtion of Value at Risk - Trent(Simulation)
B11: 02/13/2026 | C11: 4251.35 | D11: =(C11-C12)/C12 -> -0.0077835088 | E11: -0.0077835088 | G11: 1 | H11: =_xlfn.NORM.INV(RAND(),N$13,N$14) -> 0.0054631101
B12: 46083 | C12: 4284.7 | D12: =(C12-C13)/C13 -> 0.015187414 | E12: 0.015187414 | G12: 2 | H12: =_xlfn.NORM.INV(RAND(),N$13,N$14) -> 0.0073779453 | J12: Historical Approach
B13: 46144 | C13: 4220.6 | D13: =(C13-C14)/C14 -> 0.00856682 | E13: 0.00856682 | G13: 3 | H13: =_xlfn.NORM.INV(RAND(),N$13,N$14) -> 0.00074139101 | J13: Mean | N13: =AVERAGE(E11:E502) -> 0.00037689508
B14: 01/29/2026 | C14: 4184.75 | D14: =(C14-C15)/C15 -> 0.0029358898 | E14: 0.0029358898 | G14: 4 | H14: =_xlfn.NORM.INV(RAND(),N$13,N$14) -> 0.021510433 | J14: Standered Deviation | N14: =_xlfn.STDEV.S(E11:E502) -> 0.02286805
B15: 01/28/2026 | C15: 4172.5 | D15: =(C15-C16)/C16 -> 0.013013183 | E15: 0.013013183 | G15: 5 | H15: =_xlfn.NORM.INV(RAND(),N$13,N$14) -> 0.016306107 | J15: Min | N15: =MIN(E11:E502) -> -0.14757474
B16: 01/23/2026 | C16: 4118.9 | D16: =(C16-C17)/C17 -> -0.0030738697 | E16: -0.0030738697 | G16: 6 | H16: =_xlfn.NORM.INV(RAND(),N$13,N$14) -> 0.0093043563 | J16: Max | N16: =MAX(E11:E502) -> 0.11237329
B17: 02/27/2024 | C17: 4131.6 | D17: =(C17-C18)/C18 -> 0.029502641 | E17: 0.029502641 | G17: 7 | H17: =_xlfn.NORM.INV(RAND(),N$13,N$14) -> 0.0040240542 | J17: CMP | N17: 2565.8
B18: 02/14/2024 | C18: 4013.2 | D18: =(C18-C19)/C19 -> 0.049847619 | E18: 0.049847619 | G18: 8 | H18: =_xlfn.NORM.INV(RAND(),N$13,N$14) -> -0.003066081
B19: 45569 | C19: 3822.65 | D19: =(C19-C20)/C20 -> 0.027842758 | E19: 0.027842758 | G19: 9 | H19: =_xlfn.NORM.INV(RAND(),N$13,N$14) -> 0.011860828 | J19: Monte carlo Simulation
B20: 45476 | C20: 3719.1 | D20: =(C20-C21)/C21 -> -0.017566568 | E20: -0.017566568 | G20: 10 | H20: =_xlfn.NORM.INV(RAND(),N$13,N$14) -> -0.0013993797 | J20: Mean | N20: =AVERAGE(H11:H10010) -> 0.00010005652
B21: 03/28/2024 | C21: 3785.6 | D21: =(C21-C22)/C22 -> -0.0097958436 | E21: -0.0097958436 | G21: 11 | H21: =_xlfn.NORM.INV(RAND(),N$13,N$14) -> -0.027066421 | J21: Standered Deviation | N21: =_xlfn.STDEV.S(H11:H10010) -> 0.022828901
B22: 01/20/2026 | C22: 3823.05 | D22: =(C22-C23)/C23 -> -0.010418554 | E22: -0.010418554 | G22: 12 | H22: =_xlfn.NORM.INV(RAND(),N$13,N$14) -> -0.023997358 | J22: Min | N22: =MIN(H11:H10010) -> -0.10003533
B23: 03/14/2024 | C23: 3863.3 | D23: =(C23-C24)/C24 -> 0.019071485 | E23: 0.019071485 | G23: 13 | H23: =_xlfn.NORM.INV(RAND(),N$13,N$14) -> -0.018659375 | J23: Max | N23: =MAX(H11:H10010) -> 0.08691519
B24: 45446 | C24: 3791 | D24: =(C24-C25)/C25 -> 0.0096141042 | E24: 0.0096141042 | G24: 14 | H24: =_xlfn.NORM.INV(RAND(),N$13,N$14) -> -0.016054998 | J24: CMP | N24: 2565.8
B25: 02/22/2024 | C25: 3754.9 | D25: =(C25-C26)/C26 -> -0.012595982 | E25: -0.012595982 | G25: 15 | H25: =_xlfn.NORM.INV(RAND(),N$13,N$14) -> -0.013903159
B26: 45355 | C26: 3802.8 | D26: =(C26-C27)/C27 -> 0.010106913 | E26: 0.010106913 | G26: 16 | H26: =_xlfn.NORM.INV(RAND(),N$13,N$14) -> 0.030641097 | J26: Percentile | K26: Confidence | L26: VAR% | M26: Stock Price | N26: VAR(INR)
B27: 45386 | C27: 3764.75 | D27: =(C27-C28)/C28 -> -0.017805896 | E27: -0.017805896 | G27: 17 | H27: =_xlfn.NORM.INV(RAND(),N$13,N$14) -> 0.040369239 | J27: 0.05 | K27: =100%-J27 -> 0.95 | L27: =_xlfn.PERCENTILE.INC($H$11:$H$10010,J27) -> -0.037337343 | M27: =$N$17*(1-L27) -> 2661.6002 | N27: =$N$17-M27 -> -95.800154
B28: 45294 | C28: 3833 | D28: =(C28-C29)/C29 -> -0.028858091 | E28: -0.028858091 | G28: 18 | H28: =_xlfn.NORM.INV(RAND(),N$13,N$14) -> 0.010852088 | J28: 0.01 | K28: =100%-J28 -> 0.99 | L28: =_xlfn.PERCENTILE.INC($H$11:$H$10010,J28) -> -0.053324315 | M28: =$N$17*(1-L28) -> 2702.6195 | N28: =$N$17-M28 -> -136.81953 | V28: =U28*N27 -> 0
B29: 46175 | C29: 3946.9 | D29: =(C29-C30)/C30 -> 0.011571731 | E29: 0.011571731 | G29: 19 | H29: =_xlfn.NORM.INV(RAND(),N$13,N$14) -> -0.0058527898 | J29: 0.005 | K29: =100%-J29 -> 0.995 | L29: =_xlfn.PERCENTILE.INC($H$11:$H$10010,J29) -> -0.058525277 | M29: =$N$17*(1-L29) -> 2715.9642 | N29: =$N$17-M29 -> -150.16415
B30: 01/27/2026 | C30: 3901.75 | D30: =(C30-C31)/C31 -> -0.0073019629 | E30: -0.0073019629 | G30: 20 | H30: =_xlfn.NORM.INV(RAND(),N$13,N$14) -> -0.017810965 | J30: 0.1 | K30: =100%-J30 -> 0.9 | L30: =_xlfn.PERCENTILE.INC($H$11:$H$10010,J30) -> -0.028981591 | M30: =$N$17*(1-L30) -> 2640.161 | N30: =$N$17-M30 -> -74.360966
B31: 01/22/2026 | C31: 3930.45 | D31: =(C31-C32)/C32 -> 0.0027937237 | E31: 0.0027937237 | G31: 21 | H31: =_xlfn.NORM.INV(RAND(),N$13,N$14) -> 0.0010336984
B32: 46114 | C32: 3919.5 | D32: =(C32-C33)/C33 -> -0.033927757 | E32: -0.033927757 | G32: 22 | H32: =_xlfn.NORM.INV(RAND(),N$13,N$14) -> -0.00018897768
B33: 45326 | C33: 4057.15 | D33: =(C33-C34)/C34 -> 0.020461291 | E33: 0.020461291 | G33: 23 | H33: =_xlfn.NORM.INV(RAND(),N$13,N$14) -> 0.0036266001
B34: 45385 | C34: 3975.8 | D34: =(C34-C35)/C35 -> -0.0032466312 | E34: -0.0032466312 | G34: 24 | H34: =_xlfn.NORM.INV(RAND(),N$13,N$14) -> 0.00053440777
B35: 02/16/2024 | C35: 3988.75 | D35: =(C35-C36)/C36 -> -0.017500862 | E35: -0.017500862 | G35: 25 | H35: =_xlfn.NORM.INV(RAND(),N$13,N$14) -> 0.031829818
B36: 04/18/2024 | C36: 4059.8 | D36: =(C36-C37)/C37 -> 0.002989352 | E36: 0.002989352 | G36: 26 | H36: =_xlfn.NORM.INV(RAND(),N$13,N$14) -> -0.003963299
B37: 03/27/2024 | C37: 4047.7 | D37: =(C37-C38)/C38 -> -0.086184515 | E37: -0.086184515 | G37: 27 | H37: =_xlfn.NORM.INV(RAND(),N$13,N$14) -> -0.009016586
B38: 45599 | C38: 4429.45 | D38: =(C38-C39)/C39 -> 0.0046838142 | E38: 0.0046838142 | G38: 28 | H38: =_xlfn.NORM.INV(RAND(),N$13,N$14) -> -0.054224709
B39: 46055 | C39: 4408.8 | D39: =(C39-C40)/C40 -> 0.025827167 | E39: 0.025827167 | G39: 29 | H39: =_xlfn.NORM.INV(RAND(),N$13,N$14) -> 0.010014181
B40: 01/30/2026 | C40: 4297.8 | D40: =(C40-C41)/C41 -> 0.0046165893 | E40: 0.0046165893 | G40: 30 | H40: =_xlfn.NORM.INV(RAND(),N$13,N$14) -> 0.02570752
B41: 02/15/2024 | C41: 4278.05 | D41: =(C41-C42)/C42 -> 0.01632081 | E41: 0.01632081 | G41: 31 | H41: =_xlfn.NORM.INV(RAND(),N$13,N$14) -> 0.038612496
B42: 01/13/2026 | C42: 4209.35 | D42: =(C42-C43)/C43 -> -0.0038691814 | E42: -0.0038691814 | G42: 32 | H42: =_xlfn.NORM.INV(RAND(),N$13,N$14) -> -0.018046039
B43: 01/19/2026 | C43: 4225.7 | D43: =(C43-C44)/C44 -> -0.013562725 | E43: -0.013562725 | G43: 33 | H43: =_xlfn.NORM.INV(RAND(),N$13,N$14) -> -0.015909273
B44: 02/26/2024 | C44: 4283.8 | D44: =(C44-C45)/C45 -> -0.0011891161 | E44: -0.0011891161 | G44: 34 | H44: =_xlfn.NORM.INV(RAND(),N$13,N$14) -> 0.031428612
B45: 01/16/2026 | C45: 4288.9 | D45: =(C45-C46)/C46 -> 0.023616034 | E45: 0.023616034 | G45: 35 | H45: =_xlfn.NORM.INV(RAND(),N$13,N$14) -> 0.0072071059
B46: 03/21/2024 | C46: 4189.95 | D46: =(C46-C47)/C47 -> -0.0038988672 | E46: -0.0038988672 | G46: 36 | H46: =_xlfn.NORM.INV(RAND(),N$13,N$14) -> 0.014011563
B47: 04/16/2024 | C47: 4206.35 | D47: =(C47-C48)/C48 -> 0.035600419 | E47: 0.035600419 | G47: 37 | H47: =_xlfn.NORM.INV(RAND(),N$13,N$14) -> 0.0061689531
B48: 12/23/2025 | C48: 4061.75 | D48: =(C48-C49)/C49 -> 0.0080535081 | E48: 0.0080535081 | G48: 38 | H48: =_xlfn.NORM.INV(RAND(),N$13,N$14) -> -0.017478142
B49: 45508 | C49: 4029.3 | D49: =(C49-C50)/C50 -> -0.0035118091 | E49: -0.0035118091 | G49: 39 | H49: =_xlfn.NORM.INV(RAND(),N$13,N$14) -> 0.028454463
B50: 03/20/2024 | C50: 4043.5 | D50: =(C50-C51)/C51 -> -0.016120202 | E50: -0.016120202 | G50: 40 | H50: =_xlfn.NORM.INV(RAND(),N$13,N$14) -> -0.026334668
B51: 02/28/2024 | C51: 4109.75 | D51: =(C51-C52)/C52 -> 0.0010961574 | E51: 0.0010961574 | G51: 41 | H51: =_xlfn.NORM.INV(RAND(),N$13,N$14) -> -0.0037392105
B52: 02/29/2024 | C52: 4105.25 | D52: =(C52-C53)/C53 -> 0.0079303699 | E52: 0.0079303699 | G52: 42 | H52: =_xlfn.NORM.INV(RAND(),N$13,N$14) -> 0.026178933
B53: 45539 | C53: 4072.95 | D53: =(C53-C54)/C54 -> 0.0068475372 | E53: 0.0068475372 | G53: 43 | H53: =_xlfn.NORM.INV(RAND(),N$13,N$14) -> 0.05212996
B54: 12/16/2025 | C54: 4045.25 | D54: =(C54-C55)/C55 -> 0.0067819811 | E54: 0.0067819811 | G54: 44 | H54: =_xlfn.NORM.INV(RAND(),N$13,N$14) -> 0.048701778
B55: 12/22/2025 | C55: 4018 | D55: =(C55-C56)/C56 -> -0.016569988 | E55: -0.016569988 | G55: 45 | H55: =_xlfn.NORM.INV(RAND(),N$13,N$14) -> 0.021770357
B56: 45415 | C56: 4085.7 | D56: =(C56-C57)/C57 -> -0.0012833205 | E56: -0.0012833205 | G56: 46 | H56: =_xlfn.NORM.INV(RAND(),N$13,N$14) -> 0.0084960162
B57: 45630 | C57: 4090.95 | D57: =(C57-C58)/C58 -> -0.023488131 | E57: -0.023488131 | G57: 47 | H57: =_xlfn.NORM.INV(RAND(),N$13,N$14) -> 0.036360149
B58: 46357 | C58: 4189.35 | D58: =(C58-C59)/C59 -> -0.0060854093 | E58: -0.0060854093 | G58: 48 | H58: =_xlfn.NORM.INV(RAND(),N$13,N$14) -> 0.0090097867
B59: 02/19/2024 | C59: 4215 | D59: =(C59-C60)/C60 -> 0.0062908097 | E59: 0.0062908097 | G59: 49 | H59: =_xlfn.NORM.INV(RAND(),N$13,N$14) -> 0.013352795
B60: 45629 | C60: 4188.65 | D60: =(C60-C61)/C61 -> -0.0090843496 | E60: -0.0090843496 | G60: 50 | H60: =_xlfn.NORM.INV(RAND(),N$13,N$14) -> 0.017249151
B61: 45295 | C61: 4227.05 | D61: =(C61-C62)/C62 -> 0.0020386635 | E61: 0.0020386635 | G61: 51 | H61: =_xlfn.NORM.INV(RAND(),N$13,N$14) -> -0.033437804
B62: 46003 | C62: 4218.45 | D62: =(C62-C63)/C63 -> -0.007622005 | E62: -0.007622005 | G62: 52 | H62: =_xlfn.NORM.INV(RAND(),N$13,N$14) -> 0.0458498
B63: 03/26/2024 | C63: 4250.85 | D63: =(C63-C64)/C64 -> -0.004134942 | E63: -0.004134942 | G63: 53 | H63: =_xlfn.NORM.INV(RAND(),N$13,N$14) -> -0.024951565
B64: 02/23/2024 | C64: 4268.5 | D64: =(C64-C65)/C65 -> -0.0055332285 | E64: -0.0055332285 | G64: 54 | H64: =_xlfn.NORM.INV(RAND(),N$13,N$14) -> 0.022089802
B65: 04/19/2024 | C65: 4292.25 | D65: =(C65-C66)/C66 -> 0.011297505 | E65: 0.011297505 | G65: 55 | H65: =_xlfn.NORM.INV(RAND(),N$13,N$14) -> -0.01158967
B66: 12/19/2025 | C66: 4244.3 | D66: =(C66-C67)/C67 -> -0.015186496 | E66: -0.015186496 | G66: 56 | H66: =_xlfn.NORM.INV(RAND(),N$13,N$14) -> 0.021940721
B67: 45942 | C67: 4309.75 | D67: =(C67-C68)/C68 -> -0.011615907 | E67: -0.011615907 | G67: 57 | H67: =_xlfn.NORM.INV(RAND(),N$13,N$14) -> -0.055710727
B68: 46235 | C68: 4360.4 | D68: =(C68-C69)/C69 -> -0.0064823359 | E68: -0.0064823359 | G68: 58 | H68: =_xlfn.NORM.INV(RAND(),N$13,N$14) -> 0.013658977
B69: 03/22/2024 | C69: 4388.85 | D69: =(C69-C70)/C70 -> 0.0070558271 | E69: 0.0070558271 | G69: 59 | H69: =_xlfn.NORM.INV(RAND(),N$13,N$14) -> -0.010877327
B70: 03/18/2024 | C70: 4358.1 | D70: =(C70-C71)/C71 -> -0.0031109179 | E70: -0.0031109179 | G70: 60 | H70: =_xlfn.NORM.INV(RAND(),N$13,N$14) -> -0.014003191
B71: 46297 | C71: 4371.7 | D71: =(C71-C72)/C72 -> -0.0085948839 | E71: -0.0085948839 | G71: 61 | H71: =_xlfn.NORM.INV(RAND(),N$13,N$14) -> -0.038039209
B72: 45416 | C72: 4409.6 | D72: =(C72-C73)/C73 -> 0.0046019957 | E72: 0.0046019957 | G72: 62 | H72: =_xlfn.NORM.INV(RAND(),N$13,N$14) -> 0.057001404
B73: 45973 | C73: 4389.4 | D73: =(C73-C74)/C74 -> 0.015606381 | E73: 0.015606381 | G73: 63 | H73: =_xlfn.NORM.INV(RAND(),N$13,N$14) -> 0.036462967
B74: 02/20/2024 | C74: 4321.95 | D74: =(C74-C75)/C75 -> -0.011865976 | E74: -0.011865976 | G74: 64 | H74: =_xlfn.NORM.INV(RAND(),N$13,N$14) -> -0.020639497
B75: 03/13/2024 | C75: 4373.85 | D75: =(C75-C76)/C76 -> 0.013356656 | E75: 0.013356656 | G75: 65 | H75: =_xlfn.NORM.INV(RAND(),N$13,N$14) -> -0.019294902
B76: 04/24/2024 | C76: 4316.2 | D76: =(C76-C77)/C77 -> 0.0079045384 | E76: 0.0079045384 | G76: 66 | H76: =_xlfn.NORM.INV(RAND(),N$13,N$14) -> -0.014540428
B77: 01/21/2026 | C77: 4282.35 | D77: =(C77-C78)/C78 -> -0.074056456 | E77: -0.074056456 | G77: 67 | H77: =_xlfn.NORM.INV(RAND(),N$13,N$14) -> -0.0132639
B78: 12/15/2025 | C78: 4624.85 | D78: =(C78-C79)/C79 -> -0.011509607 | E78: -0.011509607 | G78: 68 | H78: =_xlfn.NORM.INV(RAND(),N$13,N$14) -> 0.019215429
B79: 03/15/2024 | C79: 4678.7 | D79: =(C79-C80)/C80 -> 0.0039697867 | E79: 0.0039697867 | G79: 69 | H79: =_xlfn.NORM.INV(RAND(),N$13,N$14) -> 0.010843437
B80: 12/26/2025 | C80: 4660.2 | D80: =(C80-C81)/C81 -> -0.011161093 | E80: -0.011161093 | G80: 70 | H80: =_xlfn.NORM.INV(RAND(),N$13,N$14) -> -0.01634189
B81: 46266 | C81: 4712.8 | D81: =(C81-C82)/C82 -> 0.0040906767 | E81: 0.0040906767 | G81: 71 | H81: =_xlfn.NORM.INV(RAND(),N$13,N$14) -> 0.016996099
B82: 04/25/2024 | C82: 4693.6 | D82: =(C82-C83)/C83 -> -0.010613518 | E82: -0.010613518 | G82: 72 | H82: =_xlfn.NORM.INV(RAND(),N$13,N$14) -> -0.026343455
B83: 04/22/2024 | C83: 4743.95 | D83: =(C83-C84)/C84 -> -0.0076767804 | E83: -0.0076767804 | G83: 73 | H83: =_xlfn.NORM.INV(RAND(),N$13,N$14) -> -0.0020008648
B84: 46267 | C84: 4780.65 | D84: =(C84-C85)/C85 -> 0.011649314 | E84: 0.011649314 | G84: 74 | H84: =_xlfn.NORM.INV(RAND(),N$13,N$14) -> -0.037847879
B85: 04/15/2024 | C85: 4725.6 | D85: =(C85-C86)/C86 -> -0.015366664 | E85: -0.015366664 | G85: 75 | H85: =_xlfn.NORM.INV(RAND(),N$13,N$14) -> 0.056344615
B86: 46023 | C86: 4799.35 | D86: =(C86-C87)/C87 -> 0.00225538 | E86: 0.00225538 | G86: 76 | H86: =_xlfn.NORM.INV(RAND(),N$13,N$14) -> -0.040957662
B87: 46328 | C87: 4788.55 | D87: =(C87-C88)/C88 -> 0.0008778622 | E87: 0.0008778622 | G87: 77 | H87: =_xlfn.NORM.INV(RAND(),N$13,N$14) -> -0.025496847
B88: 12/17/2025 | C88: 4784.35 | D88: =(C88-C89)/C89 -> -0.0012003925 | E88: -0.0012003925 | G88: 78 | H88: =_xlfn.NORM.INV(RAND(),N$13,N$14) -> -0.047077766
B89: 02/21/2024 | C89: 4790.1 | D89: =(C89-C90)/C90 -> -0.0023534802 | E89: -0.0023534802 | G89: 79 | H89: =_xlfn.NORM.INV(RAND(),N$13,N$14) -> 0.025774175
B90: 01/14/2026 | C90: 4801.4 | D90: =(C90-C91)/C91 -> -0.0018916952 | E90: -0.0018916952 | G90: 80 | H90: =_xlfn.NORM.INV(RAND(),N$13,N$14) -> -0.012784761
B91: 11/27/2025 | C91: 4810.5 | D91: =(C91-C92)/C92 -> 0.0044684805 | E91: 0.0044684805 | G91: 81 | H91: =_xlfn.NORM.INV(RAND(),N$13,N$14) -> -0.02583181
B92: 12/18/2025 | C92: 4789.1 | D92: =(C92-C93)/C93 -> 0.014844089 | E92: 0.014844089 | G92: 82 | H92: =_xlfn.NORM.INV(RAND(),N$13,N$14) -> -0.0036600369
B93: 45789 | C93: 4719.05 | D93: =(C93-C94)/C94 -> 0.021892831 | E93: 0.021892831 | G93: 83 | H93: =_xlfn.NORM.INV(RAND(),N$13,N$14) -> -0.029901871
B94: 04/23/2024 | C94: 4617.95 | D94: =(C94-C95)/C95 -> -0.013795902 | E94: -0.013795902 | G94: 84 | H94: =_xlfn.NORM.INV(RAND(),N$13,N$14) -> 0.022768032
B95: 45327 | C95: 4682.55 | D95: =(C95-C96)/C96 -> -0.0014926805 | E95: -0.0014926805 | G95: 85 | H95: =_xlfn.NORM.INV(RAND(),N$13,N$14) -> 0.017196563
B96: 03/19/2024 | C96: 4689.55 | D96: =(C96-C97)/C97 -> 0.0052194976 | E96: 0.0052194976 | G96: 86 | H96: =_xlfn.NORM.INV(RAND(),N$13,N$14) -> -0.021497204
B97: 46358 | C97: 4665.2 | D97: =(C97-C98)/C98 -> 0.010264628 | E97: 0.010264628 | G97: 87 | H97: =_xlfn.NORM.INV(RAND(),N$13,N$14) -> 0.0033604359
B98: 46143 | C98: 4617.8 | D98: =(C98-C99)/C99 -> -0.014638102 | E98: -0.014638102 | G98: 88 | H98: =_xlfn.NORM.INV(RAND(),N$13,N$14) -> -0.015705517
B99: 45418 | C99: 4686.4 | D99: =(C99-C100)/C100 -> -0.017763013 | E99: -0.017763013 | G99: 89 | H99: =_xlfn.NORM.INV(RAND(),N$13,N$14) -> 0.02573926
B100: 12/31/2025 | C100: 4771.15 | D100: =(C100-C101)/C101 -> -0.0090863777 | E100: -0.0090863777 | G100: 90 | H100: =_xlfn.NORM.INV(RAND(),N$13,N$14) -> -0.0059919195
B101: 45881 | C101: 4814.9 | D101: =(C101-C102)/C102 -> -0.0038481432 | E101: -0.0038481432 | G101: 91 | H101: =_xlfn.NORM.INV(RAND(),N$13,N$14) -> 0.028184564
B102: 12/24/2025 | C102: 4833.5 | D102: =(C102-C103)/C103 -> 0.033108195 | E102: 0.033108195 | G102: 92 | H102: =_xlfn.NORM.INV(RAND(),N$13,N$14) -> 0.041662731
B103: 45728 | C103: 4678.6 | D103: =(C103-C104)/C104 -> -0.011305763 | E103: -0.011305763 | G103: 93 | H103: =_xlfn.NORM.INV(RAND(),N$13,N$14) -> 0.0029710951
B104: 11/13/2025 | C104: 4732.1 | D104: =(C104-C105)/C105 -> 0.01084089 | E104: 0.01084089 | G104: 94 | H104: =_xlfn.NORM.INV(RAND(),N$13,N$14) -> 0.031321212
B105: 46054 | C105: 4681.35 | D105: =(C105-C106)/C106 -> -0.012685859 | E105: -0.012685859 | G105: 95 | H105: =_xlfn.NORM.INV(RAND(),N$13,N$14) -> -0.024037524
B106: 45759 | C106: 4741.5 | D106: =(C106-C107)/C107 -> -0.031852986 | E106: -0.031852986 | G106: 96 | H106: =_xlfn.NORM.INV(RAND(),N$13,N$14) -> -0.020279718
B107: 04/29/2024 | C107: 4897.5 | D107: =(C107-C108)/C108 -> 0.0011242845 | E107: 0.0011242845 | G107: 97 | H107: =_xlfn.NORM.INV(RAND(),N$13,N$14) -> -0.0032772559
B108: 45700 | C108: 4892 | D108: =(C108-C109)/C109 -> -0.023445688 | E108: -0.023445688 | G108: 98 | H108: =_xlfn.NORM.INV(RAND(),N$13,N$14) -> 0.0097942619
B109: 46002 | C109: 5009.45 | D109: =(C109-C110)/C110 -> -0.01378102 | E109: -0.01378102 | G109: 99 | H109: =_xlfn.NORM.INV(RAND(),N$13,N$14) -> -0.0087689956
...

Sheet Data Room>

Sheet Data Sheet
A1: COMPANY NAME | B1: TRENT LTD
A2: LATEST VERSION | B2: 2.1 | E2: PLEASE DO NOT MAKE ANY CHANGES TO THIS SHEET
A3: CURRENT VERSION | B3: 2.1
A5: META
A6: Number of shares | B6: =IF(B9>0, B9/B8, 0) -> 35.534427
A7: Face Value | B7: 1
A8: Current Price | B8: 4285.6
A9: Market Capitalization | B9: 152286.34
A15: PROFIT & LOSS
A16: Report Date | B16: 42460 | C16: 42825 | D16: 43190 | E16: 43555 | F16: 43921 | G16: 44286 | H16: 44651 | I16: 45016 | J16: 45382 | K16: 45747
A17: Sales | B17: 1686.17 | C17: 1812.44 | D17: 2157.46 | E17: 2630.24 | F17: 3485.98 | G17: 2592.96 | H17: 4498.02 | I17: 8242.02 | J17: 12375.11 | K17: 17134.61
A18: Raw Material Cost | B18: 810.2 | C18: 911.22 | D18: 1070.02 | E18: 1459.67 | F18: 1951.64 | G18: 1371.64 | H18: 2920.38 | I18: 5211.05 | J18: 7123.6 | K18: 10143.39
A19: Change in Inventory | B19: 14.59 | C19: 29.86 | D19: 38.51 | E19: 148.23 | F19: 69.89 | G19: -162.36 | H19: 438.84 | I19: 491.31 | J19: 164.71 | K19: 454.25
A20: Power and Fuel | B20: 48.92 | C20: 51.28 | D20: 52.75 | E20: 59.18 | F20: 66.64 | G20: 49.41 | H20: 71.89 | I20: 144.28 | J20: 229.16 | K20: 349.87
A21: Other Mfr. Exp | B21: 76.42 | C21: 81.91 | D21: 90.78 | E21: 122.09 | F21: 97.51 | G21: 92 | H21: 127.14 | I21: 211.99 | J21: 264.59 | K21: 369.79
A22: Employee Cost | B22: 165.69 | C22: 194.72 | D22: 233.02 | E22: 288.89 | F22: 361.01 | G22: 303.4 | H22: 402.92 | I22: 659.07 | J22: 1041.74 | K22: 1315.54
A23: Selling and admin | B23: 444.06 | C23: 407.07 | D23: 450.61 | E23: 514.41 | F23: 436.82 | G23: 364.62 | H23: 705.03 | I23: 1252.53 | J23: 1709.55 | K23: 2322.83
A24: Other Expenses | B24: 65.71 | C24: 62.57 | D24: 90.29 | E24: 93.59 | F24: 113.28 | G24: 135.66 | H24: 114.78 | I24: 140.26 | J24: 200.49 | K24: 267.48
A25: Other Income | B25: 86.44 | C25: 81.31 | D25: 27.47 | E25: 30.14 | F25: 146.63 | G25: 199.4 | H25: 152.16 | I25: 340.6 | J25: 988.91 | K25: 305.06
A26: Depreciation | B26: 38.59 | C26: 41.29 | D26: 45.53 | E26: 51.67 | F26: 247.24 | G26: 257.3 | H26: 310.82 | I26: 493.69 | J26: 671.11 | K26: 895.18
A27: Interest | B27: 47.73 | C27: 45.55 | D27: 43.78 | E27: 50.64 | F27: 263.37 | G27: 260.79 | H27: 324.84 | I27: 408.99 | J27: 367.66 | K27: 200.1
... A29: Tax | B29: 34.71 | C29: 43.05 | D29: 59.62 | E29: 73.61 | F29: 59.01 | G29: -23.69 | H29: 76.62 | I29: 158.44 | J29: 443.37 | K29: 495.33
A30: Net profit | B30: 55.1 | C30: 84.86 | D30: 86.97 | E30: 96.96 | F30: 122.85 | G30: -146.17 | H30: 105.83 | I30: 444.63 | J30: 1486.8 | K30: 1546.72 | N30: EBITDA
A31: Dividend Amount | B31: 29.91 | C31: 33.23 | D31: 38.21 | E31: 43.2 | F31: 35.55 | G31: 21.33 | H31: 60.44 | I31: 78.21 | J31: 78.21 | K31: 78.21 | N31: Net profit+depreciation+tax+interest
A33: EBITDA | B33: =B30+B29+B27+B26 -> 176.13 | C33: =C30+C29+C27+C26 -> 214.75 | D33: =D30+D29+D27+D26 -> 235.9 | E33: =E30+E29+E27+E26 -> 272.88 | F33: =F30+F29+F27+F26 -> 692.47 | G33: =G30+G29+G27+G26 -> 348.23 | H33: =H30+H29+H27+H26 -> 818.11 | I33: =I30+I29+I27+I26 -> 1505.75 | ... K33: =K30+K29+K27+K26 -> 3137.33
A40: Quarters
A41: Report Date | B41: 45199 | C41: 45291 | D41: 45382 | E41: 45473 | F41: 45565 | G41: 45657 | H41: 45747 | I41: 45838 | J41: 45930 | K41: 46022
A42: Sales | B42: 2982.42 | C42: 3466.62 | D42: 3297.7 | E42: 4104.44 | F42: 4156.67 | G42: 4656.56 | H42: 4216.94 | I42: 4883.48 | J42: 4817.68 | K42: 5345.06
A43: Expenses | B43: 2525.85 | C43: 2838.1 | D43: 2828.06 | E43: 3491.09 | F43: 3510.95 | G43: 3809.19 | H43: 3566.03 | I43: 4035.62 | J43: 4001.7 | K43: 4263.99
A44: Other Income | B44: 105.42 | C44: 110.01 | D44: 694.87 | E44: 100.91 | F44: 51.04 | G44: 79.87 | H44: 74.34 | I44: 49.8 | J44: 27.55 | K44: 4.55
A45: Depreciation | B45: 152.22 | C45: 164.53 | D45: 212.94 | E45: 181.32 | F45: 196.95 | G45: 244.93 | H45: 271.98 | I45: 292.93 | J45: 324.93 | K45: 366.74
A46: Interest | B46: 95.45 | C46: 98.81 | D46: 32.54 | E46: 31.55 | F46: 33 | G46: 36.52 | H46: 37.52 | I46: 40.04 | J46: 41.62 | K46: 42.94
A47: Profit before tax | B47: 314.32 | C47: 475.19 | D47: 919.03 | E47: 501.39 | F47: 466.81 | G47: 645.79 | H47: 415.75 | I47: 564.69 | J47: 476.98 | K47: 675.94
A48: Tax | B48: 86.26 | C48: 104.55 | D48: 206.94 | E48: 110.18 | F48: 131.75 | G48: 149.25 | H48: 104.15 | I48: 139.99 | J48: 103.56 | K48: 165.83
A49: Net profit | B49: 234.73 | C49: 374.36 | D49: 704.23 | E49: 392.57 | F49: 338.75 | G49: 497.25 | H49: 318.15 | I49: 429.69 | J49: 376.86 | K49: 512.77
A50: Operating Profit | B50: 456.57 | C50: 628.52 | D50: 469.64 | E50: 613.35 | F50: 645.72 | G50: 847.37 | H50: 650.91 | I50: 847.86 | J50: 815.98 | K50: 1081.07
A55: BALANCE SHEET
A56: Report Date | B56: 42460 | C56: 42825 | D56: 43190 | E56: 43555 | F56: 43921 | G56: 44286 | H56: 44651 | I56: 45016 | J56: 45382 | K56: 45747
A57: Equity Share Capital | B57: 33.23 | C57: 33.23 | D57: 33.23 | E57: 33.23 | F57: 35.55 | G57: 35.55 | H57: 35.55 | I57: 35.55 | J57: 35.55 | K57: 35.55
A58: Reserves | B58: 1431.16 | C58: 1514.46 | D58: 1562.14 | E58: 1613.28 | F58: 2352.22 | G58: 2277.48 | H58: 2328.45 | I58: 2559.94 | J58: 4032.19 | K58: 5426.19
A59: Borrowings | B59: 399.8 | C59: 391.74 | D59: 391.43 | E59: 494.14 | F59: 299.74 | G59: 299.93 | H59: 4725.36 | I59: 4464.14 | J59: 1752.99 | K59: 2237.19
A60: Other Liabilities | B60: 292.4 | C60: 282.82 | D60: 349.06 | E60: 418.11 | F60: 2819.17 | G60: 3110.77 | H60: 636.66 | I60: 1021.9 | J60: 1341.02 | K60: 1720.71
A61: Total | B61: 2156.59 | C61: 2222.25 | D61: 2335.86 | E61: 2558.76 | F61: 5506.68 | G61: 5723.73 | H61: 7726.02 | I61: 8081.53 | J61: 7161.75 | K61: 9419.64
A62: Net Block | B62: 476.79 | C62: 548.71 | D62: 612.53 | E62: 662.18 | F62: 2738.43 | G62: 3053.82 | H62: 4686.71 | I62: 4526.95 | J62: 2449.92 | K62: 3895.13
A63: Capital Work in Progress | B63: 54.86 | C63: 5.48 | D63: 9.59 | E63: 87.18 | F63: 23.32 | G63: 107.98 | H63: 104.72 | I63: 101.72 | J63: 223.78 | K63: 179.5
A64: Investments | B64: 1066.97 | C64: 1079.96 | D64: 1022.88 | E64: 882.83 | F64: 1514.78 | G64: 1487.29 | H64: 1283.72 | I64: 1109.87 | J64: 1416.03 | K64: 1480.25
A65: Other Assets | B65: 557.97 | C65: 588.1 | D65: 690.86 | E65: 926.57 | F65: 1230.15 | G65: 1074.64 | H65: 1650.87 | I65: 2342.99 | J65: 3072.02 | K65: 3864.76
A66: Total | B66: 2156.59 | C66: 2222.25 | D66: 2335.86 | E66: 2558.76 | F66: 5506.68 | G66: 5723.73 | H66: 7726.02 | I66: 8081.53 | J66: 7161.75 | K66: 9419.64
A67: Receivables | B67: 12.99 | C67: 5.92 | D67: 15.1 | E67: 16.54 | F67: 17.12 | G67: 20.77 | H67: 18.26 | I67: 34.39 | J67: 81.74 | K67: 62.95
... A70: No. of Equity Shares | B70: 33231673 | C70: 332316730 | D70: 332316730 | E70: 332316730 | F70: 355487461 | G70: 355487461 | H70: 355487461 | I70: 355487461 | J70: 355487461 | K70: 355487461
A71: New Bonus Shares
A72: Face value | B72: 10 | C72: 1 | D72: 1 | E72: 1 | F72: 1 | G72: 1 | H72: 1 | I72: 1 | J72: 1 | K72: 1 | N72: Other Assest
A74: Ave Receivable | C74: =(C67+B67)/2 -> 9.455 | D74: =(D67+C67)/2 -> 10.51 | E74: =(E67+D67)/2 -> 15.82 | F74: =(F67+E67)/2 -> 16.83 | G74: =(G67+F67)/2 -> 18.945 | H74: =(H67+G67)/2 -> 19.515 | I74: =(I67+H67)/2 -> 26.325 | J74: =(J67+I67)/2 -> 58.065 | K74: =(K67+J67)/2 -> 72.345
N75: other assets-sum(receivlbe inventory cash & Bank)
A76: other assets | B76: =B65-SUM(B67:B69) -> 238.89 | C76: =C65-SUM(C67:C69) -> 242.54 | D76: =D65-SUM(D67:D69) -> 298.18 | E76: =E65-SUM(E67:E69) -> 358.79 | F76: =F65-SUM(F67:F69) -> 543.81 | G76: =G65-SUM(G67:G69) -> 544.01 | H76: =H65-SUM(H67:H69) -> 678.86 | I76: =I65-SUM(I67:I69) -> 861.14 | ... K76: =K65-SUM(K67:K69) -> 1416.92
A77: Total Assets | B77: =B61 -> 2156.59 | C77: =C61 -> 2222.25 | D77: =D61 -> 2335.86 | E77: =E61 -> 2558.76 | F77: =F61 -> 5506.68 | G77: =G61 -> 5723.73 | H77: =H61 -> 7726.02 | I77: =I61 -> 8081.53 | ... K77: =K61 -> 9419.64
A78: Average Total Assets | C78: =(C66+B66)/2 -> 2189.42 | D78: =(D66+C66)/2 -> 2279.055 | E78: =(E66+D66)/2 -> 2447.31 | F78: =(F66+E66)/2 -> 4032.72 | G78: =(G66+F66)/2 -> 5615.205 | H78: =(H66+G66)/2 -> 6724.875 | I78: =(I66+H66)/2 -> 7903.775 | J78: =(J66+I66)/2 -> 7621.64 | K78: =(K66+J66)/2 -> 8290.695
A79: Average Equity | C79: =(SUM(B57:B58)+SUM(C57:C58))/2 -> 1506.04 | D79: =(SUM(C57:C58)+SUM(D57:D58))/2 -> 1571.53 | E79: =(SUM(D57:D58)+SUM(E57:E58))/2 -> 1620.94 | F79: =(SUM(E57:E58)+SUM(F57:F58))/2 -> 2017.14 | G79: =(SUM(F57:F58)+SUM(G57:G58))/2 -> 2350.4 | H79: =(SUM(G57:G58)+SUM(H57:H58))/2 -> 2338.515 | I79: =(SUM(H57:H58)+SUM(I57:I58))/2 -> 2479.745 | J79: =(SUM(I57:I58)+SUM(J57:J58))/2 -> 3331.615 | K79: =(SUM(J57:J58)+SUM(K57:K58))/2 -> 4764.74
A81: Capital Employed | B81: =SUM(B57:B59) -> 1864.19 | C81: =SUM(C57:C59) -> 1939.43 | D81: =SUM(D57:D59) -> 1986.8 | E81: =SUM(E57:E59) -> 2140.65 | F81: =SUM(F57:F59) -> 2687.51 | G81: =SUM(G57:G59) -> 2612.96 | H81: =SUM(H57:H59) -> 7089.36 | I81: =SUM(I57:I59) -> 7059.63 | ... K81: =SUM(K57:K59) -> 7698.93
A82: Ave CE | C82: =(C81+B81)/2 -> 1901.81 | D82: =(D81+C81)/2 -> 1963.115 | E82: =(E81+D81)/2 -> 2063.725 | F82: =(F81+E81)/2 -> 2414.08 | G82: =(G81+F81)/2 -> 2650.235 | H82: =(H81+G81)/2 -> 4851.16 | I82: =(I81+H81)/2 -> 7074.495 | J82: =(J81+I81)/2 -> 6440.18 | K82: =(K81+J81)/2 -> 6759.83
A85: CASH FLOW:
A86: Report Date | B86: 42460 | C86: 42825 | D86: 43190 | E86: 43555 | F86: 43921 | G86: 44286 | H86: 44651 | I86: 45016 | J86: 45382 | K86: 45747
A87: Cash from Operating Activity | B87: 109.42 | C87: 102.44 | D87: 76.86 | E87: 20.98 | F87: 361.16 | G87: 285.03 | H87: 58.08 | I87: 594.88 | J87: 1348.98 | K87: 1660.9
A88: Cash from Investing Activity | B88: -98.4 | C88: -43.7 | D88: -4.02 | E88: -37.03 | F88: -808.56 | G88: 17.71 | H88: 56.03 | I88: -102.63 | J88: -508.21 | K88: -923.31
A89: Cash from Financing Activity | B89: -13.33 | C89: -51.36 | D89: -74.31 | E89: 37.47 | F89: 451.94 | G89: -283.11 | H89: -107.98 | I89: -491.41 | J89: -629.45 | K89: -693.67
A90: Net Cash Flow | B90: -2.31 | C90: 7.38 | D90: -1.47 | E90: 21.42 | F90: 4.54 | G90: 19.63 | H90: 6.13 | I90: 0.84 | J90: 211.32 | K90: 43.92
I92: =SUM(H67:H68)-SUM(I67:I68) -> -509.51 | J92: =SUM(I67:I68)-SUM(J67:J68) -> -268.92 | K92: =SUM(J67:J68)-SUM(K67:K68) -> -443.53
I93: =I92+I88 -> -612.14 | J93: =J92+J88 -> -777.13 | K93: =K92+K88 -> -1366.84
I94: =HistoricalFS!J28*(1-Tax_rate) -> 465.345 | J94: =HistoricalFS!K28*(1-Tax_rate) -> 974.685 | K94: =HistoricalFS!L28*(1-Tax_rate) -> 1443.585
I95: =I93/I94 -> -1.3154541 | J95: =J93/J94 -> -0.797314 | K95: =K93/K94 -> -0.94683721
A97: PRICE: | B97: 159.18 | C97: 266.7 | D97: 345.05 | E97: 361.9 | F97: 484.35 | G97: 751.05 | H97: 1275.5 | I97: 1374.95 | J97: 3948 | K97: 5325.15
A99: DERIVED:
A100: Adjusted Equity Shares in Cr | B100: 33.23 | C100: 33.23 | D100: 33.23 | E100: 33.23 | F100: 35.55 | G100: 35.55 | H100: 35.55 | I100: 35.55 | J100: 35.55 | K100: 35.55

Sheet  Cash Flow Date
C2: 42430 | D2: 42795 | E2: 43160 | F2: 43525 | G2: 43891 | H2: 44256 | I2: 44621 | J2: 44986 | K2: 45352 | L2: 45717
B3: Cash from Operating Activity -
B4: Profit from operations | C4: 2848 | D4: 3056 | E4: 3274 | F4: 3861 | G4: 4380 | H4: 4970 | I4: 4957 | J4: 6460 | K4: 7929 | L4: 6390
B5: Receivables | C5: -146 | D5: -475 | E5: -483 | F5: -205 | G5: 160 | H5: -849 | I5: -1326 | J5: -834 | K5: -362 | L5: 282
B6: Inventory | C6: 202 | D6: -629 | E6: -39 | F6: -492 | G6: -251 | H6: -409 | I6: -2354 | J6: -56 | K6: 315 | L6: -805
B7: Payables | C7: 142 | D7: 501 | E7: 442 | F7: 287 | G7: -241 | H7: 1143 | I7: 644 | J7: -539 | K7: 269 | L7: -160
B8: Other WC items | C8: 0 | D8: 0 | E8: 0 | F8: 0 | G8: 0 | H8: -92 | I8: 242 | J8: 657 | K8: -212 | L8: 114
B9: Working capital changes | C9: 198 | D9: -603 | E9: -80 | F9: -410 | G9: -331 | H9: -206 | I9: -2795 | J9: -772 | K9: 10 | L9: -570
B10: Direct taxes | C10: -802 | D10: -925 | E10: -1081 | F10: -982 | G10: -1011 | H10: -1080 | I10: -1176 | J10: -1494 | K10: -1835 | L10: -1396
B11: Cash from Investing Activity - | C11: -866 | D11: -681 | E11: -1556 | F11: -918 | G11: -518 | H11: -541 | I11: -317 | J11: -1282 | K11: -2548 | L11: -941
B12: Fixed assets purchased | C12: -817 | D12: -684 | E12: -1426 | F12: -1151 | G12: -404 | H12: -282 | I12: -551 | J12: -1446 | K12: -2496 | L12: -1830
B13: Fixed assets sold | C13: 15 | D13: 17 | E13: 17 | F13: 17 | G13: 37 | H13: 28 | I13: 40 | J13: 26 | K13: 5 | L13: 10
B14: Investments purchased | C14: -282 | D14: -153 | E14: -320 | F14: -573 | G14: -25 | H14: -140 | I14: 0 | J14: -146 | K14: -212 | L14: -1
B15: Investments sold | C15: 205 | D15: 357 | E15: 362 | F15: 733 | G15: 134 | H15: 272 | I15: 207 | J15: 446 | K15: 240 | L15: 421
... B35: Net Cash Flow | C35: 25 | D35: -202 | E35: 21 | F35: -28 | G35: 2595 | H35: -1374 | I35: -695 | J35: -446 | K35: 111 | L35: 5258

Sheet RM
B3: Return on market
B5: Year | C5: Annual
B6: 2025 | C6: 0.1051 | E6: Average Return | F6: 0.14
B7: 2024 | C7: 0.0875 | E7: Dividend Yield | F7: 1.28%1
B8: 2023 | C8: 0.1942 | E8: Total market Return | F8: 0.12
B9: 2022 | C9: 0.0432
B10: 2021 | C10: 0.2412
B11: 2020 | C11: 0.149
B12: 2019 | C12: 0.1202
B13: 2018 | C13: 0.0315
B14: 2017 | C14: 0.2865
B15: 2016 | C15: 0.0301
B16: 2015 | C16: -0.0406
B17: 2014 | C17: 0.3139
B18: 2013 | C18: 0.0676
B19: 2012 | C19: 0.277
B20: 2011 | C20: -0.2462
... B31: 2000 | C31: -0.1465

Sheet Beta-comps
B2: S.No. | C2: Name | D2: CMP Rs. | E2: Mar Cap Rs.Cr. | F2: Debt / Eq | G2: Debt Rs.Cr.
B3: 1 | C3: Trent | D3: 4260.7 | E3: 151462.5 | F3: 0.38 | G3: 2348.57
B4: 2 | C4: Avenue Super. | D4: 3909.2 | E4: 254384.57 | F4: 0.07 | G4: 1609.19
B5: 3 | C5: Page Industries | D5: 33530 | E5: 37398.94 | F5: 0.19 | G5: 268.13
B6: 4 | C6: Vedant Fashions | D6: 455.3 | E6: 11062.57 | F6: 0.27 | G6: 463.76
B7: 5 | C7: V2 Retail | D7: 2031.2 | E7: 7406.52 | F7: 3.39 | G7: 1312.5

Sheet Realtive Data
B2: S.No. | C2: Name | D2: CMP Rs. | E2: No. Eq. Shares Cr. | F2: market Capital | G2: Debt Rs.Cr. | H2: Cash End Rs.Cr. | I2: Net Debt | J2: EV | K2: Sales Rs.Cr. | L2: EV / EBITDA | M2: EBITDA | N2: Net Profit
B3: 1 | C3: Trent | D3: 4252 | E3: 35.55 | F3: 151153.27 | G3: 2348.57 | H3: 339.84 | I3: =G3-H3 -> 2008.73 | J3: =F3+G3-H3 -> 153162 | K3: 19263.16 | L3: 42.85 | M3: 4100 | N3: 1619.83
B4: 2 | C4: Avenue Super. | D4: 3909.2 | E4: 65.07 | F4: 254384.57 | G4: 1609.19 | H4: 358.2 | I4: 255783.91 | J4: 66008.74 | K4: 66008.74 | L4: 51.03 | M4: 9600 | N4: 2864.23
B5: 3 | C5: Page Industries | D5: 33530 | E5: 1.12 | F5: 37398.94 | G5: 268.13 | H5: 471.38 | I5: =G5-H5 -> -203.25 | J5: =F5+G5-H5 -> 37195.69 | K5: 5092.25 | L5: 31.11 | M5: 1250 | N5: 749.11
B6: 4 | C6: Vedant Fashions | D6: 455.3 | E6: 24.3 | F6: 11062.57 | G6: 463.76 | H6: 17.23 | I6: =G6-H6 -> 446.53 | J6: =F6+G6-H6 -> 11509.1 | K6: 1403.49 | L6: 16.35 | M6: 730 | N6: 362.35
B7: 5 | C7: V2 Retail | D7: 2031.2 | E7: 3.65 | F7: 7406.52 | G7: 1312.5 | H7: 9.4 | I7: =G7-H7 -> 1303.1 | J7: =F7+G7-H7 -> 8709.62 | K7: 2768.55 | L7: 21.11 | M7: 320 | N7: 150.4
P10: Ev

Sheet List of Stock
A2: COMPANY_NAME | B2: BSE | C2: NSE | D2: Industry
A3: 20 MICRONS LTD | B3: 533022 | C3: 20MICRONS | D3: Mining
A4: 21ST CENTURY MANAGEMENT SERVICES LTD | B4: 526921 | C4: 21STCENMGM | D4: Other Financial Services
A5: 3I INFOTECH LTD | B5: 532628 | C5: 3IINFOTECH | D5: IT Consulting & Software
A6: 3M (INDIA) LTD | B6: 523395 | C6: 3M(INDIA) | D6: Diversified
A7: 3M INDIA LTD | B7: 523395 | C7: 3MINDIA | D7: Diversified
A8: 3P LAND HOLDINGS LTD | B8: 516092 | C8: 3PLAND | D8: Paper & Paper Products
A9: 5PAISA CAPITAL LTD | B9: 540776 | C9: 5PAISA | D9: Other Financial Services
A10: 63 MOONS TECHNOLOGIES LTD | B10: 526881 | C10: 63MOONS | D10: IT Consulting & Software
A11: 7NR RETAIL LTD | B11: 540615 | C11: Not Listed | D11: Specialty Retail
A12: 7SEAS ENTERTAINMENT LTD | B12: 540874 | C12: Not Listed | D12: Movies & Entertainment
A13: 8K MILES SOFTWARE SERVICES LTD | B13: 512161 | C13: 8KMILES | D13: Internet Software & Services
A14: A & M FEBCON LTD | B14: 540697 | C14: Not Listed | D14: Industrial Machinery
A15: A AND M JUMBO BAGS LTD | B15: Not Listed | C15: AMJUMBO | D15: SME
A16: A INFRASTRUCTURE LTD | B16: 539620 | C16: Not Listed | D16: Cement & Cement Products
A17: A K SPINTEX LTD | B17: 539300 | C17: Not Listed | D17: Textiles
A18: A K CAPITAL SERVICES LTD | B18: 530499 | C18: Not Listed | D18: Finance (including NBFCs)
A19: A.F. Enterprises Ltd | B19: 538351 | C19: AFEL | D19: Investment Companies
A20: A-1 ACID LTD | B20: 542012 | C20: Not Listed | D20: Comm.Trading & Distribution
A21: A2Z INFRA ENGINEERING LTD | B21: 533292 | C21: A2ZINFRA | D21: Utilities:Non-Elec.
A22: AADHAAR VENTURES (INDIA) LTD | B22: 531611 | C22: Not Listed | D22: Finance (including NBFCs)
A23: AADHAAR VENTURES INDIA LTD | B23: 531611 | C23: Not Listed | D23: Finance (including NBFCs)
A24: AAKASH EXPLORATION SERVICES LTD | B24: Not Listed | C24: AAKASH | D24: SME
A25: AANANDA LAKSHMI SPINNING MILLS LTD | B25: 539096 | C25: Not Listed | D25: Textiles
A26: AANCHAL ISPAT LTD | B26: 538812 | C26: Not Listed | D26: Iron & Steel/Interm.Products
A27: AAR COMMERCIAL COMPANY LTD | B27: 539632 | C27: Not Listed | D27: Distributors
A28: Aar Shyam India Investment Company Ltd | B28: 542377 | C28: AARSHYAM | D28: Finance (including NBFCs)
A29: AAREY DRUGS & PHARMACEUTICALS LTD | B29: 524412 | C29: Not Listed | D29: Pharmaceuticals
A30: AARON INDUSTRIES LTD | B30: Not Listed | C30: AARON | D30: SME
A31: Aartech Solonics Ltd | B31: 542580 | C31: AARTECH | D31: Heavy Electrical Equipment
A32: AARTI DRUGS LTD | B32: 524348 | C32: AARTIDRUGS | D32: Pharmaceuticals
A33: AARTI INDUSTRIES LTD | B33: 524208 | C33: AARTIIND | D33: Commodity Chemicals
A34: AARV INFRATEL LTD | B34: 526488 | C34: Not Listed | D34: Textiles
A35: AARVEE DENIMS & EXPORTS LTD | B35: 514274 | C35: AARVEEDEN | D35: Textiles
A36: AARVI ENCON LTD | B36: Not Listed | C36: AARVI | D36: SME
A37: AASHEE INFOTECH LTD | B37: 519319 | C37: Not Listed | D37: Internet Software & Services
A38: AASWA TRADING & EXPORTS LTD | B38: 512038 | C38: Not Listed | D38: Comm.Trading & Distribution
A39: AAVAS FINANCIERS LTD | B39: 541988 | C39: AAVAS | D39: Housing Finance
A40: AAYUSH FOOD AND HERBS LTD | B40: 539528 | C40: Not Listed | D40: Packaged Foods
A41: ABAN OFFSHORE LTD | B41: 523204 | C41: ABAN | D41: Exploration & Production
A42: ABANS ENTERPRISES LTD | B42: 512165 | C42: Not Listed | D42: Comm.Trading & Distribution
A43: ABB INDIA LTD | B43: 500002 | C43: ABB | D43: Heavy Electrical Equipment
A44: ABBOTT (INDIA) LTD | B44: 500488 | C44: ABBOT(INDIA) | D44: Pharmaceuticals
A45: ABBOTT INDIA LTD | B45: 500488 | C45: ABBOTINDIA | D45: Pharmaceuticals
A46: ABC (INDIA) LTD | B46: 520123 | C46: Not Listed | D46: Surface Transportation
A47: ABC GAS INTERNATIONAL LTD | B47: 513119 | C47: Not Listed | D47: Copper
A48: ABC INDIA LTD | B48: 520123 | C48: Not Listed | D48: Surface Transportation
... A56: ABIRAMI FINANCIAL SERVICES INDIA LTD | B56: 511756 | C56: Not Listed | D56: Finance (including NBFCs)
A57: ABM INTERNATIONAL LTD | B57: Not Listed | C57: ABMINTLTD | D57: Others
A58: ABM KNOWLEDGEWARE LTD | B58: 531161 | C58: Not Listed | D58: IT Software Products
A59: ACC LTD | B59: 500410 | C59: ACC | D59: Cement & Cement Products
A60: ACCEL LTD | B60: 517494 | C60: Not Listed | D60: Storage Media & Peripherals
A61: ACCELYA KALE SOLUTIONS LTD | B61: 532268 | C61: ACCELYA | D61: IT Consulting & Software
A62: ACCORD SYNERGY LTD | B62: Not Listed | C62: ACCORD | D62: SME
A63: ACCURACY SHIPPING LTD | B63: Not Listed | C63: ACCURACY | D63: SME
A64: ACE EDUTREND LTD | B64: 530093 | C64: Not Listed | D64: Education
A65: ACE INTEGRATED SOLUTIONS LTD | B65: Not Listed | C65: ACEINTEG | D65: SME
A66: ACE MEN ENGG WORKS LTD | B66: 539661 | C66: Not Listed | D66: Distributors
A67: ACE SOFTWARE EXPORTS LTD | B67: 531525 | C67: Not Listed | D67: IT Software Products
A68: Achal Investments Ltd | B68: 538570 | C68: ACHAL | D68: Other Financial Services
A69: ACI INFOCOM LTD | B69: 517356 | C69: Not Listed | D69: Storage Media & Peripherals
A70: ACKNIT INDUSTRIES LTD | B70: 530043 | C70: Not Listed | D70: Other Apparels & Accessories
A71: ACME RESOURCES LTD | B71: 539391 | C71: Not Listed | D71: Finance (including NBFCs)
A72: ACROW INDIA LTD. | B72: 513149 | C72: ACROW | D72: Iron &amp; Steel Products
A73: ACRYSIL LTD | B73: 524091 | C73: Not Listed | D73: Plastic Products
A74: ACTION CONSTRUCTION EQUIPMENT LTD | B74: 532762 | C74: ACE | D74: Transport Related Services
A75: ACTION FINANCIAL SERVICES (INDIA) LTD | B75: 511706 | C75: Not Listed | D75: Other Financial Services
A76: ACTION FINANCIAL SERVICES INDIA LTD | B76: 511706 | C76: Not Listed | D76: Other Financial Services
A77: ACTIVE CLOTHING CO LTD | B77: 541144 | C77: Not Listed | D77: Other Apparels & Accessories
... A135: AGRI-TECH INDIA LTD | B135: 537292 | C135: AGRITECH | D135: Other Agricultural Products
A136: AGRO PHOS (INDIA) LTD | B136: Not Listed | C136: AGROPHOS | D136: SME
A137: AGRO PHOS INDIA LTD | B137: Not Listed | C137: AGROPHOS | D137: SME
A138: AGRO TECH FOODS LTD | B138: 500215 | C138: ATFL | D138: Other Agricultural Products
A139: AHIMSA INDUSTRIES LTD | B139: Not Listed | C139: AHIMSA | D139: SME
A140: AHLADA ENGINEERS LTD | B140: Not Listed | C140: AHLADA | D140: SME
A141: AHLUWALIA CONTRACTS (INDIA) LTD | B141: 532811 | C141: AHLUCONT | D141: Realty
A142: AHLUWALIA CONTRACTS INDIA LTD | B142: 532811 | C142: AHLUCONT | D142: Realty
A143: AHMEDABAD STEELCRAFT LTD | B143: 522273 | C143: Not Listed | D143: Iron & Steel/Interm.Products
A144: AI CHAMPDANY INDUSTRIES LTD | B144: 532806 | C144: Not Listed | D144: Jute & Jute Products
A145: AIA ENGINEERING LTD | B145: 532683 | C145: AIAENG | D145: Other Industrial Goods
A146: AIMCO PESTICIDES LTD | B146: 524288 | C146: Not Listed | D146: Agrochemicals
A147: AIRAN LTD | B147: Not Listed | C147: AIRAN | D147: SME
A148: AIRO LAM LTD | B148: Not Listed | C148: AIROLAM | D148: SME
A149: AISHWARYA TELECOM LTD | B149: 532975 | C149: Not Listed | D149: Telecom Equipment
A150: AJANTA PHARMA LTD | B150: 532331 | C150: AJANTPHARM | D150: Pharmaceuticals
A151: AJANTA SOYA LTD | B151: 519216 | C151: Not Listed | D151: Edible Oils
A152: AJCON GLOBAL SERVICES LTD | B152: 511692 | C152: Not Listed | D152: Other Financial Services
A153: AJEL LTD | B153: 530713 | C153: Not Listed | D153: IT Consulting & Software
A154: AJMERA REALTY & INFRA (INDIA) LTD | B154: 513349 | C154: AJMERA | D154: Realty
A155: AJMERA REALTY & INFRA INDIA LTD | B155: 513349 | C155: AJMERA | D155: Realty
A156: AJOONI BIOTECH LTD | B156: Not Listed | C156: AJOONI | D156: SME
A157: AJWA FUN WORLD & RESORT LTD | B157: 526628 | C157: Not Listed | D157: Other Leisure Facilities
A158: AKAR AUTO INDUSTRIES LTD | B158: 530621 | C158: Not Listed | D158: Industrial Machinery
A159: AKASH INFRA PROJECTS LTD | B159: Not Listed | C159: AKASH | D159: SME
A160: AKASHDEEP METAL INDUSTRIES LTD | B160: 538778 | C160: Not Listed | D160: Finance (including NBFCs)
A161: AKG EXIM LTD | B161: Not Listed | C161: AKG | D161: SME
A162: AKI (INDIA) LTD | B162: 542020 | C162: Not Listed | D162: Other Apparels & Accessories
A163: AKI INDIA LTD | B163: 542020 | C163: Not Listed | D163: Other Apparels & Accessories
A164: AKM LACE AND EMBROTEX LTD | B164: 540718 | C164: Not Listed | D164: Textiles
A165: AKME STAR HOUSING FINANCE LTD | B165: 539017 | C165: Not Listed | D165: Housing Finance
...
