Workbook
Name Gross_Margin: Annual_Budget_Model!$C$12
Name Inital_headcount: Annual_Budget_Model!$C$16
Name MRR: Annual_Budget_Model!$C$10
Name MRR_Growth_Rate: Annual_Budget_Model!$C$11
Name Office_Rent: Annual_Budget_Model!$C$19
Name Software_tools: Annual_Budget_Model!$C$20

Sheet Budgeting>

Sheet Annual_Budget_Model
B3: Growth Tech Inc. - FY2026 Budget
B5: Create a complete FY2026 budget for a SaaS startup using the assumptions provided below
A7: # | B7: Assumptions
B9: Assumption | C9: Value | D9: Note
B10: Starting Monthly Recurring Revenue (MRR) | C10: 300000 | D10: USD
B11: MRR Growth Rate | C11: 0.08
B12: Gross Margin | C12: 0.8
B13: Sales & Marketing % of Revenue | C13: 0.15
B14: R&D % of Revenue | C14: 0.05
B15: G&A % of Revenue | C15: 0.08
B16: Initial Headcount | C16: 25 | D16: Employees
B17: Monthly Headcount Addition | C17: 2 | D17: Employees/Month
B18: Average Salary per Employee | C18: 60000 | D18: USD/Year
B19: Office rent (Annual) | C19: 120000 | D19: USD
B20: Software & Tools (Annual) | C20: 60000 | D20: USD
B22: Annual Budget
B23: Line Item | C23: Jan | D23: Feb | E23: Mar | F23: Apr | G23: May | H23: Jun | I23: Jul | J23: Aug | K23: Sep | L23: Oct | M23: Nov | N23: Dec | O23: FY 2026 Total
B25: Revenue | C25: =C10 -> 300000 | D25: =C25*(1+MRR_Growth_Rate) -> 324000 | E25: =D25*(1+MRR_Growth_Rate) -> 349920 | F25: =E25*(1+MRR_Growth_Rate) -> 377913.6 | G25: =F25*(1+MRR_Growth_Rate) -> 408146.69 | H25: =G25*(1+MRR_Growth_Rate) -> 440798.42 | I25: =H25*(1+MRR_Growth_Rate) -> 476062.3 | J25: =I25*(1+MRR_Growth_Rate) -> 514147.28 | K25: =J25*(1+MRR_Growth_Rate) -> 555279.06 | ... N25: =M25*(1+MRR_Growth_Rate) -> 699491.7 | O25: =SUM(C25:N25) -> 5693137.9
B27: Cost of Goods Sold | C27: =C25*(1-Gross_Margin) -> 60000 | D27: =D25*(1-Gross_Margin) -> 64800 | E27: =E25*(1-Gross_Margin) -> 69984 | F27: =F25*(1-Gross_Margin) -> 75582.72 | G27: =G25*(1-Gross_Margin) -> 81629.338 | H27: =H25*(1-Gross_Margin) -> 88159.685 | I27: =I25*(1-Gross_Margin) -> 95212.459 | J27: =J25*(1-Gross_Margin) -> 102829.46 | ... N27: =N25*(1-Gross_Margin) -> 139898.34 | O27: =SUM(C27:N27) -> 1138627.6
B29: Gross Margin | C29: =C25-C27 -> 240000 | D29: =D25-D27 -> 259200 | E29: =E25-E27 -> 279936 | F29: =F25-F27 -> 302330.88 | G29: =G25-G27 -> 326517.35 | H29: =H25-H27 -> 352638.74 | I29: =I25-I27 -> 380849.84 | J29: =J25-J27 -> 411317.82 | ... N29: =N25-N27 -> 559593.36 | O29: =SUM(C29:N29) -> 4554510.4
B30: Gross Margin % | C30: =C29/C25 -> 0.8 | D30: =D29/D25 -> 0.8 | E30: =E29/E25 -> 0.8 | F30: =F29/F25 -> 0.8 | G30: =G29/G25 -> 0.8 | H30: =H29/H25 -> 0.8 | I30: =I29/I25 -> 0.8 | J30: =J29/J25 -> 0.8 | ... O30: =O29/O25 -> 0.8
B32: Operating Expenses:
B33: Sales & Marketing | C33: =C25*$C$13 -> 45000 | D33: =D25*$C$13 -> 48600 | E33: =E25*$C$13 -> 52488 | F33: =F25*$C$13 -> 56687.04 | G33: =G25*$C$13 -> 61222.003 | H33: =H25*$C$13 -> 66119.763 | I33: =I25*$C$13 -> 71409.345 | J33: =J25*$C$13 -> 77122.092 | ... N33: =N25*$C$13 -> 104923.75 | O33: =SUM(C33:N33) -> 853970.69
B34: Research & Development | C34: =C25*$C$14 -> 15000 | D34: =D25*$C$14 -> 16200 | E34: =E25*$C$14 -> 17496 | F34: =F25*$C$14 -> 18895.68 | G34: =G25*$C$14 -> 20407.334 | H34: =H25*$C$14 -> 22039.921 | I34: =I25*$C$14 -> 23803.115 | J34: =J25*$C$14 -> 25707.364 | ... N34: =N25*$C$14 -> 34974.585 | O34: =SUM(C34:N34) -> 284656.9
B35: General & Administrative | C35: =C25*$C$15 -> 24000 | D35: =D25*$C$15 -> 25920 | E35: =E25*$C$15 -> 27993.6 | F35: =F25*$C$15 -> 30233.088 | G35: =G25*$C$15 -> 32651.735 | H35: =H25*$C$15 -> 35263.874 | I35: =I25*$C$15 -> 38084.984 | J35: =J25*$C$15 -> 41131.782 | ... N35: =N25*$C$15 -> 55959.336 | O35: =SUM(C35:N35) -> 455451.04
B36: Salaries | C36: =$C$18/12*C44 -> 125000 | D36: =$C$18/12*D44 -> 135000 | E36: =$C$18/12*E44 -> 145000 | F36: =$C$18/12*F44 -> 155000 | G36: =$C$18/12*G44 -> 165000 | H36: =$C$18/12*H44 -> 175000 | I36: =$C$18/12*I44 -> 185000 | J36: =$C$18/12*J44 -> 195000 | ... N36: =$C$18/12*N44 -> 235000 | O36: =SUM(C36:N36) -> 2160000
B37: Office Rent | C37: =Office_Rent/12 -> 10000 | D37: =Office_Rent/12 -> 10000 | E37: =Office_Rent/12 -> 10000 | F37: =Office_Rent/12 -> 10000 | G37: =Office_Rent/12 -> 10000 | H37: =Office_Rent/12 -> 10000 | I37: =Office_Rent/12 -> 10000 | J37: =Office_Rent/12 -> 10000 | ... N37: =Office_Rent/12 -> 10000 | O37: =SUM(C37:N37) -> 120000
B38: Software & Tools | C38: =Software_tools/12 -> 5000 | D38: =Software_tools/12 -> 5000 | E38: =Software_tools/12 -> 5000 | F38: =Software_tools/12 -> 5000 | G38: =Software_tools/12 -> 5000 | H38: =Software_tools/12 -> 5000 | I38: =Software_tools/12 -> 5000 | J38: =Software_tools/12 -> 5000 | ... N38: =Software_tools/12 -> 5000 | O38: =SUM(C38:N38) -> 60000
B39: Total Operating Expenses | C39: =SUM(C33:C38) -> 224000 | D39: =SUM(D33:D38) -> 240720 | E39: =SUM(E33:E38) -> 257977.6 | F39: =SUM(F33:F38) -> 275815.81 | G39: =SUM(G33:G38) -> 294281.07 | H39: =SUM(H33:H38) -> 313423.56 | I39: =SUM(I33:I38) -> 333297.44 | J39: =SUM(J33:J38) -> 353961.24 | ... N39: =SUM(N33:N38) -> 445857.68 | O39: =SUM(C39:N39) -> 3934078.6
B41: EBITDA | C41: =C29-C39 -> 16000 | D41: =D29-D39 -> 18480 | E41: =E29-E39 -> 21958.4 | F41: =F29-F39 -> 26515.072 | G41: =G29-G39 -> 32236.278 | H41: =H29-H39 -> 39215.18 | I41: =I29-I39 -> 47552.394 | J41: =J29-J39 -> 57356.586 | ... O41: =O29-O39 -> 620431.73
B42: EBITDA Margin % | C42: =C41/C25 -> 0.053333333 | D42: =D41/D25 -> 0.057037037 | E42: =E41/E25 -> 0.062752629 | F42: =F41/F25 -> 0.07016173 | G42: =G41/G25 -> 0.078982088 | H42: =H41/H25 -> 0.088963975 | I42: =I41/I25 -> 0.099886915 | J42: =J41/J25 -> 0.11155672 | ... O42: =O41/O25 -> 0.10897887
B44: Headcount | C44: =Inital_headcount -> 25 | D44: =C44+$C$17 -> 27 | E44: =D44+$C$17 -> 29 | F44: =E44+$C$17 -> 31 | G44: =F44+$C$17 -> 33 | H44: =G44+$C$17 -> 35 | I44: =H44+$C$17 -> 37 | J44: =I44+$C$17 -> 39 | K44: =J44+$C$17 -> 41 | ... N44: =M44+$C$17 -> 47 | O44: =N44 -> 47

Sheet Budget_Reconciliation
B2: Scenario: GrowthTech Inc. - FY2026 Budget
B4: Top-Down Budget (Leadership Target)
B5: Line Item | C5: FY 2027 | D5: % of Revenue | E5: Notes
B7: Revenue Target | C7: 15000000 | D7: - | E7: CEO strategic goal
B8: Gross Profit Target | C8: 11250000 | D8: =C8/$C$7 -> 0.75 | E8: 75% Target margin
B9: S&M Budget | C9: 5250000 | D9: =C9/$C$7 -> 0.35 | E9: 35% of Revenue
B10: R&D Budget | C10: 3000000 | D10: =C10/$C$7 -> 0.2 | E10: 20% of Revenue
B11: G&A Budget | C11: 1500000 | D11: =C11/$C$7 -> 0.1 | E11: 10% of Revenue
B12: Total OpEx | C12: 9750000 | D12: =C12/$C$7 -> 0.65 | E12: 65% of Revenue
B13: Target EBITDA | C13: 1500000 | D13: =C13/$C$7 -> 0.1 | E13: 10% Target margin
B15: Bottom-Up Budget (Department Submissions)
B16: Line Item | C16: FY 2027 | D16: % of Revenue | E16: Notes
B18: Revenue Target | C18: 12500000 | D18: - | E18: Sales team forecast
B19: Gross Profit Target | C19: 9375000 | D19: =C19/$C$18 -> 0.75 | E19: Same margin assumption
B20: S&M Budget | C20: 4625000 | D20: =C20/$C$18 -> 0.37 | E20: Dept. head request
B21: R&D Budget | C21: 3500000 | D21: =C21/$C$18 -> 0.28 | E21: Dept. head request
B22: G&A Budget | C22: 2125000 | D22: =C22/$C$18 -> 0.17 | E22: Dept. head request
B23: Total OpEx | C23: 10250000 | D23: =C23/$C$18 -> 0.82 | E23: Higher than target
B24: Target EBITDA | C24: -875000 | D24: =C24/$C$18 -> -0.07 | E24: Nagative margin

Sheet Rrecommended_Reconciliation
B2: Budget Approach Comparison & Reconciliation
B4: Bottom-Up Budget
B5: Metric | C5: Top Down | D5: Bottom-Up | E5: Variance
B7: Revenue | C7: =Budget_Reconciliation!C7 -> 15000000 | D7: =Budget_Reconciliation!C18 -> 12500000 | E7: =D7-C7 -> -2500000
B8: Total OpEx | C8: =Budget_Reconciliation!C12 -> 9750000 | D8: =Budget_Reconciliation!C23 -> 10250000 | E8: =D8-C8 -> 500000
B9: EBITDA | C9: =Budget_Reconciliation!C13 -> 1500000 | D9: =Budget_Reconciliation!C24 -> -875000 | E9: =D9-C9 -> -2375000
B10: EBITDA Margin | C10: =C9/C7 -> 0.1 | D10: =D9/D7 -> -0.07 | E10: -
B12: Key Findings
B14: 1. Revenue gap: Bottom-up forecast is $2.5M (~17%) blow top down target. Sales team may lack confidence or resources to hit CEO goal.
B15: 2. OpEx Overspend Crisis: Despite lower revenue, department requested $500K more in spending. OpEx ratio is 82% vs 65% TARGET.
B16: 3. Profitability Crisis: Botto-up plan shows negative EBITDA of $875K vs target of +1.5M profit. $2.37M gap.
B17: 4. Department Inefficiency: Each Department exceeded their % allocation.
B18: 5. Unrealistic Expectaions: Top-down target may be too aggressive without corresponding investment in sales capacity.
A20: # | B20: Recommened Reconciliation Approach
B21: Line Item | C21: Top-down | D21: Bottom-Up | E21: Recommened | F21: Rationale
B23: Revenue | C23: =Budget_Reconciliation!C7 -> 15000000 | D23: =Budget_Reconciliation!C18 -> 12500000 | E23: =D23*1.1 -> 13750000 | F23: Stretch goal: +10% above bottom-up
B24: Gross Profit | C24: =Budget_Reconciliation!C8 -> 11250000 | D24: =Budget_Reconciliation!C19 -> 9375000 | E24: =E23*0.75 -> 10312500 | F24: Maintain 75% Margins
B25: S&M (40%) | C25: =Budget_Reconciliation!C9 -> 5250000 | D25: =Budget_Reconciliation!C20 -> 4625000 | E25: =E23*40% -> 5500000 | F25: Invest more to hit revenue target
B26: R&D (23%) | C26: =Budget_Reconciliation!C10 -> 3000000 | D26: =Budget_Reconciliation!C21 -> 3500000 | E26: =E23*23% -> 3162500 | F26: Compromise between target
B27: G&A (12%) | C27: =Budget_Reconciliation!C11 -> 1500000 | D27: =Budget_Reconciliation!C22 -> 2125000 | E27: =E23*12% -> 1650000 | F27: Tirm 22% from deptt request
B28: Total OpEx | C28: =Budget_Reconciliation!C12 -> 9750000 | D28: =Budget_Reconciliation!C23 -> 10250000 | E28: =SUM(E25:E27) -> 10312500 | F28: Match gross profit exactly
B29: EBITDA | C29: =Budget_Reconciliation!C13 -> 1500000 | D29: =Budget_Reconciliation!C24 -> -875000 | E29: =E24-E28 -> 0 | F29: Breakeven year, invest for grwoth
B31: Implementation Steps & Best Practices
B33: 1. Negotiate with Sales: Challenge them to commit to $13.75M with increased S&M investment. Add 3-5 sales reps.
B34: 2. Cost reduction workshop: Work with G&A to find $475K in savings. Focus on subscriptions, travel, consultants.
B35: 3. R&D Prioritization: Cut lower-priority projects. Defer $337K to to maintain product velocity within buget.
B36: 4. Quarterly Reviews: Implement rolling forecast. Adjust quarterly based on actual perforemance VS Plan.
B37: 5. Senario Planning: Build upside/downside cases. If revenue hits $15M, reinvest savings. If misses, trigger cost controls.
B38: 6. Accountability: Tie executive bonuses to achieving reconciled budget. Monthly variance reviews with department heads.
B39: 7. Communication: Present reconciled budget to board as 'Investment Year' - breakeven acceptable to capture growth.
B40: 8. Contingency: Build 5% reserve ($516) for unforeseen expenses. Release only with CFO approval.
