Workbook
Name After_tax_discount_rate: 'RE Model'!$K$23
Name capital_gain_rate: 'RE Model'!$K$9
Name Closing_cost: 'RE Model'!$E$17
Name Deperication_rate: 'RE Model'!$E$16
Name Depericiable_basis: 'RE Model'!$E$15
Name Down_Payment: 'RE Model'!$E$14
Name Exit_cap_rate: 'RE Model'!$E$22
Name Exit_selling_rate: 'RE Model'!$E$23
Name Inflation_Rate: 'RE Model'!$E$8
Name Loan_Amount: 'RE Model'!$K$14
Name Loan_Fees: 'RE Model'!$K$13
Name Loan_interest_rate: 'RE Model'!$K$15
Name loan_term: 'RE Model'!$K$16
Name Marginal_tax_rate: 'RE Model'!$K$8
Name NPV_discount_rate: 'RE Model'!$K$22
Name Pertax_discount_rate: 'RE Model'!$K$22
Name Purchases_Price: 'RE Model'!$E$13
Name Vacancy_Rate: 'RE Model'!$E$9

Sheet RE Model
C2: REAL ESTATE MODEL
C4: KEY ASSUMPTIONS
A6: # | C6: Global Inputs | H6: Taxation Inputs
C8: Inflation rate | E8: 0.03 | H8: Marginal Tax rate | K8: 0.22
C9: Vacancy rate | E9: 0.05 | H9: Capital gain rate | K9: 0.15
C11: Purchases Inputs | H11: Loan cost & cash flow
C13: Purchases price | E13: 1130000 | F13: - | H13: Loan Fees | K13: =Loan_Amount*L13 -> 4237.5 | L13: 0.005
C14: Down payment | E14: =E13*F14 -> 282500 | F14: 0.25 | H14: Loan Amount | K14: =Purchases_Price-Down_Payment -> 847500 | L14: -
C15: Deperciable basis | E15: =E13*F15+E18 -> 904000 | F15: 0.8 | H15: Loan interest rate | K15: 0.035 | L15: -
C16: Deperication rate | E16: 0.05 | F16: - | H16: Loan term | K16: =L16*12 -> 360 | L16: 30
C17: Closing cost | E17: 15000 | F17: -
C18: Addition Capex | E18: 0 | F18: -
C20: Sales exit inputs | H20: NPV Calculation Inputs
C22: Exit cap rate | E22: 0.045 | H22: Pretax discount rate | K22: 0.12
C23: Exit selling cost | E23: 0.06 | H23: Aftertax discoount rate | K23: 0.09
C25: Monthly loan payment | E25: =PMT(Loan_interest_rate/12,loan_term,Loan_Amount) -> -3805.6537
A27: # | C27: FORECASTING OPERATING INCOME
B29: Particular | F29: 1 | G29: =F29+1 -> 2 | H29: =G29+1 -> 3 | I29: =H29+1 -> 4 | J29: =I29+1 -> 5 | K29: =J29+1 -> 6 | L29: =K29+1 -> 7 | M29: =L29+1 -> 8 | N29: =M29+1 -> 9 | ... P29: =O29+1 -> 11
B31: Operating Income
B32: Rental Income | D32: Monthly | E32: Units
C33: Studios
C34: One bedrooms
C35: Two bedrooms | D35: 1000 | E35: 12 | F35: =D35*E35*12 -> 144000 | G35: =F35*(1+Inflation_Rate) -> 148320 | H35: =G35*(1+Inflation_Rate) -> 152769.6 | I35: =H35*(1+Inflation_Rate) -> 157352.69 | J35: =I35*(1+Inflation_Rate) -> 162073.27 | K35: =J35*(1+Inflation_Rate) -> 166935.47 | L35: =K35*(1+Inflation_Rate) -> 171943.53 | M35: =L35*(1+Inflation_Rate) -> 177101.84 | N35: =M35*(1+Inflation_Rate) -> 182414.89 | ... P35: =O35*(1+Inflation_Rate) -> 193523.96
C37: Total Potencial Income | F37: =SUM(F33:F35) -> 144000 | G37: =SUM(G33:G35) -> 148320 | H37: =SUM(H33:H35) -> 152769.6 | I37: =SUM(I33:I35) -> 157352.69 | J37: =SUM(J33:J35) -> 162073.27 | K37: =SUM(K33:K35) -> 166935.47 | L37: =SUM(L33:L35) -> 171943.53 | M37: =SUM(M33:M35) -> 177101.84 | ... P37: =SUM(P33:P35) -> 193523.96
C39: Vacancy Allowance | F39: =F37*Vacancy_Rate -> 7200 | G39: =G37*Vacancy_Rate -> 7416 | H39: =H37*Vacancy_Rate -> 7638.48 | I39: =I37*Vacancy_Rate -> 7867.6344 | J39: =J37*Vacancy_Rate -> 8103.6634 | K39: =K37*Vacancy_Rate -> 8346.7733 | L39: =L37*Vacancy_Rate -> 8597.1765 | M39: =M37*Vacancy_Rate -> 8855.0918 | ... P39: =P37*Vacancy_Rate -> 9676.1979
C41: Forecasted Income | F41: =F37-F39 -> 136800 | G41: =G37-G39 -> 140904 | H41: =H37-H39 -> 145131.12 | I41: =I37-I39 -> 149485.05 | J41: =J37-J39 -> 153969.61 | K41: =K37-K39 -> 158588.69 | L41: =L37-L39 -> 163346.35 | M41: =M37-M39 -> 168246.74 | ... P41: =P37-P39 -> 183847.76
B43: Operating Expenses
C44: Admin
C45: Minor Repairs
C46: Maintanac | F46: 0 | G46: 0 | H46: 0 | I46: 0 | J46: 0 | K46: 0 | L46: 0 | M46: 0 | N46: 0 | O46: 0 | P46: 0
C47: Maintenance/Landscape | F47: 0 | G47: 0 | H47: 0 | I47: 0 | J47: 0 | K47: 0 | L47: 0 | M47: 0 | N47: 0 | O47: 0 | P47: 0
C48: Leasing Commissions | D48: 0.05 | F48: =F41*$D$48 -> 6840 | G48: =G41*$D$48 -> 7045.2 | H48: =H41*$D$48 -> 7256.556 | I48: =I41*$D$48 -> 7474.2527 | J48: =J41*$D$48 -> 7698.4803 | K48: =K41*$D$48 -> 7929.4347 | L48: =L41*$D$48 -> 8167.3177 | M48: =M41*$D$48 -> 8412.3372 | ... P48: =P41*$D$48 -> 9192.388
C49: Insurance | D49: 2000 | F49: =D49 -> 2000 | G49: =F49*(1+Inflation_Rate) -> 2060 | H49: =G49*(1+Inflation_Rate) -> 2121.8 | I49: =H49*(1+Inflation_Rate) -> 2185.454 | J49: =I49*(1+Inflation_Rate) -> 2251.0176 | K49: =J49*(1+Inflation_Rate) -> 2318.5481 | L49: =K49*(1+Inflation_Rate) -> 2388.1046 | M49: =L49*(1+Inflation_Rate) -> 2459.7477 | N49: =M49*(1+Inflation_Rate) -> 2533.5402 | ... P49: =O49*(1+Inflation_Rate) -> 2687.8328
C50: Legal & Other Professinal fees | F50: 0 | G50: 0 | H50: 0 | I50: 0 | J50: 0 | K50: 0 | L50: 0 | M50: 0 | N50: 0 | O50: 0 | P50: 0
C51: Management Fees | F51: 0 | G51: 0 | H51: 0 | I51: 0 | J51: 0 | K51: 0 | L51: 0 | M51: 0 | N51: 0 | O51: 0 | P51: 0
C52: Repairs/ Units Turns | F52: 0 | G52: 0 | H52: 0 | I52: 0 | J52: 0 | K52: 0 | L52: 0 | M52: 0 | N52: 0 | O52: 0 | P52: 0
C53: Home Warrantly | F53: 0 | G53: 0 | H53: 0 | I53: 0 | J53: 0 | K53: 0 | L53: 0 | M53: 0 | N53: 0 | O53: 0 | P53: 0
C54: Propety Tax | D54: 14000 | F54: =D54 -> 14000 | G54: =F54*(1+Inflation_Rate) -> 14420 | H54: =G54*(1+Inflation_Rate) -> 14852.6 | I54: =H54*(1+Inflation_Rate) -> 15298.178 | J54: =I54*(1+Inflation_Rate) -> 15757.123 | K54: =J54*(1+Inflation_Rate) -> 16229.837 | L54: =K54*(1+Inflation_Rate) -> 16716.732 | M54: =L54*(1+Inflation_Rate) -> 17218.234 | N54: =M54*(1+Inflation_Rate) -> 17734.781 | ... P54: =O54*(1+Inflation_Rate) -> 18814.829
C55: Utilites | F55: 0 | G55: 0 | H55: 0 | I55: 0 | J55: 0 | K55: 0 | L55: 0 | M55: 0 | N55: 0 | O55: 0 | P55: 0
C56: Others | F56: 0 | G56: 0 | H56: 0 | I56: 0 | J56: 0 | K56: 0 | L56: 0 | M56: 0 | N56: 0 | O56: 0 | P56: 0
C57: Total Oer | F57: 0 | G57: 0 | H57: 0 | I57: 0 | J57: 0 | K57: 0 | L57: 0 | M57: 0 | N57: 0 | O57: 0 | P57: 0
C58: Total Operating Expenses | F58: =SUM(F48:F57) -> 22840 | G58: =SUM(G48:G57) -> 23525.2 | H58: =SUM(H48:H57) -> 24230.956 | I58: =SUM(I48:I57) -> 24957.885 | J58: =SUM(J48:J57) -> 25706.621 | K58: =SUM(K48:K57) -> 26477.82 | L58: =SUM(L48:L57) -> 27272.154 | M58: =SUM(M48:M57) -> 28090.319 | ... P58: =SUM(P48:P57) -> 30695.05
B60: Operating Income | F60: =F41-F58 -> 113960 | G60: =G41-G58 -> 117378.8 | H60: =H41-H58 -> 120900.16 | I60: =I41-I58 -> 124527.17 | J60: =J41-J58 -> 128262.98 | K60: =K41-K58 -> 132110.87 | L60: =L41-L58 -> 136074.2 | M60: =M41-M58 -> 140156.43 | ... P60: =P41-P58 -> 153152.71
A62: # | B62: CALCULATION OF PRETAX NPV & IRR
B64: Total Annual Loan Payments | F64: =$E$25*12 -> -45667.845 | G64: =$E$25*12 -> -45667.845 | H64: =$E$25*12 -> -45667.845 | I64: =$E$25*12 -> -45667.845 | J64: =$E$25*12 -> -45667.845 | K64: =$E$25*12 -> -45667.845 | L64: =$E$25*12 -> -45667.845 | M64: =$E$25*12 -> -45667.845 | ... P64: =$E$25*12 -> -45667.845
B66: Pretax Cash Flows
C67: Initial Investment | E67: =-(Down_Payment+Closing_cost+E18+Loan_Fees) -> -301737.5
C68: Operating Income | F68: =F60 -> 113960 | G68: =G60 -> 117378.8 | H68: =H60 -> 120900.16 | I68: =I60 -> 124527.17 | J68: =J60 -> 128262.98 | K68: =K60 -> 132110.87 | L68: =L60 -> 136074.2 | M68: =M60 -> 140156.43 | ... P68: =P60 -> 153152.71
C69: Loan Payments | F69: {=F64} -> -45667.845 | G69: -45667.845 | H69: -45667.845 | I69: -45667.845 | J69: -45667.845 | K69: -45667.845 | L69: -45667.845 | M69: -45667.845 | N69: -45667.845 | O69: -45667.845 | P69: -45667.845
C70: Sales Proceeds | P70: =P60/Exit_cap_rate -> 3403393.6
C71: Selling Cost | P71: =P70*-Exit_selling_rate -> -204203.61
C72: Loan Payments | P72: =-'Loan Amortization Schedule'!F132 -> -642834.03
C73: Total Pretax Cash Flow | E73: =SUM(E67:E72) -> -301737.5 | F73: =SUM(F67:F72) -> 68292.155 | G73: =SUM(G67:G72) -> 71710.955 | H73: =SUM(H67:H72) -> 75232.319 | I73: =SUM(I67:I72) -> 78859.324 | J73: =SUM(J67:J72) -> 82595.139 | K73: =SUM(K67:K72) -> 86443.029 | L73: =SUM(L67:L72) -> 90406.355 | ... P73: =SUM(P67:P72) -> 2663840.8
C75: Cap Rate | D75: =F60/Purchases_Price -> 0.10084956
C76: Pertax IRR | D76: =IRR(E73:P73) -> 0.35353484 | F76: =F73/-$E$67 -> 0.22632969 | G76: =G73/-$E$67 -> 0.23766007 | H76: =H73/-$E$67 -> 0.24933036 | I76: =I73/-$E$67 -> 0.26135076 | J76: =J73/-$E$67 -> 0.27373177 | K76: =K73/-$E$67 -> 0.28648421 | L76: =L73/-$E$67 -> 0.29961922 | M76: =M73/-$E$67 -> 0.31314829 | ... P76: =P73/-$E$67 -> 8.8283385
C77: Cash On Cash Return | D77: =AVERAGE(F76:O76) -> 0.28161738
C78: Pretax NPV | D78: =NPV(Pertax_discount_rate,E73:P73)/(1+Pertax_discount_rate) -> 736878.96
C79: Avg. DSCR | D79: =AVERAGE(F79:P79) -> 2.9055184 | F79: =F60/-F64 -> 2.4954101 | G79: =G60/-G64 -> 2.5702724 | H79: =H60/-H64 -> 2.6473806 | I79: =I60/-I64 -> 2.726802 | J79: =J60/-J64 -> 2.808606 | K79: =K60/-K64 -> 2.8928642 | L79: =L60/-L64 -> 2.9796501 | M79: =M60/-M64 -> 3.0690396 | ... P79: =P60/-P64 -> 3.3536225
A81: # | B81: CALCULATION OF AFTERTAX NPV & IRR
B83: Taxable Income Forecast
C84: Operating Income | F84: =F60 -> 113960 | G84: =G60 -> 117378.8 | H84: =H60 -> 120900.16 | I84: =I60 -> 124527.17 | J84: =J60 -> 128262.98 | K84: =K60 -> 132110.87 | L84: =L60 -> 136074.2 | M84: =M60 -> 140156.43 | ... P84: =P60 -> 153152.71
C85: Loan Interest | F85: =SUM('Loan Amortization Schedule'!D6:D17) -> -29403.235 | G85: =SUM('Loan Amortization Schedule'!D18:D29) -> -28824.752 | H85: =SUM('Loan Amortization Schedule'!D30:D41) -> -28225.695 | I85: =SUM('Loan Amortization Schedule'!D42:D53) -> -27605.331 | J85: =SUM('Loan Amortization Schedule'!D54:D65) -> -26962.902 | K85: =SUM('Loan Amortization Schedule'!D66:D77) -> -26297.624 | L85: =SUM('Loan Amortization Schedule'!D78:D89) -> -25608.685 | M85: =SUM('Loan Amortization Schedule'!D90:D101) -> -24895.241 | N85: =SUM('Loan Amortization Schedule'!D102:D113) -> -24156.423 | O85: =SUM('Loan Amortization Schedule'!D114:D125) -> -23391.327 | P85: =SUM('Loan Amortization Schedule'!D126:D137) -> -22599.02
C86: Deperication | F86: =-Depericiable_basis*Deperication_rate -> -45200 | G86: =-Depericiable_basis*Deperication_rate -> -45200 | H86: =-Depericiable_basis*Deperication_rate -> -45200 | I86: =-Depericiable_basis*Deperication_rate -> -45200 | J86: =-Depericiable_basis*Deperication_rate -> -45200 | K86: =-Depericiable_basis*Deperication_rate -> -45200 | L86: =-Depericiable_basis*Deperication_rate -> -45200 | M86: =-Depericiable_basis*Deperication_rate -> -45200 | ... P86: =-Depericiable_basis*Deperication_rate -> -45200
C87: Loan fee amortization | F87: =-Loan_Fees/loan_term*12 -> -141.25 | G87: =-Loan_Fees/loan_term*12 -> -141.25 | H87: =-Loan_Fees/loan_term*12 -> -141.25 | I87: =-Loan_Fees/loan_term*12 -> -141.25 | J87: =-Loan_Fees/loan_term*12 -> -141.25 | K87: =-Loan_Fees/loan_term*12 -> -141.25 | L87: =-Loan_Fees/loan_term*12 -> -141.25 | M87: =-Loan_Fees/loan_term*12 -> -141.25 | ... O87: =-Loan_Fees/loan_term*12 -> -141.25 | P87: =-Loan_Fees-SUM(F87:O87) -> -2825
C88: Taxable Income (Loss) | F88: =SUM(F84:F87) -> 39215.515 | G88: =SUM(G84:G87) -> 43212.798 | H88: =SUM(H84:H87) -> 47333.219 | I88: =SUM(I84:I87) -> 51580.588 | J88: =SUM(J84:J87) -> 55958.832 | K88: =SUM(K84:K87) -> 60471.999 | L88: =SUM(L84:L87) -> 65124.265 | M88: =SUM(M84:M87) -> 69919.934 | ... P88: =SUM(P84:P87) -> 82528.691
B90: Tax Expenses (Savings) | F90: =F88*-Marginal_tax_rate -> -8627.4133 | G90: =G88*-Marginal_tax_rate -> -9506.8155 | H90: =H88*-Marginal_tax_rate -> -10413.308 | I90: =I88*-Marginal_tax_rate -> -11347.729 | J90: =J88*-Marginal_tax_rate -> -12310.943 | K90: =K88*-Marginal_tax_rate -> -13303.84 | L90: =L88*-Marginal_tax_rate -> -14327.338 | M90: =M88*-Marginal_tax_rate -> -15382.386 | ... P90: =P88*-Marginal_tax_rate -> -18156.312
B92: Aftertax operating cash flows | F92: =F68+F69+F90 -> 59664.742 | G92: =G68+G69+G90 -> 62204.14 | H92: =H68+H69+H90 -> 64819.011 | I92: =I68+I69+I90 -> 67511.595 | J92: =J68+J69+J90 -> 70284.196 | K92: =K68+K69+K90 -> 73139.189 | L92: =L68+L69+L90 -> 76079.017 | M92: =M68+M69+M90 -> 79106.195 | ... P92: =P68+P69+P90 -> 89328.554
B94: Other aftertax Cashflow
C95: Initial Investment | E95: =E67 -> -301737.5
C96: Sales Proceed | P96: =P70 -> 3403393.6
C97: Selling cost | P97: =P71 -> -204203.61
C98: Loan Repayment | P98: =P72 -> -642834.03
C99: Capital gain tax | P99: =(P96+P97-(Purchases_Price+Closing_cost))*-capital_gain_rate -> -308128.49
B100: After tax all inclue cash flow | E100: =SUM(E92:E99) -> -301737.5 | F100: =SUM(F92:F99) -> 59664.742 | G100: =SUM(G92:G99) -> 62204.14 | H100: =SUM(H92:H99) -> 64819.011 | I100: =SUM(I92:I99) -> 67511.595 | J100: =SUM(J92:J99) -> 70284.196 | K100: =SUM(K92:K99) -> 73139.189 | L100: =SUM(L92:L99) -> 76079.017 | ... P100: =SUM(P92:P99) -> 2337556
B102: After tax IRR | D102: =IRR(E100:P100) -> 0.32190663
B103: After tax NPV | D103: =NPV(After_tax_discount_rate,E100:P100)/(1+After_tax_discount_rate) -> 886853.22

Sheet Loan Amortization Schedule
B2: The Loan Amortization Schedule
B4: Month | C4: Payment | D4: Interest | E4: Principal | F4: Balance
B6: 1 | C6: ='RE Model'!$E$25 -> -3805.6537 | D6: =-Loan_Amount*Loan_interest_rate/12 -> -2471.875 | E6: =C6-D6 -> -1333.7787 | F6: =Loan_Amount+E6 -> 846166.22
B7: 2 | C7: =IF(B7<=loan_term,C6,0) -> -3805.6537 | D7: =-F6*Loan_interest_rate/12 -> -2467.9848 | E7: =C7-D7 -> -1337.6689 | F7: =F6+E7 -> 844828.55
B8: 3 | C8: =IF(B8<=loan_term,C7,0) -> -3805.6537 | D8: =-F7*Loan_interest_rate/12 -> -2464.0833 | E8: =C8-D8 -> -1341.5705 | F8: =F7+E8 -> 843486.98
B9: 4 | C9: =IF(B9<=loan_term,C8,0) -> -3805.6537 | D9: =-F8*Loan_interest_rate/12 -> -2460.1704 | E9: =C9-D9 -> -1345.4834 | F9: =F8+E9 -> 842141.5
B10: 5 | C10: =IF(B10<=loan_term,C9,0) -> -3805.6537 | D10: =-F9*Loan_interest_rate/12 -> -2456.246 | E10: =C10-D10 -> -1349.4077 | F10: =F9+E10 -> 840792.09
B11: 6 | C11: =IF(B11<=loan_term,C10,0) -> -3805.6537 | D11: =-F10*Loan_interest_rate/12 -> -2452.3103 | E11: =C11-D11 -> -1353.3435 | F11: =F10+E11 -> 839438.75
B12: 7 | C12: =IF(B12<=loan_term,C11,0) -> -3805.6537 | D12: =-F11*Loan_interest_rate/12 -> -2448.363 | E12: =C12-D12 -> -1357.2907 | F12: =F11+E12 -> 838081.46
B13: 8 | C13: =IF(B13<=loan_term,C12,0) -> -3805.6537 | D13: =-F12*Loan_interest_rate/12 -> -2444.4042 | E13: =C13-D13 -> -1361.2495 | F13: =F12+E13 -> 836720.21
B14: 9 | C14: =IF(B14<=loan_term,C13,0) -> -3805.6537 | D14: =-F13*Loan_interest_rate/12 -> -2440.4339 | E14: =C14-D14 -> -1365.2198 | F14: =F13+E14 -> 835354.99
B15: 10 | C15: =IF(B15<=loan_term,C14,0) -> -3805.6537 | D15: =-F14*Loan_interest_rate/12 -> -2436.452 | E15: =C15-D15 -> -1369.2017 | F15: =F14+E15 -> 833985.79
B16: 11 | C16: =IF(B16<=loan_term,C15,0) -> -3805.6537 | D16: =-F15*Loan_interest_rate/12 -> -2432.4585 | E16: =C16-D16 -> -1373.1952 | F16: =F15+E16 -> 832612.59
B17: 12 | C17: =IF(B17<=loan_term,C16,0) -> -3805.6537 | D17: =-F16*Loan_interest_rate/12 -> -2428.4534 | E17: =C17-D17 -> -1377.2003 | F17: =F16+E17 -> 831235.39
B18: 13 | C18: =IF(B18<=loan_term,C17,0) -> -3805.6537 | D18: =-F17*Loan_interest_rate/12 -> -2424.4366 | E18: =C18-D18 -> -1381.2172 | F18: =F17+E18 -> 829854.17
... B365: 360 | C365: =IF(B365<=loan_term,C364,0) -> -3805.6537 | D365: =-F364*Loan_interest_rate/12 -> -11.067543 | E365: =C365-D365 -> -3794.5862 | F365: =F364+E365 -> 9.3677954e-10
